Workbook
Name Division: '[1]Not Available'!$B$2:$B$7
Name Division: 'Not Available'!$B$2:$B$7
Name Status: '[1]Not Available'!$B$10:$B$13
Name Status: 'Not Available'!$B$10:$B$13
Name Status: 'Not Available'!$B$10:$B$13

Sheet 説明
A2: ① | B2: 案件．要員情報シートについて
B3: ▲今月のため対応された各案件、プロジェクト管理と他のテストの計画と実績人間を報告することです。 | K3: ※ | L3: メモ
B4: 列名の説明 | C4: 列名 | D4: 内容 | L4: 今週⇒ | M4: 「先週の定例会の日から今週の水曜日までのカウント」
C5: No.列 | D5: 連番 | L5: 来週⇒ | M5: 「今週の定例会の日から来週の水曜日までのカウント」
C6: ステータス | D6: 案件のステータス「未着手、進行中、レビュー待ち、完了」
C7: 区分 | D7: 案件のカテゴリー | L7: ・11月の計画工数の作成方法の説明
C8: DIR 担当 | D8: 案件依頼しているDIR担当者名 | L8: ・11月の計画工数と実績工数の差異の理由
C9: 案件管理コード（DAT) | D9: DAT側でのWBS管理コード | L9: ・12月の計画工数（案件毎の内訳情報も）および過不足工数の説明
C10: 案件管理コード（DIR) | D10: DIR側からの管理コード
C11: 案件 | D11: 今週中対応された案件名
C12: 備考 | D12: リマーク
J14: http://w3ttsvn10/svn/webbroker3_pr/ミャンマーDAT/30_見積り依頼/オンライン開発(2022年9月~2023年2月)についての見積書.xlsx
B15: 案件の計画工数作成方法の説明 | C15: 案件名 | D15: 計画工数作成方法
C16: 定型案件 | D16: WBSを参考し、案件の範囲とメンバーのスキルに依存して作成しています。
C17: (全社)脆弱性対応（2022年）_パス・トラバーサル対応 | D17: ◆他のプロジェクトにはFASE Formを提出して対応するプロジェクトがあります。しかし、WB4にはありません。プロジェクトの計画をPMが上記のことなどを向けて作成しています。
D18: ◆「(全社)脆弱性対応（2022年）_パス・トラバーサル対応」は徳田様が9月から12月まで各月に４人間として企画しました。
D19: ◆DIRと月次会議後には、サービス機能テストもする可能性がありますので、イェさんが２月まで各月に４人間として企画しました。 (9月~2月)の計画人間⇒25.18 各月の計画人間 ⇒ 4.19 (25.18/6)
B21: 計画工数と実績工数の差異の理由 | C21: 案件名 | D21: 理由
C22: 定型案件と (全社)脆弱性対応（2022年）_パス・トラバーサル対応 | D22: ◆DIRから計画を立っていないし、PMが自分で計画したので異なりました。
D23: ◆仕事がありますが、様々な理由で (エラーが発生など)停止しているので異なりました。 ◆仕事が止まる時、メンバーのスキルアップのため研修しています。
B25: ▲DATメンバーが対応しているプロジェクト管理タスクは６つあります。
B27: プロジェクト管理の計画工数作成方法の説明 | C27: タスク名 | D27: 計画工数作成方法
C28: DATチーム会議 | D28: ◆毎日30分(0.5 hr)かかります。 ◆全メンバーが出席しています。 ◆一人⇒(0.5 x Working Day)
C29: DIRとの定例会 | D29: ◆毎週1時間かかります。 ◆全メンバーが出席しています。 ◆一人⇒(１ x week count of a month)
C30: 日次報告書 | D30: ◆DATの社内システム(WHM)とThincの日次報告書に報告記入する時間です。 ◆毎日30分(0.5 hr)かかります。 ◆全メンバーがやっています。 ◆一人⇒(0.5 x Working Day)
C31: 週次報告 | D31: ◆毎週の水曜日DIRへ送信する週次報告作成時間と毎週の金曜日DAT管理人送信する週次報告作成時間 ◆毎週３時間かかります。 ◆PMだけやっています。 ◆一人⇒(0.5 x Working Day)
C32: プロジェクト管理、メール送受信、WBS管理、Redmine管理 | D32: ◆メール送受信時間、WBS作成時間、Redmine管理時間と他の報告作成時間です。 ◆毎日PMは３時間、二人のリーダーは30分かかる。 ◆(3 x Working Day)+(0.5 x Working Day)+(0.5 x Working Day)
C33: メンバーサポート | D33: ◆PMとリーダーが他のメンバーにサポートする時間です。 ◆毎日PMと二人のリーダーは1時間かかる。 ◆(1 x Working Day)+(1 x Working Day)+(1 x Working Day)
B35: 計画工数と実績工数の差異の理由 | C35: 案件名 | D35: 理由
C36: DATチーム会議 | D36: いつものは計画と実績が合っています。
C37: DIRとの定例会 | D37: 計画は1時間ですが、実際は30分以下かかるので 異なりました。
C38: 日次報告書 | D38: いつものは計画と実績が合っています。
C39: 週次報告 | D39: 計画を記入していますが、実績は計算する時には下記のプロジェクト管理テクストに追加して計算しています。 そして、週次報告の実績は'0'になっています。
C40: プロジェクト管理、メール送受信、WBS管理、Redmine管理 | D40: ◆毎日PMのため３時間として予定されていますが、週次報告作成時間を追加し、他の管理タスクがあるため計画と実績が異なります。 ◆毎日二人のリーダーのため30分として予定されていますが、管理タクスがない日もあるので計画と実績が異なります。
C41: メンバーサポート | D41: メンバーはサポートが不要な日もあるので計画と実績が異なります。
B43: ▲その他のタクスには案件と管理以外のタクス例えばJinwa研修やDAT社内作業などのタクスです。
B45: プロジェクト管理の計画工数作成方法の説明 | C45: タスク名 | D45: 計画工数作成方法
C46: WB4 Internal Training | D46: 新入社員がいる月には計画を作成しています。 今は新入社員がいないので計画は０になりました。
C47: JINWA Training(Class Hours) | D47: DATの社内報告書の計画時間と合わせるため、計画が０になりました。
C48: JINWA Training(Practicals) | D48: ◆メンバー４人が毎日3時間対応しています。 ◆一人⇒(３x Working Day)
C49: 開発レベル②、開発レベル③ | D49: ◆Offshore 証明書のためやっているタクスです。 ◆毎日は２時間かかります。 ◆11月にはメンバー５人が開発レベルのタクスを対応しています。 ◆一人⇒(２ x Working Day)
C50: DAT社内作業、DATエベント、トレーニング等 | D50: 計画が計算できないので、０になりました。
C51: 休暇 | D51: 休暇の計画が計算できないので、０になりました。
B53: 計画工数と実績工数の差異の理由 | C53: 案件名 | D53: 理由
C54: WB4 Internal Training | D54: 今は新入社員がいないので計画は０ですが、案件がない時は後輩メンバーがスキルアップのため過去定型案件やエラーメッセージ修正とかをやっていますので計画と実績が異なります。
C55: JINWA Training(Class Hours) | D55: 11月には授業時間が1日あるので計画と実績が異なります。
C56: JINWA Training(Practicals) | D56: 案件がない時にもJinwa研修を対応しているので計画と実績が異なります。
C57: 開発レベル②、開発レベル③ | D57: いつものは計画と実績が合っています。
C58: DAT社内作業、DATエベント、トレーニング等 | D58: 11月にはDIRの社長と会議があるし、社内トレーニング(C トレーニング)があるので計画と実績が異なります。
C59: 休暇 | D59: 11月にはイェさんは８日と18日に休暇を取ったので計画と実績が異なります。
A62: ② | B62: 週次報告シートについて
B63: ▲今週のため対応された案件などをリストアップして内訳として説明を報告することです。
B64: 列名の説明 | C64: 列名 | D64: 内容
C65: No.列 | D65: 連番
C66: DIR担当 | D66: 案件依頼しているDIR担当者名
C67: 案件管理コード（DAT) | D67: DAT側でのWBS管理コード
C68: 案件管理コード（DIR) | D68: DIR側からの管理コード
C69: 案件 | D69: 今週中対応された案件名
C70: 日付[F] | D70: 今回の期間
C71: 日付[G] | D71: 来週の期間
B73: ▲大体プロジェクトの種類として四つあります。報告スタイルは下記の通りになります。
B74: 定型案件 | C74: 開発の流れ | D74: ステータス
C75: 調査と開発 | D75: 未着手、進行中、レビュー待ち、完了
C76: 結合テスト | D76: 未着手、進行中、レビュー待ち、完了
C77: UPDATE用資料 | D77: 未着手、進行中、レビュー待ち、完了
C78: poptreeチェック | D78: 未着手、進行中、レビュー待ち、完了
B80: バッチ開発作業 | C80: 開発の流れ | D80: ステータス
C81: 基本設計 | D81: 未着手、進行中、レビュー待ち、完了
C82: 詳細設計 | D82: 未着手、進行中、レビュー待ち、完了
C83: コード開発 | D83: 未着手、進行中、レビュー待ち、完了
C84: 単体テスト | D84: 未着手、進行中、レビュー待ち、完了
C85: 総合テスト | D85: 未着手、進行中、レビュー待ち、完了
C86: UPDATE用資料 | D86: 未着手、進行中、レビュー待ち、完了
C87: poptreeチェック | D87: 未着手、進行中、レビュー待ち、完了
B89: アドホックのタスク | C89: 開発の流れ | D89: ステータス
C90: 要件確認 | D90: 未着手、進行中、レビュー待ち、完了
C91: 調査と開発 | D91: 未着手、進行中、レビュー待ち、完了
C92: 単体テスト | D92: 未着手、進行中、レビュー待ち、完了
C93: 結合テスト | D93: 未着手、進行中、レビュー待ち、完了
C94: 総合テスト | D94: 未着手、進行中、レビュー待ち、完了
C95: UPDATE用資料 | D95: 未着手、進行中、レビュー待ち、完了
C96: poptreeチェック | D96: 未着手、進行中、レビュー待ち、完了
B98: PR案件 | C98: 開発の流れ | D98: ステータス
C99: 要件確認 | D99: 未着手、進行中、レビュー待ち、完了
C100: 調査と開発 | D100: 未着手、進行中、レビュー待ち、完了
C101: 単体テスト | D101: 未着手、進行中、レビュー待ち、完了
C102: 結合テスト | D102: 未着手、進行中、レビュー待ち、完了
C103: UPDATE用資料 | D103: 未着手、進行中、レビュー待ち、完了
C104: poptreeチェック | D104: 未着手、進行中、レビュー待ち、完了
A106: ③ | B106: 休暇シートについて
B107: ▲今週、来週のためWB4チームメンバーの休暇情報を報告することです。
B108: テーブルの説明 | C108: 略語 | D108: 説明
C109: A | D109: 出勤
C110: L | D110: 休暇
C111: HL | D111: 半休
C112: H | D112: 祝日
C113: S | D113: 土曜日、日曜日
C114: YTN | D114: メンバー名の略語
C115: L-Days | D115: 総休暇日数
C116: Actual Working Days | D116: 総実稼働日数
...

Sheet 案件．要員情報まとめ
A1: 案件．要員情報 | S1: Total Member -7 | W1: Contract Member - 5
S2: FOC Member - 2
A3: ■案件
A4: No. | B4: ステータス | C4: 区分 | D4: DIR 担当 | E4: 案件管理コード（DAT) | F4: 案件管理コード（DIR) | G4: 案件 | H4: 計画 (DIR) | I4: 計画 (DAT) | J4: 実績 | K4: 着手日 | L4: 完了日 | M4: 備考/理由 | N4: 工数（人月）
O5: 4月 | P5: 5月 | Q5: 6月 | R5: 7月 | S5: 8月 | T5: 9月 | U5: 10月 | V5: 11月 | W5: 12月 | X5: 1月 | Y5: 2月 | Z5: 3月
A6: 1 | B6: 着手中 | C6: その他 | D6: 飯田 | E6: BW1 | F6: A5207110 | G6: 【案件依頼】ビルド作業を対応 | N6: 計画 | O6: =SUM('案件．要員情報'!O7:X7) -> 0.7 | P6: =SUM('案件．要員情報'!Y7:AH7) -> 0.44444444 | Q6: =SUM('案件．要員情報'!AI7:AR7) -> 0.39365079 | R6: =SUM('案件．要員情報'!AS7:BB7) -> 0.42424242 | S6: =SUM('案件．要員情報'!BC7:BL7) -> 0.66666667 | T6: =SUM('案件．要員情報'!BM7:BV7) -> 0.42424242 | U6: =SUM('案件．要員情報'!BW7:CF7) -> 0.4 | V6: =SUM('案件．要員情報'!CG7:CP7) -> 0.2962963 | W6: =SUM('案件．要員情報'!CQ7:CW7) -> 0.23333333 | X6: =SUM('案件．要員情報'!CX7:DD7) -> 0.28571429 | Y6: =SUM('案件．要員情報'!DE7:DK7) -> 0.47058824 | Z6: =SUM('案件．要員情報'!DL7:DS7) -> 0 | AA6: =SUM(O6:Z6) -> 4.7391789
N7: 実績 | O7: =SUM('案件．要員情報'!O8:X8) -> 0.64583333 | P7: =SUM('案件．要員情報'!Y8:AH8) -> 0.4031746 | Q7: =SUM('案件．要員情報'!AI8:AR8) -> 0.37777778 | R7: =SUM('案件．要員情報'!AS8:BB8) -> 0.38787879 | S7: =SUM('案件．要員情報'!BC8:BL8) -> 0.66031746 | T7: =SUM('案件．要員情報'!BM8:BV8) -> 0.36666667 | U7: =SUM('案件．要員情報'!BW8:CF8) -> 0.39666667 | V7: =SUM('案件．要員情報'!CG8:CP8) -> 0.21851852 | W7: =SUM('案件．要員情報'!CQ8:CW8) -> 0.21333333 | X7: =SUM('案件．要員情報'!CX8:DD8) -> 0.26349206 | Y7: =SUM('案件．要員情報'!DE8:DK8) -> 0.24313725 | Z7: =SUM('案件．要員情報'!DL8:DS8) -> 0 | AA7: =SUM(O7:Z7) -> 4.1767965
A8: 2 | B8: 完了 | C8: その他 | D8: 坂野 | E8: PL6 | F8: PBxxxxxxxx | G8: 【PLATE】対面WEB_初期フォーカス改善対応 | N8: 計画 | O8: =SUM('案件．要員情報'!O9:X9) -> 0 | P8: =SUM('案件．要員情報'!Y9:AH9) -> 0 | Q8: =SUM('案件．要員情報'!AI9:AR9) -> 0 | R8: =SUM('案件．要員情報'!AS9:BB9) -> 0 | S8: =SUM('案件．要員情報'!BC9:BL9) -> 0 | T8: =SUM('案件．要員情報'!BM9:BV9) -> 0 | U8: =SUM('案件．要員情報'!BW9:CF9) -> 0 | V8: =SUM('案件．要員情報'!CG9:CP9) -> 0 | W8: =SUM('案件．要員情報'!CQ9:CW9) -> 0 | X8: =SUM('案件．要員情報'!CX9:DD9) -> 0 | Y8: =SUM('案件．要員情報'!DE9:DK9) -> 0 | Z8: =SUM('案件．要員情報'!DL9:DS9) -> 0 | AA8: =SUM(O8:Z8) -> 0
N9: 実績 | O9: =SUM('案件．要員情報'!O10:X10) -> 0 | P9: =SUM('案件．要員情報'!Y10:AH10) -> 0 | Q9: =SUM('案件．要員情報'!AI10:AR10) -> 0 | R9: =SUM('案件．要員情報'!AS10:BB10) -> 0 | S9: =SUM('案件．要員情報'!BC10:BL10) -> 0 | T9: =SUM('案件．要員情報'!BM10:BV10) -> 0 | U9: =SUM('案件．要員情報'!BW10:CF10) -> 0 | V9: =SUM('案件．要員情報'!CG10:CP10) -> 0 | W9: =SUM('案件．要員情報'!CQ10:CW10) -> 0 | X9: =SUM('案件．要員情報'!CX10:DD10) -> 0 | Y9: =SUM('案件．要員情報'!DE10:DK10) -> 0 | Z9: =SUM('案件．要員情報'!DL10:DS10) -> 0 | AA9: =SUM(O9:Z9) -> 0
A10: 3 | B10: 完了 | C10: その他 | D10: 山本 | E10: WA2 | G10: 【開発依頼】作業の自動化_UATヘルスチェック | N10: 計画 | O10: =SUM('案件．要員情報'!O11:X11) -> 1.3083333 | P10: =SUM('案件．要員情報'!Y11:AH11) -> 1.968254 | Q10: =SUM('案件．要員情報'!AI11:AR11) -> 0.019047619 | R10: =SUM('案件．要員情報'!AS11:BB11) -> 0.45454545 | S10: =SUM('案件．要員情報'!BC11:BL11) -> 0.28571429 | T10: =SUM('案件．要員情報'!BM11:BV11) -> 0.60606061 | U10: =SUM('案件．要員情報'!BW11:CF11) -> 0.3 | V10: =SUM('案件．要員情報'!CG11:CP11) -> 0 | W10: =SUM('案件．要員情報'!CQ11:CW11) -> 0 | X10: =SUM('案件．要員情報'!CX11:DD11) -> 0 | Y10: =SUM('案件．要員情報'!DE11:DK11) -> 0 | Z10: =SUM('案件．要員情報'!DL11:DS11) -> 0 | AA10: =SUM(O10:Z10) -> 4.9419553
N11: 実績 | O11: =SUM('案件．要員情報'!O12:X12) -> 1.2708333 | P11: =SUM('案件．要員情報'!Y12:AH12) -> 1.9492063 | Q11: =SUM('案件．要員情報'!AI12:AR12) -> 0.015873016 | R11: =SUM('案件．要員情報'!AS12:BB12) -> 0.43636364 | S11: =SUM('案件．要員情報'!BC12:BL12) -> 0.26031746 | T11: =SUM('案件．要員情報'!BM12:BV12) -> 0.61818182 | U11: =SUM('案件．要員情報'!BW12:CF12) -> 0.28666667 | V11: =SUM('案件．要員情報'!CG12:CP12) -> 0 | W11: =SUM('案件．要員情報'!CQ12:CW12) -> 0 | X11: =SUM('案件．要員情報'!CX12:DD12) -> 0 | Y11: =SUM('案件．要員情報'!DE12:DK12) -> 0 | Z11: =SUM('案件．要員情報'!DL12:DS12) -> 0 | AA11: =SUM(O11:Z11) -> 4.8374423
A12: 4 | B12: 完了 | C12: 定型 | D12: 山本 | E12: F180 | F12: PB00201841 | G12: 【定型】定時定額の注文画面での文言追加 | N12: 計画 | O12: =SUM('案件．要員情報'!O13:X13) -> 0.15 | P12: =SUM('案件．要員情報'!Y13:AH13) -> 0 | Q12: =SUM('案件．要員情報'!AI13:AR13) -> 0 | R12: =SUM('案件．要員情報'!AS13:BB13) -> 0 | S12: =SUM('案件．要員情報'!BC13:BL13) -> 0 | T12: =SUM('案件．要員情報'!BM13:BV13) -> 0 | U12: =SUM('案件．要員情報'!BW13:CF13) -> 0 | V12: =SUM('案件．要員情報'!CG13:CP13) -> 0 | W12: =SUM('案件．要員情報'!CQ13:CW13) -> 0 | X12: =SUM('案件．要員情報'!CX13:DD13) -> 0 | Y12: =SUM('案件．要員情報'!DE13:DK13) -> 0 | Z12: =SUM('案件．要員情報'!DL13:DS13) -> 0 | AA12: =SUM(O12:Z12) -> 0.15
N13: 実績 | O13: =SUM('案件．要員情報'!O14:X14) -> 0.14166667 | P13: =SUM('案件．要員情報'!Y14:AH14) -> 0 | Q13: =SUM('案件．要員情報'!AI14:AR14) -> 0 | R13: =SUM('案件．要員情報'!AS14:BB14) -> 0 | S13: =SUM('案件．要員情報'!BC14:BL14) -> 0 | T13: =SUM('案件．要員情報'!BM14:BV14) -> 0 | U13: =SUM('案件．要員情報'!BW14:CF14) -> 0 | V13: =SUM('案件．要員情報'!CG14:CP14) -> 0 | W13: =SUM('案件．要員情報'!CQ14:CW14) -> 0 | X13: =SUM('案件．要員情報'!CX14:DD14) -> 0 | Y13: =SUM('案件．要員情報'!DE14:DK14) -> 0 | Z13: =SUM('案件．要員情報'!DL14:DS14) -> 0 | AA13: =SUM(O13:Z13) -> 0.14166667
A14: 5 | B14: 完了 | C14: 定型 | D14: 山田 | E14: F181 | F14: PB00201845 | G14: 【定型】CFDサービス終了に伴う画面修正 | N14: 計画 | O14: =SUM('案件．要員情報'!O15:X15) -> 0.29166667 | P14: =SUM('案件．要員情報'!Y15:AH15) -> 0 | Q14: =SUM('案件．要員情報'!AI15:AR15) -> 0 | R14: =SUM('案件．要員情報'!AS15:BB15) -> 0 | S14: =SUM('案件．要員情報'!BC15:BL15) -> 0 | T14: =SUM('案件．要員情報'!BM15:BV15) -> 0 | U14: =SUM('案件．要員情報'!BW15:CF15) -> 0 | V14: =SUM('案件．要員情報'!CG15:CP15) -> 0 | W14: =SUM('案件．要員情報'!CQ15:CW15) -> 0 | X14: =SUM('案件．要員情報'!CX15:DD15) -> 0 | Y14: =SUM('案件．要員情報'!DE15:DK15) -> 0 | Z14: =SUM('案件．要員情報'!DL15:DS15) -> 0 | AA14: =SUM(O14:Z14) -> 0.29166667
N15: 実績 | O15: =SUM('案件．要員情報'!O16:X16) -> 0.28333333 | P15: =SUM('案件．要員情報'!Y16:AH16) -> 0 | Q15: =SUM('案件．要員情報'!AI16:AR16) -> 0 | R15: =SUM('案件．要員情報'!AS16:BB16) -> 0 | S15: =SUM('案件．要員情報'!BC16:BL16) -> 0 | T15: =SUM('案件．要員情報'!BM16:BV16) -> 0 | U15: =SUM('案件．要員情報'!BW16:CF16) -> 0 | V15: =SUM('案件．要員情報'!CG16:CP16) -> 0 | W15: =SUM('案件．要員情報'!CQ16:CW16) -> 0 | X15: =SUM('案件．要員情報'!CX16:DD16) -> 0 | Y15: =SUM('案件．要員情報'!DE16:DK16) -> 0 | Z15: =SUM('案件．要員情報'!DL16:DS16) -> 0 | AA15: =SUM(O15:Z15) -> 0.28333333
A16: 6 | B16: 完了 | C16: 定型 | D16: 山田 | E16: F182 | F16: PB00201860 | G16: 【定型】WB4ログイン画面ロゴ画像の変更 | N16: 計画 | O16: =SUM('案件．要員情報'!O17:X17) -> 0.79166667 | P16: =SUM('案件．要員情報'!Y17:AH17) -> 0 | Q16: =SUM('案件．要員情報'!AI17:AR17) -> 0 | R16: =SUM('案件．要員情報'!AS17:BB17) -> 0 | S16: =SUM('案件．要員情報'!BC17:BL17) -> 0 | T16: =SUM('案件．要員情報'!BM17:BV17) -> 0 | U16: =SUM('案件．要員情報'!BW17:CF17) -> 0 | V16: =SUM('案件．要員情報'!CG17:CP17) -> 0 | W16: =SUM('案件．要員情報'!CQ17:CW17) -> 0 | X16: =SUM('案件．要員情報'!CX17:DD17) -> 0 | Y16: =SUM('案件．要員情報'!DE17:DK17) -> 0 | Z16: =SUM('案件．要員情報'!DL17:DS17) -> 0 | AA16: =SUM(O16:Z16) -> 0.79166667
N17: 実績 | O17: =SUM('案件．要員情報'!O18:X18) -> 0.77916667 | P17: =SUM('案件．要員情報'!Y18:AH18) -> 0 | Q17: =SUM('案件．要員情報'!AI18:AR18) -> 0 | R17: =SUM('案件．要員情報'!AS18:BB18) -> 0 | S17: =SUM('案件．要員情報'!BC18:BL18) -> 0 | T17: =SUM('案件．要員情報'!BM18:BV18) -> 0 | U17: =SUM('案件．要員情報'!BW18:CF18) -> 0 | V17: =SUM('案件．要員情報'!CG18:CP18) -> 0 | W17: =SUM('案件．要員情報'!CQ18:CW18) -> 0 | X17: =SUM('案件．要員情報'!CX18:DD18) -> 0 | Y17: =SUM('案件．要員情報'!DE18:DK18) -> 0 | Z17: =SUM('案件．要員情報'!DL18:DS18) -> 0 | AA17: =SUM(O17:Z17) -> 0.77916667
A18: 7 | B18: 完了 | C18: その他 | D18: 寺澤 | E18: MSC1 | G18: 【MSC】画面設計書最新化対応のお願い | N18: 計画 | O18: =SUM('案件．要員情報'!O19:X19) -> 0.70833333 | P18: =SUM('案件．要員情報'!Y19:AH19) -> 0 | Q18: =SUM('案件．要員情報'!AI19:AR19) -> 0 | R18: =SUM('案件．要員情報'!AS19:BB19) -> 0 | S18: =SUM('案件．要員情報'!BC19:BL19) -> 0 | T18: =SUM('案件．要員情報'!BM19:BV19) -> 0 | U18: =SUM('案件．要員情報'!BW19:CF19) -> 0 | V18: =SUM('案件．要員情報'!CG19:CP19) -> 0 | W18: =SUM('案件．要員情報'!CQ19:CW19) -> 0 | X18: =SUM('案件．要員情報'!CX19:DD19) -> 0 | Y18: =SUM('案件．要員情報'!DE19:DK19) -> 0 | Z18: =SUM('案件．要員情報'!DL19:DS19) -> 0 | AA18: =SUM(O18:Z18) -> 0.70833333
N19: 実績 | O19: =SUM('案件．要員情報'!O20:X20) -> 0.69583333 | P19: =SUM('案件．要員情報'!Y20:AH20) -> 0 | Q19: =SUM('案件．要員情報'!AI20:AR20) -> 0 | R19: =SUM('案件．要員情報'!AS20:BB20) -> 0 | S19: =SUM('案件．要員情報'!BC20:BL20) -> 0 | T19: =SUM('案件．要員情報'!BM20:BV20) -> 0 | U19: =SUM('案件．要員情報'!BW20:CF20) -> 0 | V19: =SUM('案件．要員情報'!CG20:CP20) -> 0 | W19: =SUM('案件．要員情報'!CQ20:CW20) -> 0 | X19: =SUM('案件．要員情報'!CX20:DD20) -> 0 | Y19: =SUM('案件．要員情報'!DE20:DK20) -> 0 | Z19: =SUM('案件．要員情報'!DL20:DS20) -> 0 | AA19: =SUM(O19:Z19) -> 0.69583333
A20: 8 | B20: 完了 | C20: その他 | D20: 田中 | E20: AH24 | G20: 【案件依頼】【ツール開発】シェルが稼働しているジョブネットの一覧作成 | N20: 計画 | O20: =SUM('案件．要員情報'!O21:X21) -> 1.75 | P20: =SUM('案件．要員情報'!Y21:AH21) -> 1.7142857 | Q20: =SUM('案件．要員情報'!AI21:AR21) -> 0 | R20: =SUM('案件．要員情報'!AS21:BB21) -> 0 | S20: =SUM('案件．要員情報'!BC21:BL21) -> 0 | T20: =SUM('案件．要員情報'!BM21:BV21) -> 0 | U20: =SUM('案件．要員情報'!BW21:CF21) -> 0 | V20: =SUM('案件．要員情報'!CG21:CP21) -> 0 | W20: =SUM('案件．要員情報'!CQ21:CW21) -> 0 | X20: =SUM('案件．要員情報'!CX21:DD21) -> 0 | Y20: =SUM('案件．要員情報'!DE21:DK21) -> 0 | Z20: =SUM('案件．要員情報'!DL21:DS21) -> 0 | AA20: =SUM(O20:Z20) -> 3.4642857
N21: 実績 | O21: =SUM('案件．要員情報'!O22:X22) -> 1.7416667 | P21: =SUM('案件．要員情報'!Y22:AH22) -> 1.6825397 | Q21: =SUM('案件．要員情報'!AI22:AR22) -> 0 | R21: =SUM('案件．要員情報'!AS22:BB22) -> 0 | S21: =SUM('案件．要員情報'!BC22:BL22) -> 0 | T21: =SUM('案件．要員情報'!BM22:BV22) -> 0 | U21: =SUM('案件．要員情報'!BW22:CF22) -> 0 | V21: =SUM('案件．要員情報'!CG22:CP22) -> 0 | W21: =SUM('案件．要員情報'!CQ22:CW22) -> 0 | X21: =SUM('案件．要員情報'!CX22:DD22) -> 0 | Y21: =SUM('案件．要員情報'!DE22:DK22) -> 0 | Z21: =SUM('案件．要員情報'!DL22:DS22) -> 0 | AA21: =SUM(O21:Z21) -> 3.4242063
A22: 9 | B22: 完了 | C22: その他 | D22: 田中 | E22: AH26 | G22: 【ツール開発】WB4結合環境の状況リスト一覧の作成 | N22: 計画 | O22: =SUM('案件．要員情報'!O23:X23) -> 0.91666667 | P22: =SUM('案件．要員情報'!Y23:AH23) -> 0.095238095 | Q22: =SUM('案件．要員情報'!AI23:AR23) -> 0 | R22: =SUM('案件．要員情報'!AS23:BB23) -> 0 | S22: =SUM('案件．要員情報'!BC23:BL23) -> 0 | T22: =SUM('案件．要員情報'!BM23:BV23) -> 0 | U22: =SUM('案件．要員情報'!BW23:CF23) -> 0 | V22: =SUM('案件．要員情報'!CG23:CP23) -> 0 | W22: =SUM('案件．要員情報'!CQ23:CW23) -> 0 | X22: =SUM('案件．要員情報'!CX23:DD23) -> 0 | Y22: =SUM('案件．要員情報'!DE23:DK23) -> 0 | Z22: =SUM('案件．要員情報'!DL23:DS23) -> 0 | AA22: =SUM(O22:Z22) -> 1.0119048
N23: 実績 | O23: =SUM('案件．要員情報'!O24:X24) -> 0.85 | P23: =SUM('案件．要員情報'!Y24:AH24) -> 0.082539683 | Q23: =SUM('案件．要員情報'!AI24:AR24) -> 0 | R23: =SUM('案件．要員情報'!AS24:BB24) -> 0 | S23: =SUM('案件．要員情報'!BC24:BL24) -> 0 | T23: =SUM('案件．要員情報'!BM24:BV24) -> 0 | U23: =SUM('案件．要員情報'!BW24:CF24) -> 0 | V23: =SUM('案件．要員情報'!CG24:CP24) -> 0 | W23: =SUM('案件．要員情報'!CQ24:CW24) -> 0 | X23: =SUM('案件．要員情報'!CX24:DD24) -> 0 | Y23: =SUM('案件．要員情報'!DE24:DK24) -> 0 | Z23: =SUM('案件．要員情報'!DL24:DS24) -> 0 | AA23: =SUM(O23:Z23) -> 0.93253968
A24: 10 | B24: 完了 | C24: 定型 | D24: 谷口 | E24: F183 | F24: PB00201788 | G24: 【定型】(53)820部店の対面WEB利用 | N24: 計画 | O24: =SUM('案件．要員情報'!O25:X25) -> 0.16666667 | P24: =SUM('案件．要員情報'!Y25:AH25) -> 0.057142857 | Q24: =SUM('案件．要員情報'!AI25:AR25) -> 0 | R24: =SUM('案件．要員情報'!AS25:BB25) -> 0 | S24: =SUM('案件．要員情報'!BC25:BL25) -> 0 | T24: =SUM('案件．要員情報'!BM25:BV25) -> 0 | U24: =SUM('案件．要員情報'!BW25:CF25) -> 0 | V24: =SUM('案件．要員情報'!CG25:CP25) -> 0 | W24: =SUM('案件．要員情報'!CQ25:CW25) -> 0 | X24: =SUM('案件．要員情報'!CX25:DD25) -> 0 | Y24: =SUM('案件．要員情報'!DE25:DK25) -> 0 | Z24: =SUM('案件．要員情報'!DL25:DS25) -> 0 | AA24: =SUM(O24:Z24) -> 0.22380952
N25: 実績 | O25: =SUM('案件．要員情報'!O26:X26) -> 0.15 | P25: =SUM('案件．要員情報'!Y26:AH26) -> 0.050793651 | Q25: =SUM('案件．要員情報'!AI26:AR26) -> 0 | R25: =SUM('案件．要員情報'!AS26:BB26) -> 0 | S25: =SUM('案件．要員情報'!BC26:BL26) -> 0 | T25: =SUM('案件．要員情報'!BM26:BV26) -> 0 | U25: =SUM('案件．要員情報'!BW26:CF26) -> 0 | V25: =SUM('案件．要員情報'!CG26:CP26) -> 0 | W25: =SUM('案件．要員情報'!CQ26:CW26) -> 0 | X25: =SUM('案件．要員情報'!CX26:DD26) -> 0 | Y25: =SUM('案件．要員情報'!DE26:DK26) -> 0 | Z25: =SUM('案件．要員情報'!DL26:DS26) -> 0 | AA25: =SUM(O25:Z25) -> 0.20079365
A26: 11 | B26: 完了 | C26: 定型 | D26: 邵 | E26: F184 | F26: PB00201870 | G26: 【定型】（信用）担保処分に関する文言変更 | N26: 計画 | O26: =SUM('案件．要員情報'!O27:X27) -> 0.55 | P26: =SUM('案件．要員情報'!Y27:AH27) -> 0.012698413 | Q26: =SUM('案件．要員情報'!AI27:AR27) -> 0 | R26: =SUM('案件．要員情報'!AS27:BB27) -> 0 | S26: =SUM('案件．要員情報'!BC27:BL27) -> 0 | T26: =SUM('案件．要員情報'!BM27:BV27) -> 0 | U26: =SUM('案件．要員情報'!BW27:CF27) -> 0 | V26: =SUM('案件．要員情報'!CG27:CP27) -> 0 | W26: =SUM('案件．要員情報'!CQ27:CW27) -> 0 | X26: =SUM('案件．要員情報'!CX27:DD27) -> 0 | Y26: =SUM('案件．要員情報'!DE27:DK27) -> 0 | Z26: =SUM('案件．要員情報'!DL27:DS27) -> 0 | AA26: =SUM(O26:Z26) -> 0.56269841
N27: 実績 | O27: =SUM('案件．要員情報'!O28:X28) -> 0.525 | P27: =SUM('案件．要員情報'!Y28:AH28) -> 0.0063492063 | Q27: =SUM('案件．要員情報'!AI28:AR28) -> 0 | R27: =SUM('案件．要員情報'!AS28:BB28) -> 0 | S27: =SUM('案件．要員情報'!BC28:BL28) -> 0 | T27: =SUM('案件．要員情報'!BM28:BV28) -> 0 | U27: =SUM('案件．要員情報'!BW28:CF28) -> 0 | V27: =SUM('案件．要員情報'!CG28:CP28) -> 0 | W27: =SUM('案件．要員情報'!CQ28:CW28) -> 0 | X27: =SUM('案件．要員情報'!CX28:DD28) -> 0 | Y27: =SUM('案件．要員情報'!DE28:DK28) -> 0 | Z27: =SUM('案件．要員情報'!DL28:DS28) -> 0 | AA27: =SUM(O27:Z27) -> 0.53134921
A28: 12 | B28: 完了 | C28: その他 | D28: 田中 | E28: AH21 | G28: 【ツール開発】HULFTログからの一覧作成 | N28: 計画 | O28: =SUM('案件．要員情報'!O29:X29) -> 0.091666667 | P28: =SUM('案件．要員情報'!Y29:AH29) -> 0 | Q28: =SUM('案件．要員情報'!AI29:AR29) -> 0 | R28: =SUM('案件．要員情報'!AS29:BB29) -> 0 | S28: =SUM('案件．要員情報'!BC29:BL29) -> 0 | T28: =SUM('案件．要員情報'!BM29:BV29) -> 0 | U28: =SUM('案件．要員情報'!BW29:CF29) -> 0 | V28: =SUM('案件．要員情報'!CG29:CP29) -> 0 | W28: =SUM('案件．要員情報'!CQ29:CW29) -> 0 | X28: =SUM('案件．要員情報'!CX29:DD29) -> 0 | Y28: =SUM('案件．要員情報'!DE29:DK29) -> 0 | Z28: =SUM('案件．要員情報'!DL29:DS29) -> 0 | AA28: =SUM(O28:Z28) -> 0.091666667
N29: 実績 | O29: =SUM('案件．要員情報'!O30:X30) -> 0.070833333 | P29: =SUM('案件．要員情報'!Y30:AH30) -> 0 | Q29: =SUM('案件．要員情報'!AI30:AR30) -> 0 | R29: =SUM('案件．要員情報'!AS30:BB30) -> 0 | S29: =SUM('案件．要員情報'!BC30:BL30) -> 0 | T29: =SUM('案件．要員情報'!BM30:BV30) -> 0 | U29: =SUM('案件．要員情報'!BW30:CF30) -> 0 | V29: =SUM('案件．要員情報'!CG30:CP30) -> 0 | W29: =SUM('案件．要員情報'!CQ30:CW30) -> 0 | X29: =SUM('案件．要員情報'!CX30:DD30) -> 0 | Y29: =SUM('案件．要員情報'!DE30:DK30) -> 0 | Z29: =SUM('案件．要員情報'!DL30:DS30) -> 0 | AA29: =SUM(O29:Z29) -> 0.070833333
A30: 13 | B30: 完了 | C30: その他 | D30: 安藤 | E30: WA1 | G30: 【WB4】【開発依頼】作業の自動化 | N30: 計画 | O30: =SUM('案件．要員情報'!O31:X31) -> 0 | P30: =SUM('案件．要員情報'!Y31:AH31) -> 0.47619048 | Q30: =SUM('案件．要員情報'!AI31:AR31) -> 0.20952381 | R30: =SUM('案件．要員情報'!AS31:BB31) -> 0 | S30: =SUM('案件．要員情報'!BC31:BL31) -> 0 | T30: =SUM('案件．要員情報'!BM31:BV31) -> 0 | U30: =SUM('案件．要員情報'!BW31:CF31) -> 0 | V30: =SUM('案件．要員情報'!CG31:CP31) -> 0 | W30: =SUM('案件．要員情報'!CQ31:CW31) -> 0 | X30: =SUM('案件．要員情報'!CX31:DD31) -> 0 | Y30: =SUM('案件．要員情報'!DE31:DK31) -> 0 | Z30: =SUM('案件．要員情報'!DL31:DS31) -> 0 | AA30: =SUM(O30:Z30) -> 0.68571429
N31: 実績 | O31: =SUM('案件．要員情報'!O32:X32) -> 0 | P31: =SUM('案件．要員情報'!Y32:AH32) -> 0.39365079 | Q31: =SUM('案件．要員情報'!AI32:AR32) -> 0.2031746 | R31: =SUM('案件．要員情報'!AS32:BB32) -> 0 | S31: =SUM('案件．要員情報'!BC32:BL32) -> 0 | T31: =SUM('案件．要員情報'!BM32:BV32) -> 0 | U31: =SUM('案件．要員情報'!BW32:CF32) -> 0 | V31: =SUM('案件．要員情報'!CG32:CP32) -> 0 | W31: =SUM('案件．要員情報'!CQ32:CW32) -> 0 | X31: =SUM('案件．要員情報'!CX32:DD32) -> 0 | Y31: =SUM('案件．要員情報'!DE32:DK32) -> 0 | Z31: =SUM('案件．要員情報'!DL32:DS32) -> 0 | AA31: =SUM(O31:Z31) -> 0.5968254
A32: 14 | B32: 完了 | C32: その他 | D32: 谷口 | E32: WT11 | G32: 【開発依頼】Windows11動作検証 | N32: 計画 | O32: =SUM('案件．要員情報'!O33:X33) -> 0 | P32: =SUM('案件．要員情報'!Y33:AH33) -> 0.6031746 | Q32: =SUM('案件．要員情報'!AI33:AR33) -> 3.2777778 | R32: =SUM('案件．要員情報'!AS33:BB33) -> 2.5333333 | S32: =SUM('案件．要員情報'!BC33:BL33) -> 3.3015873 | T32: =SUM('案件．要員情報'!BM33:BV33) -> 0 | U32: =SUM('案件．要員情報'!BW33:CF33) -> 0 | V32: =SUM('案件．要員情報'!CG33:CP33) -> 0 | W32: =SUM('案件．要員情報'!CQ33:CW33) -> 0 | X32: =SUM('案件．要員情報'!CX33:DD33) -> 0 | Y32: =SUM('案件．要員情報'!DE33:DK33) -> 0 | Z32: =SUM('案件．要員情報'!DL33:DS33) -> 0 | AA32: =SUM(O32:Z32) -> 9.715873
N33: 実績 | O33: =SUM('案件．要員情報'!O34:X34) -> 0 | P33: =SUM('案件．要員情報'!Y34:AH34) -> 0.58095238 | Q33: =SUM('案件．要員情報'!AI34:AR34) -> 3.2698413 | R33: =SUM('案件．要員情報'!AS34:BB34) -> 2.4575758 | S33: =SUM('案件．要員情報'!BC34:BL34) -> 3.2888889 | T33: =SUM('案件．要員情報'!BM34:BV34) -> 0 | U33: =SUM('案件．要員情報'!BW34:CF34) -> 0 | V33: =SUM('案件．要員情報'!CG34:CP34) -> 0 | W33: =SUM('案件．要員情報'!CQ34:CW34) -> 0 | X33: =SUM('案件．要員情報'!CX34:DD34) -> 0 | Y33: =SUM('案件．要員情報'!DE34:DK34) -> 0 | Z33: =SUM('案件．要員情報'!DL34:DS34) -> 0 | AA33: =SUM(O33:Z33) -> 9.5972583
A34: 15 | B34: 完了 | C34: その他 | D34: 仲井 | E34: BT1 | G34: 【全社】プリファレンステーブルの設定値最新化対応 | N34: 計画 | O34: =SUM('案件．要員情報'!O35:X35) -> 0 | P34: =SUM('案件．要員情報'!Y35:AH35) -> 0.63492063 | Q34: =SUM('案件．要員情報'!AI35:AR35) -> 1.2634921 | R34: =SUM('案件．要員情報'!AS35:BB35) -> 0.84848485 | S34: =SUM('案件．要員情報'!BC35:BL35) -> 1.8412698 | T34: =SUM('案件．要員情報'!BM35:BV35) -> 0 | U34: =SUM('案件．要員情報'!BW35:CF35) -> 0 | V34: =SUM('案件．要員情報'!CG35:CP35) -> 0 | W34: =SUM('案件．要員情報'!CQ35:CW35) -> 0 | X34: =SUM('案件．要員情報'!CX35:DD35) -> 0 | Y34: =SUM('案件．要員情報'!DE35:DK35) -> 0 | Z34: =SUM('案件．要員情報'!DL35:DS35) -> 0 | AA34: =SUM(O34:Z34) -> 4.5881674
N35: 実績 | O35: =SUM('案件．要員情報'!O36:X36) -> 0 | P35: =SUM('案件．要員情報'!Y36:AH36) -> 0.61269841 | Q35: =SUM('案件．要員情報'!AI36:AR36) -> 1.247619 | R35: =SUM('案件．要員情報'!AS36:BB36) -> 0.87575758 | S35: =SUM('案件．要員情報'!BC36:BL36) -> 1.7111111 | T35: =SUM('案件．要員情報'!BM36:BV36) -> 0 | U35: =SUM('案件．要員情報'!BW36:CF36) -> 0 | V35: =SUM('案件．要員情報'!CG36:CP36) -> 0 | W35: =SUM('案件．要員情報'!CQ36:CW36) -> 0 | X35: =SUM('案件．要員情報'!CX36:DD36) -> 0 | Y35: =SUM('案件．要員情報'!DE36:DK36) -> 0 | Z35: =SUM('案件．要員情報'!DL36:DS36) -> 0 | AA35: =SUM(O35:Z35) -> 4.4471861
A36: 16 | B36: 完了 | C36: その他 | D36: 山本 | E36: BT2 | G36: (44)注文失効件数チェック処理の改善_横展開 | N36: 計画 | O36: =SUM('案件．要員情報'!O37:X37) -> 0 | P36: =SUM('案件．要員情報'!Y37:AH37) -> 0.31746032 | Q36: =SUM('案件．要員情報'!AI37:AR37) -> 0.43180952 | R36: =SUM('案件．要員情報'!AS37:BB37) -> 0 | S36: =SUM('案件．要員情報'!BC37:BL37) -> 0 | T36: =SUM('案件．要員情報'!BM37:BV37) -> 0 | U36: =SUM('案件．要員情報'!BW37:CF37) -> 0 | V36: =SUM('案件．要員情報'!CG37:CP37) -> 0 | W36: =SUM('案件．要員情報'!CQ37:CW37) -> 0 | X36: =SUM('案件．要員情報'!CX37:DD37) -> 0 | Y36: =SUM('案件．要員情報'!DE37:DK37) -> 0 | Z36: =SUM('案件．要員情報'!DL37:DS37) -> 0 | AA36: =SUM(O36:Z36) -> 0.74926984
N37: 実績 | O37: =SUM('案件．要員情報'!O38:X38) -> 0 | P37: =SUM('案件．要員情報'!Y38:AH38) -> 0.27936508 | Q37: =SUM('案件．要員情報'!AI38:AR38) -> 0.42857143 | R37: =SUM('案件．要員情報'!AS38:BB38) -> 0 | S37: =SUM('案件．要員情報'!BC38:BL38) -> 0 | T37: =SUM('案件．要員情報'!BM38:BV38) -> 0 | U37: =SUM('案件．要員情報'!BW38:CF38) -> 0 | V37: =SUM('案件．要員情報'!CG38:CP38) -> 0 | W37: =SUM('案件．要員情報'!CQ38:CW38) -> 0 | X37: =SUM('案件．要員情報'!CX38:DD38) -> 0 | Y37: =SUM('案件．要員情報'!DE38:DK38) -> 0 | Z37: =SUM('案件．要員情報'!DL38:DS38) -> 0 | AA37: =SUM(O37:Z37) -> 0.70793651
A38: 17 | B38: 完了 | C38: その他 | D38: 寺澤 | E38: SFA6 | G38: 【SFA】画面文言変更対応のお願い | N38: 計画 | O38: =SUM('案件．要員情報'!O39:X39) -> 0 | P38: =SUM('案件．要員情報'!Y39:AH39) -> 0 | Q38: =SUM('案件．要員情報'!AI39:AR39) -> 0.36825397 | R38: =SUM('案件．要員情報'!AS39:BB39) -> 0 | S38: =SUM('案件．要員情報'!BC39:BL39) -> 0 | T38: =SUM('案件．要員情報'!BM39:BV39) -> 0 | U38: =SUM('案件．要員情報'!BW39:CF39) -> 0 | V38: =SUM('案件．要員情報'!CG39:CP39) -> 0 | W38: =SUM('案件．要員情報'!CQ39:CW39) -> 0 | X38: =SUM('案件．要員情報'!CX39:DD39) -> 0 | Y38: =SUM('案件．要員情報'!DE39:DK39) -> 0 | Z38: =SUM('案件．要員情報'!DL39:DS39) -> 0 | AA38: =SUM(O38:Z38) -> 0.36825397
N39: 実績 | O39: =SUM('案件．要員情報'!O40:X40) -> 0 | P39: =SUM('案件．要員情報'!Y40:AH40) -> 0 | Q39: =SUM('案件．要員情報'!AI40:AR40) -> 0.36507937 | R39: =SUM('案件．要員情報'!AS40:BB40) -> 0 | S39: =SUM('案件．要員情報'!BC40:BL40) -> 0 | T39: =SUM('案件．要員情報'!BM40:BV40) -> 0 | U39: =SUM('案件．要員情報'!BW40:CF40) -> 0 | V39: =SUM('案件．要員情報'!CG40:CP40) -> 0 | W39: =SUM('案件．要員情報'!CQ40:CW40) -> 0 | X39: =SUM('案件．要員情報'!CX40:DD40) -> 0 | Y39: =SUM('案件．要員情報'!DE40:DK40) -> 0 | Z39: =SUM('案件．要員情報'!DL40:DS40) -> 0 | AA39: =SUM(O39:Z39) -> 0.36507937
A40: 18 | B40: 完了 | C40: その他 | D40: 寺澤 | E40: SFA7 | G40: 【SFA】(000050)画面文言変更対応 | N40: 計画 | O40: =SUM('案件．要員情報'!O41:X41) -> 0 | P40: =SUM('案件．要員情報'!Y41:AH41) -> 0 | Q40: =SUM('案件．要員情報'!AI41:AR41) -> 1.0793651 | R40: =SUM('案件．要員情報'!AS41:BB41) -> 0.58181818 | S40: =SUM('案件．要員情報'!BC41:BL41) -> 0 | T40: =SUM('案件．要員情報'!BM41:BV41) -> 0 | U40: =SUM('案件．要員情報'!BW41:CF41) -> 0 | V40: =SUM('案件．要員情報'!CG41:CP41) -> 0 | W40: =SUM('案件．要員情報'!CQ41:CW41) -> 0 | X40: =SUM('案件．要員情報'!CX41:DD41) -> 0 | Y40: =SUM('案件．要員情報'!DE41:DK41) -> 0 | Z40: =SUM('案件．要員情報'!DL41:DS41) -> 0 | AA40: =SUM(O40:Z40) -> 1.6611833
N41: 実績 | O41: =SUM('案件．要員情報'!O42:X42) -> 0 | P41: =SUM('案件．要員情報'!Y42:AH42) -> 0 | Q41: =SUM('案件．要員情報'!AI42:AR42) -> 1.0666667 | R41: =SUM('案件．要員情報'!AS42:BB42) -> 0.57575758 | S41: =SUM('案件．要員情報'!BC42:BL42) -> 0 | T41: =SUM('案件．要員情報'!BM42:BV42) -> 0 | U41: =SUM('案件．要員情報'!BW42:CF42) -> 0 | V41: =SUM('案件．要員情報'!CG42:CP42) -> 0 | W41: =SUM('案件．要員情報'!CQ42:CW42) -> 0 | X41: =SUM('案件．要員情報'!CX42:DD42) -> 0 | Y41: =SUM('案件．要員情報'!DE42:DK42) -> 0 | Z41: =SUM('案件．要員情報'!DL42:DS42) -> 0 | AA41: =SUM(O41:Z41) -> 1.6424242
A42: 19 | B42: 完了 | C42: その他 | D42: 髙木 | E42: BT3 | G42: w3jy210foの出力メッセージの改善 | N42: 計画 | O42: =SUM('案件．要員情報'!O43:X43) -> 0 | P42: =SUM('案件．要員情報'!Y43:AH43) -> 0 | Q42: =SUM('案件．要員情報'!AI43:AR43) -> 0 | R42: =SUM('案件．要員情報'!AS43:BB43) -> 0.45454545 | S42: =SUM('案件．要員情報'!BC43:BL43) -> 0.11428571 | T42: =SUM('案件．要員情報'!BM43:BV43) -> 0 | U42: =SUM('案件．要員情報'!BW43:CF43) -> 0 | V42: =SUM('案件．要員情報'!CG43:CP43) -> 0 | W42: =SUM('案件．要員情報'!CQ43:CW43) -> 0 | X42: =SUM('案件．要員情報'!CX43:DD43) -> 0 | Y42: =SUM('案件．要員情報'!DE43:DK43) -> 0 | Z42: =SUM('案件．要員情報'!DL43:DS43) -> 0 | AA42: =SUM(O42:Z42) -> 0.56883117
N43: 実績 | O43: =SUM('案件．要員情報'!O44:X44) -> 0 | P43: =SUM('案件．要員情報'!Y44:AH44) -> 0 | Q43: =SUM('案件．要員情報'!AI44:AR44) -> 0 | R43: =SUM('案件．要員情報'!AS44:BB44) -> 0.42424242 | S43: =SUM('案件．要員情報'!BC44:BL44) -> 0.076190476 | T43: =SUM('案件．要員情報'!BM44:BV44) -> 0 | U43: =SUM('案件．要員情報'!BW44:CF44) -> 0 | V43: =SUM('案件．要員情報'!CG44:CP44) -> 0 | W43: =SUM('案件．要員情報'!CQ44:CW44) -> 0 | X43: =SUM('案件．要員情報'!CX44:DD44) -> 0 | Y43: =SUM('案件．要員情報'!DE44:DK44) -> 0 | Z43: =SUM('案件．要員情報'!DL44:DS44) -> 0 | AA43: =SUM(O43:Z43) -> 0.5004329
A44: 20 | B44: 完了 | C44: その他 | D44: 山田 | E44: AH29 | G44: 【開発依頼】ICC本番モジュール取得ツール改善 | N44: 計画 | O44: =SUM('案件．要員情報'!O45:X45) -> 0 | P44: =SUM('案件．要員情報'!Y45:AH45) -> 0 | Q44: =SUM('案件．要員情報'!AI45:AR45) -> 0 | R44: =SUM('案件．要員情報'!AS45:BB45) -> 0.39393939 | S44: =SUM('案件．要員情報'!BC45:BL45) -> 0.019047619 | T44: =SUM('案件．要員情報'!BM45:BV45) -> 0 | U44: =SUM('案件．要員情報'!BW45:CF45) -> 0 | V44: =SUM('案件．要員情報'!CG45:CP45) -> 0 | W44: =SUM('案件．要員情報'!CQ45:CW45) -> 0 | X44: =SUM('案件．要員情報'!CX45:DD45) -> 0 | Y44: =SUM('案件．要員情報'!DE45:DK45) -> 0 | Z44: =SUM('案件．要員情報'!DL45:DS45) -> 0 | AA44: =SUM(O44:Z44) -> 0.41298701
N45: 実績 | O45: =SUM('案件．要員情報'!O46:X46) -> 0 | P45: =SUM('案件．要員情報'!Y46:AH46) -> 0 | Q45: =SUM('案件．要員情報'!AI46:AR46) -> 0 | R45: =SUM('案件．要員情報'!AS46:BB46) -> 0.35757576 | S45: =SUM('案件．要員情報'!BC46:BL46) -> 0.015873016 | T45: =SUM('案件．要員情報'!BM46:BV46) -> 0 | U45: =SUM('案件．要員情報'!BW46:CF46) -> 0 | V45: =SUM('案件．要員情報'!CG46:CP46) -> 0 | W45: =SUM('案件．要員情報'!CQ46:CW46) -> 0 | X45: =SUM('案件．要員情報'!CX46:DD46) -> 0 | Y45: =SUM('案件．要員情報'!DE46:DK46) -> 0 | Z45: =SUM('案件．要員情報'!DL46:DS46) -> 0 | AA45: =SUM(O45:Z45) -> 0.37344877
A46: 21 | B46: 完了 | C46: その他 | D46: 山本 | E46: PR7 | G46: (44)管理者株式銘柄条件設定画面の改善 | N46: 計画 | O46: =SUM('案件．要員情報'!O47:X47) -> 0 | P46: =SUM('案件．要員情報'!Y47:AH47) -> 0 | Q46: =SUM('案件．要員情報'!AI47:AR47) -> 0 | R46: =SUM('案件．要員情報'!AS47:BB47) -> 0.26666667 | S46: =SUM('案件．要員情報'!BC47:BL47) -> 0.63492063 | T46: =SUM('案件．要員情報'!BM47:BV47) -> 0 | U46: =SUM('案件．要員情報'!BW47:CF47) -> 0 | V46: =SUM('案件．要員情報'!CG47:CP47) -> 0 | W46: =SUM('案件．要員情報'!CQ47:CW47) -> 0 | X46: =SUM('案件．要員情報'!CX47:DD47) -> 0 | Y46: =SUM('案件．要員情報'!DE47:DK47) -> 0 | Z46: =SUM('案件．要員情報'!DL47:DS47) -> 0 | AA46: =SUM(O46:Z46) -> 0.9015873
N47: 実績 | O47: =SUM('案件．要員情報'!O48:X48) -> 0 | P47: =SUM('案件．要員情報'!Y48:AH48) -> 0 | Q47: =SUM('案件．要員情報'!AI48:AR48) -> 0 | R47: =SUM('案件．要員情報'!AS48:BB48) -> 0.26363636 | S47: =SUM('案件．要員情報'!BC48:BL48) -> 0.65079365 | T47: =SUM('案件．要員情報'!BM48:BV48) -> 0 | U47: =SUM('案件．要員情報'!BW48:CF48) -> 0 | V47: =SUM('案件．要員情報'!CG48:CP48) -> 0 | W47: =SUM('案件．要員情報'!CQ48:CW48) -> 0 | X47: =SUM('案件．要員情報'!CX48:DD48) -> 0 | Y47: =SUM('案件．要員情報'!DE48:DK48) -> 0 | Z47: =SUM('案件．要員情報'!DL48:DS48) -> 0 | AA47: =SUM(O47:Z47) -> 0.91443001
A48: 22 | B48: 完了 | C48: その他 | D48: 安藤 | E48: WA3 | G48: (0D)(0X)定例会資料作成の自動化 | N48: 計画 | O48: =SUM('案件．要員情報'!O49:X49) -> 0 | P48: =SUM('案件．要員情報'!Y49:AH49) -> 0 | Q48: =SUM('案件．要員情報'!AI49:AR49) -> 0 | R48: =SUM('案件．要員情報'!AS49:BB49) -> 0.48484848 | S48: =SUM('案件．要員情報'!BC49:BL49) -> 0.19047619 | T48: =SUM('案件．要員情報'!BM49:BV49) -> 0 | U48: =SUM('案件．要員情報'!BW49:CF49) -> 0 | V48: =SUM('案件．要員情報'!CG49:CP49) -> 0.44444444 | W48: =SUM('案件．要員情報'!CQ49:CW49) -> 0.34 | X48: =SUM('案件．要員情報'!CX49:DD49) -> 0.12063492 | Y48: =SUM('案件．要員情報'!DE49:DK49) -> 0.10196078 | Z48: =SUM('案件．要員情報'!DL49:DS49) -> 0 | AA48: =SUM(O48:Z48) -> 1.6823648
N49: 実績 | O49: =SUM('案件．要員情報'!O50:X50) -> 0 | P49: =SUM('案件．要員情報'!Y50:AH50) -> 0 | Q49: =SUM('案件．要員情報'!AI50:AR50) -> 0 | R49: =SUM('案件．要員情報'!AS50:BB50) -> 0.47272727 | S49: =SUM('案件．要員情報'!BC50:BL50) -> 0.17777778 | T49: =SUM('案件．要員情報'!BM50:BV50) -> 0 | U49: =SUM('案件．要員情報'!BW50:CF50) -> 0 | V49: =SUM('案件．要員情報'!CG50:CP50) -> 0.38148148 | W49: =SUM('案件．要員情報'!CQ50:CW50) -> 0.32 | X49: =SUM('案件．要員情報'!CX50:DD50) -> 0.11428571 | Y49: =SUM('案件．要員情報'!DE50:DK50) -> 0.070588235 | Z49: =SUM('案件．要員情報'!DL50:DS50) -> 0 | AA49: =SUM(O49:Z49) -> 1.5368605
A50: 23 | B50: 完了 | C50: 定型 | D50: 山田 | E50: F185 | F50: PB00201943 | G50: 【定型】メールアドレス欄への注釈追加 | N50: 計画 | O50: =SUM('案件．要員情報'!O51:X51) -> 0 | P50: =SUM('案件．要員情報'!Y51:AH51) -> 0 | Q50: =SUM('案件．要員情報'!AI51:AR51) -> 0 | R50: =SUM('案件．要員情報'!AS51:BB51) -> 0.16969697 | S50: =SUM('案件．要員情報'!BC51:BL51) -> 0 | T50: =SUM('案件．要員情報'!BM51:BV51) -> 0 | U50: =SUM('案件．要員情報'!BW51:CF51) -> 0 | V50: =SUM('案件．要員情報'!CG51:CP51) -> 0 | W50: =SUM('案件．要員情報'!CQ51:CW51) -> 0 | X50: =SUM('案件．要員情報'!CX51:DD51) -> 0 | Y50: =SUM('案件．要員情報'!DE51:DK51) -> 0 | Z50: =SUM('案件．要員情報'!DL51:DS51) -> 0 | AA50: =SUM(O50:Z50) -> 0.16969697
N51: 実績 | O51: =SUM('案件．要員情報'!O52:X52) -> 0 | P51: =SUM('案件．要員情報'!Y52:AH52) -> 0 | Q51: =SUM('案件．要員情報'!AI52:AR52) -> 0 | R51: =SUM('案件．要員情報'!AS52:BB52) -> 0.15757576 | S51: =SUM('案件．要員情報'!BC52:BL52) -> 0 | T51: =SUM('案件．要員情報'!BM52:BV52) -> 0 | U51: =SUM('案件．要員情報'!BW52:CF52) -> 0 | V51: =SUM('案件．要員情報'!CG52:CP52) -> 0 | W51: =SUM('案件．要員情報'!CQ52:CW52) -> 0 | X51: =SUM('案件．要員情報'!CX52:DD52) -> 0 | Y51: =SUM('案件．要員情報'!DE52:DK52) -> 0 | Z51: =SUM('案件．要員情報'!DL52:DS52) -> 0 | AA51: =SUM(O51:Z51) -> 0.15757576
A52: 24 | B52: 完了 | C52: その他 | D52: 仲井 | E52: PR8 | G52: 【調査依頼】4453_PB00201938_(44)CFD終了対応 | N52: 計画 | O52: =SUM('案件．要員情報'!O53:X53) -> 0 | P52: =SUM('案件．要員情報'!Y53:AH53) -> 0 | Q52: =SUM('案件．要員情報'!AI53:AR53) -> 0 | R52: =SUM('案件．要員情報'!AS53:BB53) -> 0.78181818 | S52: =SUM('案件．要員情報'!BC53:BL53) -> 0.076190476 | T52: =SUM('案件．要員情報'!BM53:BV53) -> 0 | U52: =SUM('案件．要員情報'!BW53:CF53) -> 0 | V52: =SUM('案件．要員情報'!CG53:CP53) -> 0 | W52: =SUM('案件．要員情報'!CQ53:CW53) -> 0 | X52: =SUM('案件．要員情報'!CX53:DD53) -> 0 | Y52: =SUM('案件．要員情報'!DE53:DK53) -> 0 | Z52: =SUM('案件．要員情報'!DL53:DS53) -> 0 | AA52: =SUM(O52:Z52) -> 0.85800866
N53: 実績 | O53: =SUM('案件．要員情報'!O54:X54) -> 0 | P53: =SUM('案件．要員情報'!Y54:AH54) -> 0 | Q53: =SUM('案件．要員情報'!AI54:AR54) -> 0 | R53: =SUM('案件．要員情報'!AS54:BB54) -> 0.76363636 | S53: =SUM('案件．要員情報'!BC54:BL54) -> 0.073015873 | T53: =SUM('案件．要員情報'!BM54:BV54) -> 0 | U53: =SUM('案件．要員情報'!BW54:CF54) -> 0 | V53: =SUM('案件．要員情報'!CG54:CP54) -> 0 | W53: =SUM('案件．要員情報'!CQ54:CW54) -> 0 | X53: =SUM('案件．要員情報'!CX54:DD54) -> 0 | Y53: =SUM('案件．要員情報'!DE54:DK54) -> 0 | Z53: =SUM('案件．要員情報'!DL54:DS54) -> 0 | AA53: =SUM(O53:Z53) -> 0.83665224
A54: 25 | B54: 完了 | C54: 定型 | D54: 山田 | E54: F186 | F54: PB00201962 | G54: 【定型】WEB口座開設画面の外国籍文言追加（再アップロード画面） | N54: 計画 | O54: =SUM('案件．要員情報'!O55:X55) -> 0 | P54: =SUM('案件．要員情報'!Y55:AH55) -> 0 | Q54: =SUM('案件．要員情報'!AI55:AR55) -> 0 | R54: =SUM('案件．要員情報'!AS55:BB55) -> 0 | S54: =SUM('案件．要員情報'!BC55:BL55) -> 0.63492063 | T54: =SUM('案件．要員情報'!BM55:BV55) -> 0.24242424 | U54: =SUM('案件．要員情報'!BW55:CF55) -> 0 | V54: =SUM('案件．要員情報'!CG55:CP55) -> 0 | W54: =SUM('案件．要員情報'!CQ55:CW55) -> 0 | X54: =SUM('案件．要員情報'!CX55:DD55) -> 0 | Y54: =SUM('案件．要員情報'!DE55:DK55) -> 0 | Z54: =SUM('案件．要員情報'!DL55:DS55) -> 0 | AA54: =SUM(O54:Z54) -> 0.87734488
N55: 実績 | O55: =SUM('案件．要員情報'!O56:X56) -> 0 | P55: =SUM('案件．要員情報'!Y56:AH56) -> 0 | Q55: =SUM('案件．要員情報'!AI56:AR56) -> 0 | R55: =SUM('案件．要員情報'!AS56:BB56) -> 0 | S55: =SUM('案件．要員情報'!BC56:BL56) -> 0.61904762 | T55: =SUM('案件．要員情報'!BM56:BV56) -> 0.23333333 | U55: =SUM('案件．要員情報'!BW56:CF56) -> 0 | V55: =SUM('案件．要員情報'!CG56:CP56) -> 0 | W55: =SUM('案件．要員情報'!CQ56:CW56) -> 0 | X55: =SUM('案件．要員情報'!CX56:DD56) -> 0 | Y55: =SUM('案件．要員情報'!DE56:DK56) -> 0 | Z55: =SUM('案件．要員情報'!DL56:DS56) -> 0 | AA55: =SUM(O55:Z55) -> 0.85238095
A56: 26 | B56: 完了 | C56: その他 | D56: 仲井 | E56: BT4 | F56: 4429_PBxxxxxxxx | G56: 【開発依頼】シリアルナンバー初期化 | N56: 計画 | O56: =SUM('案件．要員情報'!O57:X57) -> 0 | P56: =SUM('案件．要員情報'!Y57:AH57) -> 0 | Q56: =SUM('案件．要員情報'!AI57:AR57) -> 0 | R56: =SUM('案件．要員情報'!AS57:BB57) -> 0 | S56: =SUM('案件．要員情報'!BC57:BL57) -> 0.12698413 | T56: =SUM('案件．要員情報'!BM57:BV57) -> 1.1515152 | U56: =SUM('案件．要員情報'!BW57:CF57) -> 0.046666667 | V56: =SUM('案件．要員情報'!CG57:CP57) -> 0.14814815 | W56: =SUM('案件．要員情報'!CQ57:CW57) -> 0 | X56: =SUM('案件．要員情報'!CX57:DD57) -> 0 | Y56: =SUM('案件．要員情報'!DE57:DK57) -> 0 | Z56: =SUM('案件．要員情報'!DL57:DS57) -> 0 | AA56: =SUM(O56:Z56) -> 1.4733141
N57: 実績 | O57: =SUM('案件．要員情報'!O58:X58) -> 0 | P57: =SUM('案件．要員情報'!Y58:AH58) -> 0 | Q57: =SUM('案件．要員情報'!AI58:AR58) -> 0 | R57: =SUM('案件．要員情報'!AS58:BB58) -> 0 | S57: =SUM('案件．要員情報'!BC58:BL58) -> 0.12698413 | T57: =SUM('案件．要員情報'!BM58:BV58) -> 1.1212121 | U57: =SUM('案件．要員情報'!BW58:CF58) -> 0.03 | V57: =SUM('案件．要員情報'!CG58:CP58) -> 0.096296296 | W57: =SUM('案件．要員情報'!CQ58:CW58) -> 0 | X57: =SUM('案件．要員情報'!CX58:DD58) -> 0 | Y57: =SUM('案件．要員情報'!DE58:DK58) -> 0 | Z57: =SUM('案件．要員情報'!DL58:DS58) -> 0 | AA57: =SUM(O57:Z57) -> 1.3744925
A58: 27 | B58: 完了 | C58: その他 | D58: 德田 | E58: PR9 | F58: 4246_PBxxxxxxxx | G58: 【開発依頼】WB4クロスサイトスクリプティング対応 | N58: 計画 | O58: =SUM('案件．要員情報'!O59:X59) -> 0 | P58: =SUM('案件．要員情報'!Y59:AH59) -> 0 | Q58: =SUM('案件．要員情報'!AI59:AR59) -> 0 | R58: =SUM('案件．要員情報'!AS59:BB59) -> 0 | S58: =SUM('案件．要員情報'!BC59:BL59) -> 0 | T58: =SUM('案件．要員情報'!BM59:BV59) -> 4.7575758 | U58: =SUM('案件．要員情報'!BW59:CF59) -> 1.1333333 | V58: =SUM('案件．要員情報'!CG59:CP59) -> 0 | W58: =SUM('案件．要員情報'!CQ59:CW59) -> 0.78 | X58: =SUM('案件．要員情報'!CX59:DD59) -> 0 | Y58: =SUM('案件．要員情報'!DE59:DK59) -> 0 | Z58: =SUM('案件．要員情報'!DL59:DS59) -> 0 | AA58: =SUM(O58:Z58) -> 6.6709091
N59: 実績 | O59: =SUM('案件．要員情報'!O60:X60) -> 0 | P59: =SUM('案件．要員情報'!Y60:AH60) -> 0 | Q59: =SUM('案件．要員情報'!AI60:AR60) -> 0 | R59: =SUM('案件．要員情報'!AS60:BB60) -> 0 | S59: =SUM('案件．要員情報'!BC60:BL60) -> 0 | T59: =SUM('案件．要員情報'!BM60:BV60) -> 4.7287879 | U59: =SUM('案件．要員情報'!BW60:CF60) -> 1.1133333 | V59: =SUM('案件．要員情報'!CG60:CP60) -> 0 | W59: =SUM('案件．要員情報'!CQ60:CW60) -> 0.76833333 | X59: =SUM('案件．要員情報'!CX60:DD60) -> 0 | Y59: =SUM('案件．要員情報'!DE60:DK60) -> 0 | Z59: =SUM('案件．要員情報'!DL60:DS60) -> 0 | AA59: =SUM(O59:Z59) -> 6.6104545
A60: 28 | B60: 完了 | C60: 定型 | D60: 山田 | E60: F187 | F60: PB00201966 | G60: 【定型】WB4トップページサポート欄の文言変更 | N60: 計画 | O60: =SUM('案件．要員情報'!O61:X61) -> 0 | P60: =SUM('案件．要員情報'!Y61:AH61) -> 0 | Q60: =SUM('案件．要員情報'!AI61:AR61) -> 0 | R60: =SUM('案件．要員情報'!AS61:BB61) -> 0 | S60: =SUM('案件．要員情報'!BC61:BL61) -> 0 | T60: =SUM('案件．要員情報'!BM61:BV61) -> 0.36363636 | U60: =SUM('案件．要員情報'!BW61:CF61) -> 0 | V60: =SUM('案件．要員情報'!CG61:CP61) -> 0 | W60: =SUM('案件．要員情報'!CQ61:CW61) -> 0 | X60: =SUM('案件．要員情報'!CX61:DD61) -> 0 | Y60: =SUM('案件．要員情報'!DE61:DK61) -> 0 | Z60: =SUM('案件．要員情報'!DL61:DS61) -> 0 | AA60: =SUM(O60:Z60) -> 0.36363636
N61: 実績 | O61: =SUM('案件．要員情報'!O62:X62) -> 0 | P61: =SUM('案件．要員情報'!Y62:AH62) -> 0 | Q61: =SUM('案件．要員情報'!AI62:AR62) -> 0 | R61: =SUM('案件．要員情報'!AS62:BB62) -> 0 | S61: =SUM('案件．要員情報'!BC62:BL62) -> 0 | T61: =SUM('案件．要員情報'!BM62:BV62) -> 0.27878788 | U61: =SUM('案件．要員情報'!BW62:CF62) -> 0 | V61: =SUM('案件．要員情報'!CG62:CP62) -> 0 | W61: =SUM('案件．要員情報'!CQ62:CW62) -> 0 | X61: =SUM('案件．要員情報'!CX62:DD62) -> 0 | Y61: =SUM('案件．要員情報'!DE62:DK62) -> 0 | Z61: =SUM('案件．要員情報'!DL62:DS62) -> 0 | AA61: =SUM(O61:Z61) -> 0.27878788
A62: 29 | B62: 完了 | C62: 定型 | D62: 德永 | E62: F188 | F62: PB00201964 | G62: 【定型】PIダイレクト指定登録画面の注意書き文言変更 | N62: 計画 | O62: =SUM('案件．要員情報'!O63:X63) -> 0 | P62: =SUM('案件．要員情報'!Y63:AH63) -> 0 | Q62: =SUM('案件．要員情報'!AI63:AR63) -> 0 | R62: =SUM('案件．要員情報'!AS63:BB63) -> 0 | S62: =SUM('案件．要員情報'!BC63:BL63) -> 0 | T62: =SUM('案件．要員情報'!BM63:BV63) -> 0.48484848 | U62: =SUM('案件．要員情報'!BW63:CF63) -> 0 | V62: =SUM('案件．要員情報'!CG63:CP63) -> 0 | W62: =SUM('案件．要員情報'!CQ63:CW63) -> 0 | X62: =SUM('案件．要員情報'!CX63:DD63) -> 0 | Y62: =SUM('案件．要員情報'!DE63:DK63) -> 0 | Z62: =SUM('案件．要員情報'!DL63:DS63) -> 0 | AA62: =SUM(O62:Z62) -> 0.48484848
N63: 実績 | O63: =SUM('案件．要員情報'!O64:X64) -> 0 | P63: =SUM('案件．要員情報'!Y64:AH64) -> 0 | Q63: =SUM('案件．要員情報'!AI64:AR64) -> 0 | R63: =SUM('案件．要員情報'!AS64:BB64) -> 0 | S63: =SUM('案件．要員情報'!BC64:BL64) -> 0 | T63: =SUM('案件．要員情報'!BM64:BV64) -> 0.38484848 | U63: =SUM('案件．要員情報'!BW64:CF64) -> 0 | V63: =SUM('案件．要員情報'!CG64:CP64) -> 0 | W63: =SUM('案件．要員情報'!CQ64:CW64) -> 0 | X63: =SUM('案件．要員情報'!CX64:DD64) -> 0 | Y63: =SUM('案件．要員情報'!DE64:DK64) -> 0 | Z63: =SUM('案件．要員情報'!DL64:DS64) -> 0 | AA63: =SUM(O63:Z63) -> 0.38484848
A64: 30 | B64: 完了 | C64: 定型 | D64: 德永 | E64: F189 | F64: PB00201969 | G64: 【定型】NEOTRADE W(クイック入金画面)の文言修正依頼 | N64: 計画 | O64: =SUM('案件．要員情報'!O65:X65) -> 0 | P64: =SUM('案件．要員情報'!Y65:AH65) -> 0 | Q64: =SUM('案件．要員情報'!AI65:AR65) -> 0 | R64: =SUM('案件．要員情報'!AS65:BB65) -> 0 | S64: =SUM('案件．要員情報'!BC65:BL65) -> 0 | T64: =SUM('案件．要員情報'!BM65:BV65) -> 0.33333333 | U64: =SUM('案件．要員情報'!BW65:CF65) -> 0.13333333 | V64: =SUM('案件．要員情報'!CG65:CP65) -> 0 | W64: =SUM('案件．要員情報'!CQ65:CW65) -> 0 | X64: =SUM('案件．要員情報'!CX65:DD65) -> 0 | Y64: =SUM('案件．要員情報'!DE65:DK65) -> 0 | Z64: =SUM('案件．要員情報'!DL65:DS65) -> 0 | AA64: =SUM(O64:Z64) -> 0.46666667
N65: 実績 | O65: =SUM('案件．要員情報'!O66:X66) -> 0 | P65: =SUM('案件．要員情報'!Y66:AH66) -> 0 | Q65: =SUM('案件．要員情報'!AI66:AR66) -> 0 | R65: =SUM('案件．要員情報'!AS66:BB66) -> 0 | S65: =SUM('案件．要員情報'!BC66:BL66) -> 0 | T65: =SUM('案件．要員情報'!BM66:BV66) -> 0.32121212 | U65: =SUM('案件．要員情報'!BW66:CF66) -> 0.12 | V65: =SUM('案件．要員情報'!CG66:CP66) -> 0 | W65: =SUM('案件．要員情報'!CQ66:CW66) -> 0 | X65: =SUM('案件．要員情報'!CX66:DD66) -> 0 | Y65: =SUM('案件．要員情報'!DE66:DK66) -> 0 | Z65: =SUM('案件．要員情報'!DL66:DS66) -> 0 | AA65: =SUM(O65:Z65) -> 0.44121212
A66: 31 | B66: 完了 | C66: その他 | D66: 安藤 | E66: BT5 | F66: 4474_PBxxxxxxxx | G66: 【定型】WOLFDBのテーブルバックアップ取得処理の追加 | N66: 計画 | O66: =SUM('案件．要員情報'!O67:X67) -> 0 | P66: =SUM('案件．要員情報'!Y67:AH67) -> 0 | Q66: =SUM('案件．要員情報'!AI67:AR67) -> 0 | R66: =SUM('案件．要員情報'!AS67:BB67) -> 0 | S66: =SUM('案件．要員情報'!BC67:BL67) -> 0 | T66: =SUM('案件．要員情報'!BM67:BV67) -> 0.60606061 | U66: =SUM('案件．要員情報'!BW67:CF67) -> 0.93333333 | V66: =SUM('案件．要員情報'!CG67:CP67) -> 0 | W66: =SUM('案件．要員情報'!CQ67:CW67) -> 0 | X66: =SUM('案件．要員情報'!CX67:DD67) -> 0 | Y66: =SUM('案件．要員情報'!DE67:DK67) -> 0 | Z66: =SUM('案件．要員情報'!DL67:DS67) -> 0 | AA66: =SUM(O66:Z66) -> 1.5393939
N67: 実績 | O67: =SUM('案件．要員情報'!O68:X68) -> 0 | P67: =SUM('案件．要員情報'!Y68:AH68) -> 0 | Q67: =SUM('案件．要員情報'!AI68:AR68) -> 0 | R67: =SUM('案件．要員情報'!AS68:BB68) -> 0 | S67: =SUM('案件．要員情報'!BC68:BL68) -> 0 | T67: =SUM('案件．要員情報'!BM68:BV68) -> 0.52424242 | U67: =SUM('案件．要員情報'!BW68:CF68) -> 0.89333333 | V67: =SUM('案件．要員情報'!CG68:CP68) -> 0 | W67: =SUM('案件．要員情報'!CQ68:CW68) -> 0 | X67: =SUM('案件．要員情報'!CX68:DD68) -> 0 | Y67: =SUM('案件．要員情報'!DE68:DK68) -> 0 | Z67: =SUM('案件．要員情報'!DL68:DS68) -> 0 | AA67: =SUM(O67:Z67) -> 1.4175758
A68: 32 | B68: 完了 | C68: その他 | D68: 山本 | E68: PR10 | F68: PBxxxxxxxx | G68: 【定型】(0G)投信銘柄条件登録画面の改善 | N68: 計画 | O68: =SUM('案件．要員情報'!O69:X69) -> 0 | P68: =SUM('案件．要員情報'!Y69:AH69) -> 0 | Q68: =SUM('案件．要員情報'!AI69:AR69) -> 0 | R68: =SUM('案件．要員情報'!AS69:BB69) -> 0 | S68: =SUM('案件．要員情報'!BC69:BL69) -> 0 | T68: =SUM('案件．要員情報'!BM69:BV69) -> 0.084848485 | U68: =SUM('案件．要員情報'!BW69:CF69) -> 0 | V68: =SUM('案件．要員情報'!CG69:CP69) -> 0 | W68: =SUM('案件．要員情報'!CQ69:CW69) -> 0 | X68: =SUM('案件．要員情報'!CX69:DD69) -> 0 | Y68: =SUM('案件．要員情報'!DE69:DK69) -> 0 | Z68: =SUM('案件．要員情報'!DL69:DS69) -> 0 | AA68: =SUM(O68:Z68) -> 0.084848485
N69: 実績 | O69: =SUM('案件．要員情報'!O70:X70) -> 0 | P69: =SUM('案件．要員情報'!Y70:AH70) -> 0 | Q69: =SUM('案件．要員情報'!AI70:AR70) -> 0 | R69: =SUM('案件．要員情報'!AS70:BB70) -> 0 | S69: =SUM('案件．要員情報'!BC70:BL70) -> 0 | T69: =SUM('案件．要員情報'!BM70:BV70) -> 0.072727273 | U69: =SUM('案件．要員情報'!BW70:CF70) -> 0 | V69: =SUM('案件．要員情報'!CG70:CP70) -> 0 | W69: =SUM('案件．要員情報'!CQ70:CW70) -> 0 | X69: =SUM('案件．要員情報'!CX70:DD70) -> 0 | Y69: =SUM('案件．要員情報'!DE70:DK70) -> 0 | Z69: =SUM('案件．要員情報'!DL70:DS70) -> 0 | AA69: =SUM(O69:Z69) -> 0.072727273
A70: 33 | B70: 完了 | C70: 定型 | D70: 德永 | E70: F190 | F70: PB00201985 | G70: 【定型】信用口座開設申込画面のエラーメッセージ文言変更 | N70: 計画 | O70: =SUM('案件．要員情報'!O71:X71) -> 0 | P70: =SUM('案件．要員情報'!Y71:AH71) -> 0 | Q70: =SUM('案件．要員情報'!AI71:AR71) -> 0 | R70: =SUM('案件．要員情報'!AS71:BB71) -> 0 | S70: =SUM('案件．要員情報'!BC71:BL71) -> 0 | T70: =SUM('案件．要員情報'!BM71:BV71) -> 0 | U70: =SUM('案件．要員情報'!BW71:CF71) -> 0.57333333 | V70: =SUM('案件．要員情報'!CG71:CP71) -> 0 | W70: =SUM('案件．要員情報'!CQ71:CW71) -> 0 | X70: =SUM('案件．要員情報'!CX71:DD71) -> 0 | Y70: =SUM('案件．要員情報'!DE71:DK71) -> 0 | Z70: =SUM('案件．要員情報'!DL71:DS71) -> 0 | AA70: =SUM(O70:Z70) -> 0.57333333
N71: 実績 | O71: =SUM('案件．要員情報'!O72:X72) -> 0 | P71: =SUM('案件．要員情報'!Y72:AH72) -> 0 | Q71: =SUM('案件．要員情報'!AI72:AR72) -> 0 | R71: =SUM('案件．要員情報'!AS72:BB72) -> 0 | S71: =SUM('案件．要員情報'!BC72:BL72) -> 0 | T71: =SUM('案件．要員情報'!BM72:BV72) -> 0 | U71: =SUM('案件．要員情報'!BW72:CF72) -> 0.56333333 | V71: =SUM('案件．要員情報'!CG72:CP72) -> 0 | W71: =SUM('案件．要員情報'!CQ72:CW72) -> 0 | X71: =SUM('案件．要員情報'!CX72:DD72) -> 0 | Y71: =SUM('案件．要員情報'!DE72:DK72) -> 0 | Z71: =SUM('案件．要員情報'!DL72:DS72) -> 0 | AA71: =SUM(O71:Z71) -> 0.56333333
A72: 34 | B72: 完了 | C72: 定型 | D72: 德永 | E72: F191 | F72: PB00201987 | G72: 【定型】投信手数料文言変更（Succe-s、NaitoWeb） | N72: 計画 | O72: =SUM('案件．要員情報'!O73:X73) -> 0 | P72: =SUM('案件．要員情報'!Y73:AH73) -> 0 | Q72: =SUM('案件．要員情報'!AI73:AR73) -> 0 | R72: =SUM('案件．要員情報'!AS73:BB73) -> 0 | S72: =SUM('案件．要員情報'!BC73:BL73) -> 0 | T72: =SUM('案件．要員情報'!BM73:BV73) -> 0 | U72: =SUM('案件．要員情報'!BW73:CF73) -> 0.43333333 | V72: =SUM('案件．要員情報'!CG73:CP73) -> 0 | W72: =SUM('案件．要員情報'!CQ73:CW73) -> 0 | X72: =SUM('案件．要員情報'!CX73:DD73) -> 0 | Y72: =SUM('案件．要員情報'!DE73:DK73) -> 0 | Z72: =SUM('案件．要員情報'!DL73:DS73) -> 0 | AA72: =SUM(O72:Z72) -> 0.43333333
N73: 実績 | O73: =SUM('案件．要員情報'!O74:X74) -> 0 | P73: =SUM('案件．要員情報'!Y74:AH74) -> 0 | Q73: =SUM('案件．要員情報'!AI74:AR74) -> 0 | R73: =SUM('案件．要員情報'!AS74:BB74) -> 0 | S73: =SUM('案件．要員情報'!BC74:BL74) -> 0 | T73: =SUM('案件．要員情報'!BM74:BV74) -> 0 | U73: =SUM('案件．要員情報'!BW74:CF74) -> 0.42333333 | V73: =SUM('案件．要員情報'!CG74:CP74) -> 0 | W73: =SUM('案件．要員情報'!CQ74:CW74) -> 0 | X73: =SUM('案件．要員情報'!CX74:DD74) -> 0 | Y73: =SUM('案件．要員情報'!DE74:DK74) -> 0 | Z73: =SUM('案件．要員情報'!DL74:DS74) -> 0 | AA73: =SUM(O73:Z73) -> 0.42333333
A74: 35 | B74: 完了 | C74: その他 | D74: 山田 | E74: WA4 | G74: 【開発依頼】5-2【MN証券、SP社】トランザクション件数自動化 | N74: 計画 | O74: =SUM('案件．要員情報'!O75:X75) -> 0 | P74: =SUM('案件．要員情報'!Y75:AH75) -> 0 | Q74: =SUM('案件．要員情報'!AI75:AR75) -> 0 | R74: =SUM('案件．要員情報'!AS75:BB75) -> 0 | S74: =SUM('案件．要員情報'!BC75:BL75) -> 0 | T74: =SUM('案件．要員情報'!BM75:BV75) -> 0 | U74: =SUM('案件．要員情報'!BW75:CF75) -> 1.5 | V74: =SUM('案件．要員情報'!CG75:CP75) -> 0.66666667 | W74: =SUM('案件．要員情報'!CQ75:CW75) -> 0.8 | X74: =SUM('案件．要員情報'!CX75:DD75) -> 0 | Y74: =SUM('案件．要員情報'!DE75:DK75) -> 0 | Z74: =SUM('案件．要員情報'!DL75:DS75) -> 0 | AA74: =SUM(O74:Z74) -> 2.9666667
N75: 実績 | O75: =SUM('案件．要員情報'!O76:X76) -> 0 | P75: =SUM('案件．要員情報'!Y76:AH76) -> 0 | Q75: =SUM('案件．要員情報'!AI76:AR76) -> 0 | R75: =SUM('案件．要員情報'!AS76:BB76) -> 0 | S75: =SUM('案件．要員情報'!BC76:BL76) -> 0 | T75: =SUM('案件．要員情報'!BM76:BV76) -> 0 | U75: =SUM('案件．要員情報'!BW76:CF76) -> 1.4966667 | V75: =SUM('案件．要員情報'!CG76:CP76) -> 0.57407407 | W75: =SUM('案件．要員情報'!CQ76:CW76) -> 0.78333333 | X75: =SUM('案件．要員情報'!CX76:DD76) -> 0 | Y75: =SUM('案件．要員情報'!DE76:DK76) -> 0 | Z75: =SUM('案件．要員情報'!DL76:DS76) -> 0 | AA75: =SUM(O75:Z75) -> 2.8540741
A76: 36 | B76: 完了 | C76: その他 | D76: 髙木 | E76: BT6 | G76: 【見積依頼】取引履歴アンマッチメール未送信の改善対応 | N76: 計画 | O76: =SUM('案件．要員情報'!O77:X77) -> 0 | P76: =SUM('案件．要員情報'!Y77:AH77) -> 0 | Q76: =SUM('案件．要員情報'!AI77:AR77) -> 0 | R76: =SUM('案件．要員情報'!AS77:BB77) -> 0 | S76: =SUM('案件．要員情報'!BC77:BL77) -> 0 | T76: =SUM('案件．要員情報'!BM77:BV77) -> 0 | U76: =SUM('案件．要員情報'!BW77:CF77) -> 1.5 | V76: =SUM('案件．要員情報'!CG77:CP77) -> 0.22222222 | W76: =SUM('案件．要員情報'!CQ77:CW77) -> 0 | X76: =SUM('案件．要員情報'!CX77:DD77) -> 0 | Y76: =SUM('案件．要員情報'!DE77:DK77) -> 0 | Z76: =SUM('案件．要員情報'!DL77:DS77) -> 0 | AA76: =SUM(O76:Z76) -> 1.7222222
N77: 実績 | O77: =SUM('案件．要員情報'!O78:X78) -> 0 | P77: =SUM('案件．要員情報'!Y78:AH78) -> 0 | Q77: =SUM('案件．要員情報'!AI78:AR78) -> 0 | R77: =SUM('案件．要員情報'!AS78:BB78) -> 0 | S77: =SUM('案件．要員情報'!BC78:BL78) -> 0 | T77: =SUM('案件．要員情報'!BM78:BV78) -> 0 | U77: =SUM('案件．要員情報'!BW78:CF78) -> 1.48 | V77: =SUM('案件．要員情報'!CG78:CP78) -> 0.14074074 | W77: =SUM('案件．要員情報'!CQ78:CW78) -> 0 | X77: =SUM('案件．要員情報'!CX78:DD78) -> 0 | Y77: =SUM('案件．要員情報'!DE78:DK78) -> 0 | Z77: =SUM('案件．要員情報'!DL78:DS78) -> 0 | AA77: =SUM(O77:Z77) -> 1.6207407
A78: 37 | B78: 完了 | C78: 定型 | D78: 山田 | E78: F192 | F78: PB00201990 | G78: 【定型】(46)【外国株式】ハードリミット登録依頼 | N78: 計画 | O78: =SUM('案件．要員情報'!O79:X79) -> 0 | P78: =SUM('案件．要員情報'!Y79:AH79) -> 0 | Q78: =SUM('案件．要員情報'!AI79:AR79) -> 0 | R78: =SUM('案件．要員情報'!AS79:BB79) -> 0 | S78: =SUM('案件．要員情報'!BC79:BL79) -> 0 | T78: =SUM('案件．要員情報'!BM79:BV79) -> 0 | U78: =SUM('案件．要員情報'!BW79:CF79) -> 0.2 | V78: =SUM('案件．要員情報'!CG79:CP79) -> 0 | W78: =SUM('案件．要員情報'!CQ79:CW79) -> 0 | X78: =SUM('案件．要員情報'!CX79:DD79) -> 0 | Y78: =SUM('案件．要員情報'!DE79:DK79) -> 0 | Z78: =SUM('案件．要員情報'!DL79:DS79) -> 0 | AA78: =SUM(O78:Z78) -> 0.2
N79: 実績 | O79: =SUM('案件．要員情報'!O80:X80) -> 0 | P79: =SUM('案件．要員情報'!Y80:AH80) -> 0 | Q79: =SUM('案件．要員情報'!AI80:AR80) -> 0 | R79: =SUM('案件．要員情報'!AS80:BB80) -> 0 | S79: =SUM('案件．要員情報'!BC80:BL80) -> 0 | T79: =SUM('案件．要員情報'!BM80:BV80) -> 0 | U79: =SUM('案件．要員情報'!BW80:CF80) -> 0.18 | V79: =SUM('案件．要員情報'!CG80:CP80) -> 0 | W79: =SUM('案件．要員情報'!CQ80:CW80) -> 0 | X79: =SUM('案件．要員情報'!CX80:DD80) -> 0 | Y79: =SUM('案件．要員情報'!DE80:DK80) -> 0 | Z79: =SUM('案件．要員情報'!DL80:DS80) -> 0 | AA79: =SUM(O79:Z79) -> 0.18
A80: 38 | B80: 完了 | C80: その他 | D80: 寺澤 | E80: SFA8 | G80: 【SFA】(20251020)タッチ情報_顧客ニーズ登録エラー | N80: 計画 | O80: =SUM('案件．要員情報'!O81:X81) -> 0 | P80: =SUM('案件．要員情報'!Y81:AH81) -> 0 | Q80: =SUM('案件．要員情報'!AI81:AR81) -> 0 | R80: =SUM('案件．要員情報'!AS81:BB81) -> 0 | S80: =SUM('案件．要員情報'!BC81:BL81) -> 0 | T80: =SUM('案件．要員情報'!BM81:BV81) -> 0 | U80: =SUM('案件．要員情報'!BW81:CF81) -> 0.54666667 | V80: =SUM('案件．要員情報'!CG81:CP81) -> 0 | W80: =SUM('案件．要員情報'!CQ81:CW81) -> 0 | X80: =SUM('案件．要員情報'!CX81:DD81) -> 0 | Y80: =SUM('案件．要員情報'!DE81:DK81) -> 0 | Z80: =SUM('案件．要員情報'!DL81:DS81) -> 0 | AA80: =SUM(O80:Z80) -> 0.54666667
N81: 実績 | O81: =SUM('案件．要員情報'!O82:X82) -> 0 | P81: =SUM('案件．要員情報'!Y82:AH82) -> 0 | Q81: =SUM('案件．要員情報'!AI82:AR82) -> 0 | R81: =SUM('案件．要員情報'!AS82:BB82) -> 0 | S81: =SUM('案件．要員情報'!BC82:BL82) -> 0 | T81: =SUM('案件．要員情報'!BM82:BV82) -> 0 | U81: =SUM('案件．要員情報'!BW82:CF82) -> 0.54333333 | V81: =SUM('案件．要員情報'!CG82:CP82) -> 0 | W81: =SUM('案件．要員情報'!CQ82:CW82) -> 0 | X81: =SUM('案件．要員情報'!CX82:DD82) -> 0 | Y81: =SUM('案件．要員情報'!DE82:DK82) -> 0 | Z81: =SUM('案件．要員情報'!DL82:DS82) -> 0 | AA81: =SUM(O81:Z81) -> 0.54333333
A82: 39 | B82: 完了 | C82: その他 | D82: 平石 | E82: PR11 | G82: 【開発依頼】管理者 株式銘柄条件設定の入力チェックの改善 | N82: 計画 | O82: =SUM('案件．要員情報'!O83:X83) -> 0 | P82: =SUM('案件．要員情報'!Y83:AH83) -> 0 | Q82: =SUM('案件．要員情報'!AI83:AR83) -> 0 | R82: =SUM('案件．要員情報'!AS83:BB83) -> 0 | S82: =SUM('案件．要員情報'!BC83:BL83) -> 0 | T82: =SUM('案件．要員情報'!BM83:BV83) -> 0 | U82: =SUM('案件．要員情報'!BW83:CF83) -> 0.36666667 | V82: =SUM('案件．要員情報'!CG83:CP83) -> 1.6666667 | W82: =SUM('案件．要員情報'!CQ83:CW83) -> 1.42 | X82: =SUM('案件．要員情報'!CX83:DD83) -> 0.063492063 | Y82: =SUM('案件．要員情報'!DE83:DK83) -> 0 | Z82: =SUM('案件．要員情報'!DL83:DS83) -> 0 | AA82: =SUM(O82:Z82) -> 3.5168254
N83: 実績 | O83: =SUM('案件．要員情報'!O84:X84) -> 0 | P83: =SUM('案件．要員情報'!Y84:AH84) -> 0 | Q83: =SUM('案件．要員情報'!AI84:AR84) -> 0 | R83: =SUM('案件．要員情報'!AS84:BB84) -> 0 | S83: =SUM('案件．要員情報'!BC84:BL84) -> 0 | T83: =SUM('案件．要員情報'!BM84:BV84) -> 0 | U83: =SUM('案件．要員情報'!BW84:CF84) -> 0.35 | V83: =SUM('案件．要員情報'!CG84:CP84) -> 1.6407407 | W83: =SUM('案件．要員情報'!CQ84:CW84) -> 1.3683333 | X83: =SUM('案件．要員情報'!CX84:DD84) -> 0.06984127 | Y83: =SUM('案件．要員情報'!DE84:DK84) -> 0 | Z83: =SUM('案件．要員情報'!DL84:DS84) -> 0 | AA83: =SUM(O83:Z83) -> 3.4289153
A84: 40 | B84: 完了 | C84: 定型 | D84: 山田 | E84: F193 | G84: PB00202006_(46)【外国株式】ハードリミット登録依頼 | N84: 計画 | O84: =SUM('案件．要員情報'!O85:X85) -> 0 | P84: =SUM('案件．要員情報'!Y85:AH85) -> 0 | Q84: =SUM('案件．要員情報'!AI85:AR85) -> 0 | R84: =SUM('案件．要員情報'!AS85:BB85) -> 0 | S84: =SUM('案件．要員情報'!BC85:BL85) -> 0 | T84: =SUM('案件．要員情報'!BM85:BV85) -> 0 | U84: =SUM('案件．要員情報'!BW85:CF85) -> 0 | V84: =SUM('案件．要員情報'!CG85:CP85) -> 0 | W84: =SUM('案件．要員情報'!CQ85:CW85) -> 0.21333333 | X84: =SUM('案件．要員情報'!CX85:DD85) -> 0 | Y84: =SUM('案件．要員情報'!DE85:DK85) -> 0 | Z84: =SUM('案件．要員情報'!DL85:DS85) -> 0 | AA84: =SUM(O84:Z84) -> 0.21333333
N85: 実績 | O85: =SUM('案件．要員情報'!O86:X86) -> 0 | P85: =SUM('案件．要員情報'!Y86:AH86) -> 0 | Q85: =SUM('案件．要員情報'!AI86:AR86) -> 0 | R85: =SUM('案件．要員情報'!AS86:BB86) -> 0 | S85: =SUM('案件．要員情報'!BC86:BL86) -> 0 | T85: =SUM('案件．要員情報'!BM86:BV86) -> 0 | U85: =SUM('案件．要員情報'!BW86:CF86) -> 0 | V85: =SUM('案件．要員情報'!CG86:CP86) -> 0 | W85: =SUM('案件．要員情報'!CQ86:CW86) -> 0.20666667 | X85: =SUM('案件．要員情報'!CX86:DD86) -> 0 | Y85: =SUM('案件．要員情報'!DE86:DK86) -> 0 | Z85: =SUM('案件．要員情報'!DL86:DS86) -> 0 | AA85: =SUM(O85:Z85) -> 0.20666667
A86: 41 | B86: 完了 | C86: 定型 | D86: 山田 | E86: F194 | G86: PB00202008_(46)【外国株式】ハードリミット登録依頼 | N86: 計画 | O86: =SUM('案件．要員情報'!O87:X87) -> 0 | P86: =SUM('案件．要員情報'!Y87:AH87) -> 0 | Q86: =SUM('案件．要員情報'!AI87:AR87) -> 0 | R86: =SUM('案件．要員情報'!AS87:BB87) -> 0 | S86: =SUM('案件．要員情報'!BC87:BL87) -> 0 | T86: =SUM('案件．要員情報'!BM87:BV87) -> 0 | U86: =SUM('案件．要員情報'!BW87:CF87) -> 0 | V86: =SUM('案件．要員情報'!CG87:CP87) -> 0 | W86: =SUM('案件．要員情報'!CQ87:CW87) -> 0.24 | X86: =SUM('案件．要員情報'!CX87:DD87) -> 0 | Y86: =SUM('案件．要員情報'!DE87:DK87) -> 0 | Z86: =SUM('案件．要員情報'!DL87:DS87) -> 0 | AA86: =SUM(O86:Z86) -> 0.24
N87: 実績 | O87: =SUM('案件．要員情報'!O88:X88) -> 0 | P87: =SUM('案件．要員情報'!Y88:AH88) -> 0 | Q87: =SUM('案件．要員情報'!AI88:AR88) -> 0 | R87: =SUM('案件．要員情報'!AS88:BB88) -> 0 | S87: =SUM('案件．要員情報'!BC88:BL88) -> 0 | T87: =SUM('案件．要員情報'!BM88:BV88) -> 0 | U87: =SUM('案件．要員情報'!BW88:CF88) -> 0 | V87: =SUM('案件．要員情報'!CG88:CP88) -> 0 | W87: =SUM('案件．要員情報'!CQ88:CW88) -> 0.23666667 | X87: =SUM('案件．要員情報'!CX88:DD88) -> 0 | Y87: =SUM('案件．要員情報'!DE88:DK88) -> 0 | Z87: =SUM('案件．要員情報'!DL88:DS88) -> 0 | AA87: =SUM(O87:Z87) -> 0.23666667
A88: 42 | B88: 完了 | C88: 定型 | D88: 山田 | E88: F195 | F88: PB00202011 | G88: 【定型】ログイン画面のGoogleanalytics計測タグ変更 | N88: 計画 | O88: =SUM('案件．要員情報'!O89:X89) -> 0 | P88: =SUM('案件．要員情報'!Y89:AH89) -> 0 | Q88: =SUM('案件．要員情報'!AI89:AR89) -> 0 | R88: =SUM('案件．要員情報'!AS89:BB89) -> 0 | S88: =SUM('案件．要員情報'!BC89:BL89) -> 0 | T88: =SUM('案件．要員情報'!BM89:BV89) -> 0 | U88: =SUM('案件．要員情報'!BW89:CF89) -> 0 | V88: =SUM('案件．要員情報'!CG89:CP89) -> 0 | W88: =SUM('案件．要員情報'!CQ89:CW89) -> 0.16666667 | X88: =SUM('案件．要員情報'!CX89:DD89) -> 0 | Y88: =SUM('案件．要員情報'!DE89:DK89) -> 0 | Z88: =SUM('案件．要員情報'!DL89:DS89) -> 0 | AA88: =SUM(O88:Z88) -> 0.16666667
N89: 実績 | O89: =SUM('案件．要員情報'!O90:X90) -> 0 | P89: =SUM('案件．要員情報'!Y90:AH90) -> 0 | Q89: =SUM('案件．要員情報'!AI90:AR90) -> 0 | R89: =SUM('案件．要員情報'!AS90:BB90) -> 0 | S89: =SUM('案件．要員情報'!BC90:BL90) -> 0 | T89: =SUM('案件．要員情報'!BM90:BV90) -> 0 | U89: =SUM('案件．要員情報'!BW90:CF90) -> 0 | V89: =SUM('案件．要員情報'!CG90:CP90) -> 0 | W89: =SUM('案件．要員情報'!CQ90:CW90) -> 0.14 | X89: =SUM('案件．要員情報'!CX90:DD90) -> 0 | Y89: =SUM('案件．要員情報'!DE90:DK90) -> 0 | Z89: =SUM('案件．要員情報'!DL90:DS90) -> 0 | AA89: =SUM(O89:Z89) -> 0.14
A90: 43 | B90: 完了 | C90: その他 | D90: 山田 | E90: PR12 | G90: 【WB4】【調査依頼】(0D)WB4のURL使用箇所一覧 | N90: 計画 | O90: =SUM('案件．要員情報'!O91:X91) -> 0 | P90: =SUM('案件．要員情報'!Y91:AH91) -> 0 | Q90: =SUM('案件．要員情報'!AI91:AR91) -> 0 | R90: =SUM('案件．要員情報'!AS91:BB91) -> 0 | S90: =SUM('案件．要員情報'!BC91:BL91) -> 0 | T90: =SUM('案件．要員情報'!BM91:BV91) -> 0 | U90: =SUM('案件．要員情報'!BW91:CF91) -> 0 | V90: =SUM('案件．要員情報'!CG91:CP91) -> 0 | W90: =SUM('案件．要員情報'!CQ91:CW91) -> 0.16666667 | X90: =SUM('案件．要員情報'!CX91:DD91) -> 0 | Y90: =SUM('案件．要員情報'!DE91:DK91) -> 0 | Z90: =SUM('案件．要員情報'!DL91:DS91) -> 0 | AA90: =SUM(O90:Z90) -> 0.16666667
N91: 実績 | O91: =SUM('案件．要員情報'!O92:X92) -> 0 | P91: =SUM('案件．要員情報'!Y92:AH92) -> 0 | Q91: =SUM('案件．要員情報'!AI92:AR92) -> 0 | R91: =SUM('案件．要員情報'!AS92:BB92) -> 0 | S91: =SUM('案件．要員情報'!BC92:BL92) -> 0 | T91: =SUM('案件．要員情報'!BM92:BV92) -> 0 | U91: =SUM('案件．要員情報'!BW92:CF92) -> 0 | V91: =SUM('案件．要員情報'!CG92:CP92) -> 0 | W91: =SUM('案件．要員情報'!CQ92:CW92) -> 0.14666667 | X91: =SUM('案件．要員情報'!CX92:DD92) -> 0 | Y91: =SUM('案件．要員情報'!DE92:DK92) -> 0 | Z91: =SUM('案件．要員情報'!DL92:DS92) -> 0 | AA91: =SUM(O91:Z91) -> 0.14666667
A92: 44 | B92: 完了 | C92: その他 | D92: 坂野 | E92: SFA9 | G92: 【SFA】(000051)画面文言変更対応 調査・見積依頼 | N92: 計画 | O92: =SUM('案件．要員情報'!O93:X93) -> 0 | P92: =SUM('案件．要員情報'!Y93:AH93) -> 0 | Q92: =SUM('案件．要員情報'!AI93:AR93) -> 0 | R92: =SUM('案件．要員情報'!AS93:BB93) -> 0 | S92: =SUM('案件．要員情報'!BC93:BL93) -> 0 | T92: =SUM('案件．要員情報'!BM93:BV93) -> 0 | U92: =SUM('案件．要員情報'!BW93:CF93) -> 0 | V92: =SUM('案件．要員情報'!CG93:CP93) -> 0 | W92: =SUM('案件．要員情報'!CQ93:CW93) -> 0.13333333 | X92: =SUM('案件．要員情報'!CX93:DD93) -> 0 | Y92: =SUM('案件．要員情報'!DE93:DK93) -> 0 | Z92: =SUM('案件．要員情報'!DL93:DS93) -> 0 | AA92: =SUM(O92:Z92) -> 0.13333333
N93: 実績 | O93: =SUM('案件．要員情報'!O94:X94) -> 0 | P93: =SUM('案件．要員情報'!Y94:AH94) -> 0 | Q93: =SUM('案件．要員情報'!AI94:AR94) -> 0 | R93: =SUM('案件．要員情報'!AS94:BB94) -> 0 | S93: =SUM('案件．要員情報'!BC94:BL94) -> 0 | T93: =SUM('案件．要員情報'!BM94:BV94) -> 0 | U93: =SUM('案件．要員情報'!BW94:CF94) -> 0 | V93: =SUM('案件．要員情報'!CG94:CP94) -> 0 | W93: =SUM('案件．要員情報'!CQ94:CW94) -> 0.12 | X93: =SUM('案件．要員情報'!CX94:DD94) -> 0 | Y93: =SUM('案件．要員情報'!DE94:DK94) -> 0 | Z93: =SUM('案件．要員情報'!DL94:DS94) -> 0 | AA93: =SUM(O93:Z93) -> 0.12
A94: 45 | B94: 完了 | C94: 定型 | D94: 山田 | E94: F196 | F94: PB00202019 | G94: PB00202019_【定型】WB4投資家（Succe-sTrade）年末NISA文言追加 | N94: 計画 | O94: =SUM('案件．要員情報'!O95:X95) -> 0 | P94: =SUM('案件．要員情報'!Y95:AH95) -> 0 | Q94: =SUM('案件．要員情報'!AI95:AR95) -> 0 | R94: =SUM('案件．要員情報'!AS95:BB95) -> 0 | S94: =SUM('案件．要員情報'!BC95:BL95) -> 0 | T94: =SUM('案件．要員情報'!BM95:BV95) -> 0 | U94: =SUM('案件．要員情報'!BW95:CF95) -> 0 | V94: =SUM('案件．要員情報'!CG95:CP95) -> 0 | W94: =SUM('案件．要員情報'!CQ95:CW95) -> 0.25333333 | X94: =SUM('案件．要員情報'!CX95:DD95) -> 0.031746032 | Y94: =SUM('案件．要員情報'!DE95:DK95) -> 0 | Z94: =SUM('案件．要員情報'!DL95:DS95) -> 0 | AA94: =SUM(O94:Z94) -> 0.28507937
N95: 実績 | O95: =SUM('案件．要員情報'!O96:X96) -> 0 | P95: =SUM('案件．要員情報'!Y96:AH96) -> 0 | Q95: =SUM('案件．要員情報'!AI96:AR96) -> 0 | R95: =SUM('案件．要員情報'!AS96:BB96) -> 0 | S95: =SUM('案件．要員情報'!BC96:BL96) -> 0 | T95: =SUM('案件．要員情報'!BM96:BV96) -> 0 | U95: =SUM('案件．要員情報'!BW96:CF96) -> 0 | V95: =SUM('案件．要員情報'!CG96:CP96) -> 0 | W95: =SUM('案件．要員情報'!CQ96:CW96) -> 0.24333333 | X95: =SUM('案件．要員情報'!CX96:DD96) -> 0.028571429 | Y95: =SUM('案件．要員情報'!DE96:DK96) -> 0 | Z95: =SUM('案件．要員情報'!DL96:DS96) -> 0 | AA95: =SUM(O95:Z95) -> 0.27190476
A96: 46 | B96: 完了 | C96: 定型 | D96: 山田 | E96: F197 | F96: PB00202027 | G96: 【定型】信用取引金利変更依頼（制度・一般） | N96: 計画 | O96: =SUM('案件．要員情報'!O97:X97) -> 0 | P96: =SUM('案件．要員情報'!Y97:AH97) -> 0 | Q96: =SUM('案件．要員情報'!AI97:AR97) -> 0 | R96: =SUM('案件．要員情報'!AS97:BB97) -> 0 | S96: =SUM('案件．要員情報'!BC97:BL97) -> 0 | T96: =SUM('案件．要員情報'!BM97:BV97) -> 0 | U96: =SUM('案件．要員情報'!BW97:CF97) -> 0 | V96: =SUM('案件．要員情報'!CG97:CP97) -> 0 | W96: =SUM('案件．要員情報'!CQ97:CW97) -> 0 | X96: =SUM('案件．要員情報'!CX97:DD97) -> 1.0539683 | Y96: =SUM('案件．要員情報'!DE97:DK97) -> 0 | Z96: =SUM('案件．要員情報'!DL97:DS97) -> 0 | AA96: =SUM(O96:Z96) -> 1.0539683
N97: 実績 | O97: =SUM('案件．要員情報'!O98:X98) -> 0 | P97: =SUM('案件．要員情報'!Y98:AH98) -> 0 | Q97: =SUM('案件．要員情報'!AI98:AR98) -> 0 | R97: =SUM('案件．要員情報'!AS98:BB98) -> 0 | S97: =SUM('案件．要員情報'!BC98:BL98) -> 0 | T97: =SUM('案件．要員情報'!BM98:BV98) -> 0 | U97: =SUM('案件．要員情報'!BW98:CF98) -> 0 | V97: =SUM('案件．要員情報'!CG98:CP98) -> 0 | W97: =SUM('案件．要員情報'!CQ98:CW98) -> 0 | X97: =SUM('案件．要員情報'!CX98:DD98) -> 1.031746 | Y97: =SUM('案件．要員情報'!DE98:DK98) -> 0 | Z97: =SUM('案件．要員情報'!DL98:DS98) -> 0 | AA97: =SUM(O97:Z97) -> 1.031746
A98: 47 | B98: 完了 | C98: その他 | D98: 坂野 | E98: PL7 | G98: 【対応依頼】【PLATE】画面開放（GI316） | N98: 計画 | O98: =SUM('案件．要員情報'!O99:X99) -> 0 | P98: =SUM('案件．要員情報'!Y99:AH99) -> 0 | Q98: =SUM('案件．要員情報'!AI99:AR99) -> 0 | R98: =SUM('案件．要員情報'!AS99:BB99) -> 0 | S98: =SUM('案件．要員情報'!BC99:BL99) -> 0 | T98: =SUM('案件．要員情報'!BM99:BV99) -> 0 | U98: =SUM('案件．要員情報'!BW99:CF99) -> 0 | V98: =SUM('案件．要員情報'!CG99:CP99) -> 0 | W98: =SUM('案件．要員情報'!CQ99:CW99) -> 0 | X98: =SUM('案件．要員情報'!CX99:DD99) -> 0.52698413 | Y98: =SUM('案件．要員情報'!DE99:DK99) -> 0 | Z98: =SUM('案件．要員情報'!DL99:DS99) -> 0 | AA98: =SUM(O98:Z98) -> 0.52698413
N99: 実績 | O99: =SUM('案件．要員情報'!O100:X100) -> 0 | P99: =SUM('案件．要員情報'!Y100:AH100) -> 0 | Q99: =SUM('案件．要員情報'!AI100:AR100) -> 0 | R99: =SUM('案件．要員情報'!AS100:BB100) -> 0 | S99: =SUM('案件．要員情報'!BC100:BL100) -> 0 | T99: =SUM('案件．要員情報'!BM100:BV100) -> 0 | U99: =SUM('案件．要員情報'!BW100:CF100) -> 0 | V99: =SUM('案件．要員情報'!CG100:CP100) -> 0 | W99: =SUM('案件．要員情報'!CQ100:CW100) -> 0 | X99: =SUM('案件．要員情報'!CX100:DD100) -> 0.51428571 | Y99: =SUM('案件．要員情報'!DE100:DK100) -> 0 | Z99: =SUM('案件．要員情報'!DL100:DS100) -> 0 | AA99: =SUM(O99:Z99) -> 0.51428571
A100: 48 | B100: 着手中 | C100: その他 | D100: 坂野 | E100: PA5 | G100: 【対応依頼】【PLATE】PLATE AUTOマニュアル修正 | N100: 計画 | O100: =SUM('案件．要員情報'!O101:X101) -> 0 | P100: =SUM('案件．要員情報'!Y101:AH101) -> 0 | Q100: =SUM('案件．要員情報'!AI101:AR101) -> 0 | R100: =SUM('案件．要員情報'!AS101:BB101) -> 0 | S100: =SUM('案件．要員情報'!BC101:BL101) -> 0 | T100: =SUM('案件．要員情報'!BM101:BV101) -> 0 | U100: =SUM('案件．要員情報'!BW101:CF101) -> 0 | V100: =SUM('案件．要員情報'!CG101:CP101) -> 0 | W100: =SUM('案件．要員情報'!CQ101:CW101) -> 0 | X100: =SUM('案件．要員情報'!CX101:DD101) -> 0.88888889 | Y100: =SUM('案件．要員情報'!DE101:DK101) -> 0.11764706 | Z100: =SUM('案件．要員情報'!DL101:DS101) -> 0 | AA100: =SUM(O100:Z100) -> 1.0065359
...

Sheet 案件．要員情報
A1: 案件．要員情報 | P1: Total Member - 10 | S1: Contract Member - 8 | Z1: Total Member - 10 | AC1: Contract Member - 8 | AJ1: Total Member - 10 | AM1: Contract Member - 8 | AT1: Total Member - 8 | AW1: Contract Member - 7 | BD1: Total Member - 8 | BF1: Total Member - 8 | BI1: Contract Member - 7 | BN1: Total Member - 8 | BQ1: Contract Member - 7 | BX1: Total Member - 8 | CA1: Contract Member - 7 | CH1: Total Member - 8 | CK1: Contract Member - 7 | CR1: Total Member - 8 | CU1: Contract Member - 7 | CY1: Total Member - 8 | DB1: Contract Member - 7 | DF1: Total Member - 8 | DI1: Contract Member - 7 | DM1: Total Member - 8 | DP1: Contract Member - 7
P2: FOC Member - 2 | Z2: FOC Member - 2 | AJ2: FOC Member - 2 | AT2: FOC Member - 1 | BD2: FOC Member - 1 | BF2: FOC Member - 1 | BN2: FOC Member - 1 | BX2: FOC Member - 1 | CH2: FOC Member - 1 | CR2: FOC Member - 1 | CY2: FOC Member - 1 | DF2: FOC Member - 1 | DM2: FOC Member - 1
A3: ■案件
A4: No. | B4: ステータス | C4: 区分 | D4: DIR 担当 | E4: 案件管理コード（DAT) | F4: 案件管理コード（DIR) | G4: 案件 | H4: 計画 (DIR) | I4: 計画 (DAT) | J4: 進捗 （％） | K4: 着手日 | L4: 完了日 | M4: 備考 | N4: 工数（人月）
O5: 4月 | Y5: 5月 | AI5: 6月 | AS5: 7月 | BC5: 8月 | BM5: 9月 | BW5: 10月 | CG5: 11月 | CQ5: 12月 | CX5: 1月 | DE5: 2月 | DL5: 3月
O6: TZA | P6: AMTZ | Q6: TSO | R6: NCM | S6: IKK | T6: MMH | U6: KBN | V6: SMZK | W6: SYA | X6: MHS | Y6: TZA | Z6: AMTZ | AA6: TSO | AB6: NCM | AC6: IKK | AD6: MMH | AE6: KBN | AF6: SMZK | AG6: SYA | AH6: MHS | AI6: TZA | AJ6: AMTZ | AK6: TSO | AL6: NCM | AM6: IKK | AN6: MMH | AO6: KBN | AP6: SMZK | AQ6: SYA | AR6: MHS | AS6: TZA | AT6: AMTZ | AU6: TSO | AV6: NCM | AW6: IKK | AX6: MMH | AY6: KBN | AZ6: SMZK | BA6: SYA | BB6: MHS | BC6: TZA | BD6: AMTZ | BE6: TSO | BF6: NCM | BG6: IKK | BH6: MMH | BI6: KBN | BJ6: SMZK | BK6: SYA | BL6: MHS | BM6: TZA | BN6: AMTZ | BO6: TSO | BP6: NCM | BQ6: IKK | BR6: MMH | BS6: KBN | BT6: SMZK | BU6: SYA | BV6: MHS | BW6: TZA | BX6: AMTZ | BY6: TSO | BZ6: NCM | CA6: IKK | CB6: MMH | CC6: KBN | CD6: SMZK | CE6: SYA | CF6: MHS | CG6: TZA | CH6: AMTZ | CI6: TSO | CJ6: NCM | CK6: IKK | CL6: MMH | CM6: KBN | CN6: SMZK | CO6: SYA | CP6: MHS | CQ6: TZA | CR6: AMTZ | CS6: TSO | CT6: NCM | CU6: MMH | CV6: SMZK | CW6: SYA | CX6: TZA | CY6: AMTZ | CZ6: TSO | DA6: NCM | DB6: MMH | DC6: SMZK | DD6: SYA | DE6: TZA | DF6: AMTZ | DG6: TSO | DH6: NCM | DI6: MMH | DJ6: SMZK | DK6: SYA | DL6: TZA | DM6: HWY | DN6: SPH | DO6: KSH | DP6: TSO | DQ6: SNNT | DR6: IKK | DS6: KBN
A7: 1 | B7: 着手中 | C7: その他 | D7: 飯田 | E7: BW1 | F7: A5207110 | G7: 【案件依頼】ビルド作業を対応 | H7: =SUM(DE7:DK7) -> 0.47058824 | I7: =SUM(DE8:DK8) -> 0.24313725 | N7: 計画 | O7: =(0)/120 -> 0 | P7: =(0)/120 -> 0 | Q7: =(0)/120 -> 0 | R7: =(21)/120 -> 0.175 | S7: =(21)/120 -> 0.175 | T7: =(0)/120 -> 0 | U7: =(0)/120 -> 0 | V7: =(21)/120 -> 0.175 | W7: =(21)/120 -> 0.175 | X7: =(0)/120 -> 0 | Y7: =(0)/157.5 -> 0 | Z7: =(0)/157.5 -> 0 | AA7: =(10)/157.5 -> 0.063492063 | AB7: =(10)/157.5 -> 0.063492063 | AC7: =(10)/157.5 -> 0.063492063 | AD7: =(0)/157.5 -> 0 | AE7: =(10)/157.5 -> 0.063492063 | AF7: =(10)/157.5 -> 0.063492063 | AG7: =(20)/157.5 -> 0.12698413 | AH7: =(0)/157.5 -> 0 | AI7: =(0)/157.5 -> 0 | AJ7: =(0)/157.5 -> 0 | AK7: =(0)/157.5 -> 0 | AL7: =(12.4)/157.5 -> 0.078730159 | AM7: =(12.4)/157.5 -> 0.078730159 | AN7: =(0)/157.5 -> 0 | AO7: =(12.4)/157.5 -> 0.078730159 | AP7: =(12.4)/157.5 -> 0.078730159 | AQ7: =(12.4)/157.5 -> 0.078730159 | AR7: =(0)/157.5 -> 0 | AS7: =(0)/165 -> 0 | AT7: =(0)/165 -> 0 | AU7: =(12)/165 -> 0.072727273 | AV7: =(12)/165 -> 0.072727273 | AW7: =(10)/165 -> 0.060606061 | AX7: =(0)/165 -> 0 | AY7: =(12)/165 -> 0.072727273 | AZ7: =(12)/165 -> 0.072727273 | BA7: =(12)/165 -> 0.072727273 | BB7: =(0)/165 -> 0 | BC7: =(0)/157.5 -> 0 | BD7: =(0)/157.5 -> 0 | BE7: =(19)/157.5 -> 0.12063492 | BF7: =(10)/157.5 -> 0.063492063 | BG7: =(19)/157.5 -> 0.12063492 | BH7: =(0)/157.5 -> 0 | BI7: =(19)/157.5 -> 0.12063492 | BJ7: =(19)/157.5 -> 0.12063492 | BK7: =(19)/157.5 -> 0.12063492 | BL7: =(0)/157.5 -> 0 | BM7: =(0)/165 -> 0 | BN7: =(0)/165 -> 0 | BO7: =(10)/165 -> 0.060606061 | BP7: =(15)/165 -> 0.090909091 | BQ7: =(0)/165 -> 0 | BR7: =(15)/165 -> 0.090909091 | BS7: =(10)/165 -> 0.060606061 | BT7: =(10)/165 -> 0.060606061 | BU7: =(10)/165 -> 0.060606061 | BV7: =(0)/165 -> 0 | BW7: =(0)/150 -> 0 | BX7: =(0)/150 -> 0 | BY7: =(6)/150 -> 0.04 | BZ7: =(6)/150 -> 0.04 | CA7: =(6)/150 -> 0.04 | CB7: =(6)/150 -> 0.04 | CC7: =(12)/150 -> 0.08 | CD7: =(0)/150 -> 0 | CE7: =(12)/150 -> 0.08 | CF7: =(12)/150 -> 0.08 | CG7: =(0)/135 -> 0 | CH7: =(0)/135 -> 0 | CI7: =(10)/135 -> 0.074074074 | CJ7: =(0)/135 -> 0 | CK7: =(0)/135 -> 0 | CL7: =(10)/135 -> 0.074074074 | CM7: =(0)/135 -> 0 | CN7: =(10)/135 -> 0.074074074 | CO7: =(10)/135 -> 0.074074074 | CP7: =(0)/135 -> 0 | CQ7: =(0)/150 -> 0 | CR7: =(0)/150 -> 0 | CS7: =(0)/150 -> 0 | CT7: =(10)/150 -> 0.066666667 | CU7: =(10)/150 -> 0.066666667 | CV7: =(10)/150 -> 0.066666667 | CW7: =(5)/150 -> 0.033333333 | CX7: =(0)/157.5 -> 0 | CY7: =(15)/157.5 -> 0.095238095 | CZ7: =(0)/157.5 -> 0 | DA7: =(10)/157.5 -> 0.063492063 | DB7: =(10)/157.5 -> 0.063492063 | DC7: =(10)/157.5 -> 0.063492063 | DD7: =(0)/157.5 -> 0 | DE7: =(0)/127.5 -> 0 | DF7: =(10)/127.5 -> 0.078431373 | DG7: =(10)/127.5 -> 0.078431373 | DH7: =(10)/127.5 -> 0.078431373 | DI7: =(10)/127.5 -> 0.078431373 | DJ7: =(10)/127.5 -> 0.078431373 | DK7: =(10)/127.5 -> 0.078431373 | DL7: =0/142.5 -> 0 | DM7: =0/142.5 -> 0 | DN7: =0/142.5 -> 0 | DO7: =0/142.5 -> 0 | DP7: =0/142.5 -> 0 | DQ7: =0/172.5 -> 0 | DR7: =0/172.5 -> 0 | DS7: =0/172.5 -> 0
N8: 実績 | O8: =(0)/120 -> 0 | P8: =(0)/120 -> 0 | Q8: =(0)/120 -> 0 | R8: =(0+6+4+6)/120 -> 0.13333333 | S8: =(5+7+2+4)/120 -> 0.15 | T8: =(0)/120 -> 0 | U8: =(0)/120 -> 0 | V8: =(5+5+5.5+2)/120 -> 0.14583333 | W8: =(0+9+5+12)/120 -> 0.21666667 | X8: =(0)/120 -> 0 | Y8: =(0)/157.5 -> 0 | Z8: =(0)/157.5 -> 0 | AA8: =(0+5)/157.5 -> 0.031746032 | AB8: =(2)/157.5 -> 0.012698413 | AC8: =(6+3)/157.5 -> 0.057142857 | AD8: =(0)/157.5 -> 0 | AE8: =(4+6+4)/157.5 -> 0.088888889 | AF8: =(2+6+4.5)/157.5 -> 0.079365079 | AG8: =(3+5+7+4+2)/157.5 -> 0.13333333 | AH8: =(0)/157.5 -> 0 | AI8: =(0)/157.5 -> 0 | AJ8: =(0)/157.5 -> 0 | AK8: =(0)/157.5 -> 0 | AL8: =(0+6+4)/157.5 -> 0.063492063 | AM8: =(6+3.5+5+5)/157.5 -> 0.12380952 | AN8: =(0)/157.5 -> 0 | AO8: =(0+6+4)/157.5 -> 0.063492063 | AP8: =(0+4+4)/157.5 -> 0.050793651 | AQ8: =(0+6+4+2)/157.5 -> 0.076190476 | AR8: =(0)/157.5 -> 0 | AS8: =(0)/165 -> 0 | AT8: =(0)/165 -> 0 | AU8: =(2+3+3+1)/165 -> 0.054545455 | AV8: =(4+4+4+4)/165 -> 0.096969697 | AW8: =(0+4+2)/165 -> 0.036363636 | AX8: =(0)/165 -> 0 | AY8: =(0+4+6+2)/165 -> 0.072727273 | AZ8: =(0+4+3)/165 -> 0.042424242 | BA8: =(3+2+5+4)/165 -> 0.084848485 | BB8: =(0)/165 -> 0 | BC8: =(0)/157.5 -> 0 | BD8: =(0)/157.5 -> 0 | BE8: =(1+13+8)/157.5 -> 0.13968254 | BF8: =(2+5)/157.5 -> 0.044444444 | BG8: =(5+11+4)/157.5 -> 0.12698413 | BH8: =(0)/157.5 -> 0 | BI8: =(9+6)/157.5 -> 0.095238095 | BJ8: =(8+5+9+6)/157.5 -> 0.17777778 | BK8: =(6+6)/157.5 -> 0.076190476 | BL8: =(0)/157.5 -> 0 | BM8: =(0)/165 -> 0 | BN8: =(0)/165 -> 0 | BO8: =(0+3.5)/165 -> 0.021212121 | BP8: =(8.5+5.5)/165 -> 0.084848485 | BQ8: =(0)/165 -> 0 | BR8: =(6+6+3)/165 -> 0.090909091 | BS8: =(6+4)/165 -> 0.060606061 | BT8: =(6+4+2)/165 -> 0.072727273 | BU8: =(0+6)/165 -> 0.036363636 | BV8: =(0)/165 -> 0 | BW8: =(0)/150 -> 0 | BX8: =(0)/150 -> 0 | BY8: =(3.5+4)/150 -> 0.05 | BZ8: =(0+6+4)/150 -> 0.066666667 | CA8: =(0+3+3)/150 -> 0.04 | CB8: =(0+3)/150 -> 0.02 | CC8: =(0+6+4)/150 -> 0.066666667 | CD8: =(0)/150 -> 0 | CE8: =(3+6+1)/150 -> 0.066666667 | CF8: =(0+8+5)/150 -> 0.086666667 | CG8: =(0)/135 -> 0 | CH8: =(0)/135 -> 0 | CI8: =(0+4+3.5)/135 -> 0.055555556 | CJ8: =(0)/135 -> 0 | CK8: =(0)/135 -> 0 | CL8: =(6)/135 -> 0.044444444 | CM8: =(0)/135 -> 0 | CN8: =(6)/135 -> 0.044444444 | CO8: =(0+5+5)/135 -> 0.074074074 | CP8: =(0)/135 -> 0 | CQ8: =(0)/150 -> 0 | CR8: =(0)/150 -> 0 | CS8: =(0)/150 -> 0 | CT8: =(6+2)/150 -> 0.053333333 | CU8: =(0+2+6)/150 -> 0.053333333 | CV8: =(6+4)/150 -> 0.066666667 | CW8: =(0+6)/150 -> 0.04 | CX8: =(0)/157.5 -> 0 | CY8: =(10.5+5)/157.5 -> 0.098412698 | CZ8: =(0)/157.5 -> 0 | DA8: =(0+6+4)/157.5 -> 0.063492063 | DB8: =(6)/157.5 -> 0.038095238 | DC8: =(0+6+4)/157.5 -> 0.063492063 | DD8: =(0)/157.5 -> 0 | DE8: =(0)/127.5 -> 0 | DF8: =(0+2.5+5.5)/127.5 -> 0.062745098 | DG8: =(0+2+4)/127.5 -> 0.047058824 | DH8: =(0)/127.5 -> 0 | DI8: =(6+4)/127.5 -> 0.078431373 | DJ8: =(0)/127.5 -> 0 | DK8: =(4+3)/127.5 -> 0.054901961 | DL8: =0/142.5 -> 0 | DM8: =0/142.5 -> 0 | DN8: =0/142.5 -> 0 | DO8: =0/142.5 -> 0 | DP8: =0/142.5 -> 0 | DQ8: =0/172.5 -> 0 | DR8: =0/172.5 -> 0 | DS8: =0/172.5 -> 0
A9: 2 | B9: 完了 | C9: その他 | D9: 坂野 | E9: PL6 | F9: PBxxxxxxxx | G9: 【PLATE】対面WEB_初期フォーカス改善対応 | H9: =SUM(Y9:AH9) -> 0 | I9: =SUM(Y10:AH10) -> 0 | N9: 計画 | O9: =(0)/120 -> 0 | P9: =(0)/120 -> 0 | Q9: =(0)/120 -> 0 | R9: =(0)/120 -> 0 | S9: =(0)/120 -> 0 | T9: =(0)/120 -> 0 | U9: =(0)/120 -> 0 | V9: =(0)/120 -> 0 | ... X9: =(0)/120 -> 0 | Y9: =(0)/157.5 -> 0 | Z9: =(0)/157.5 -> 0 | AA9: =(0)/157.5 -> 0 | AB9: =(0)/157.5 -> 0 | AC9: =(0)/157.5 -> 0 | AD9: =(0)/157.5 -> 0 | AE9: =(0)/157.5 -> 0 | AF9: =(0)/157.5 -> 0 | ... AH9: =(0)/157.5 -> 0 | AI9: =0/165 -> 0 | AJ9: =0/165 -> 0 | AK9: =0/165 -> 0 | AL9: =0/165 -> 0 | AM9: =0/165 -> 0 | AN9: =0/165 -> 0 | AO9: =0/165 -> 0 | AP9: =0/165 -> 0 | ... AR9: =0/165 -> 0 | AS9: =0/157.5 -> 0 | AT9: =0/157.5 -> 0 | AU9: =0/157.5 -> 0 | AV9: =0/157.5 -> 0 | AW9: =0/157.5 -> 0 | AX9: =0/165 -> 0 | AY9: =0/165 -> 0 | AZ9: =0/165 -> 0 | BA9: =0/165 -> 0 | BB9: =0/165 -> 0 | BC9: =0/157.5 -> 0 | BD9: =0/157.5 -> 0 | BE9: =0/157.5 -> 0 | BF9: =0/157.5 -> 0 | BG9: =0/157.5 -> 0 | BH9: =0/157.5 -> 0 | BI9: =0/157.5 -> 0 | BJ9: =0/165 -> 0 | BK9: =0/165 -> 0 | BL9: =0/165 -> 0 | BM9: =0/172.5 -> 0 | BN9: =0/172.5 -> 0 | BO9: =0/172.5 -> 0 | BP9: =0/172.5 -> 0 | BQ9: =0/172.5 -> 0 | BR9: =0/172.5 -> 0 | BS9: =0/172.5 -> 0 | BV9: =0/172.5 -> 0 | BW9: =0/142.5 -> 0 | BX9: =(0)/165 -> 0 | BY9: =(0)/165 -> 0 | BZ9: =(0)/165 -> 0 | CA9: =(0)/165 -> 0 | CB9: =(0)/165 -> 0 | CC9: =(0)/165 -> 0 | CD9: =(0)/165 -> 0 | CE9: =(0)/165 -> 0 | CF9: =(0)/165 -> 0 | CG9: =0/142.5 -> 0 | CH9: =0/142.5 -> 0 | CI9: =0/142.5 -> 0 | CJ9: =0/142.5 -> 0 | CK9: =0/142.5 -> 0 | CL9: =0/172.5 -> 0 | CM9: =0/172.5 -> 0 | CN9: =0/172.5 -> 0 | CO9: =0/172.5 -> 0 | CP9: =0/172.5 -> 0 | CQ9: =0/157.5 -> 0 | CR9: =0/157.5 -> 0 | CS9: =0/157.5 -> 0 | CT9: =0/157.5 -> 0 | CU9: =0/157.5 -> 0 | CV9: =0/172.5 -> 0 | CW9: =0/172.5 -> 0 | CX9: =0/157.5 -> 0 | CY9: =0/157.5 -> 0 | CZ9: =0/157.5 -> 0 | DA9: =0/157.5 -> 0 | DB9: =0/157.5 -> 0 | DC9: =0/172.5 -> 0 | DD9: =0/172.5 -> 0 | DE9: =0/127.5 -> 0 | DF9: =0/127.5 -> 0 | DG9: =0/127.5 -> 0 | DH9: =0/127.5 -> 0 | DI9: =0/127.5 -> 0 | DJ9: =0/172.5 -> 0 | DK9: =0/172.5 -> 0 | DL9: =0/142.5 -> 0 | DM9: =0/142.5 -> 0 | DN9: =0/142.5 -> 0 | DO9: =0/142.5 -> 0 | DP9: =0/142.5 -> 0 | DQ9: =0/172.5 -> 0 | DR9: =0/172.5 -> 0 | DS9: =0/172.5 -> 0
N10: 実績 | O10: =(0)/120 -> 0 | P10: =(0)/120 -> 0 | Q10: =(0)/120 -> 0 | R10: =(0)/120 -> 0 | S10: =(0)/120 -> 0 | T10: =(0)/120 -> 0 | U10: =(0)/120 -> 0 | V10: =(0)/120 -> 0 | ... X10: =(0)/120 -> 0 | Y10: =(0)/157.5 -> 0 | Z10: =(0)/157.5 -> 0 | AA10: =(0)/157.5 -> 0 | AB10: =(0)/157.5 -> 0 | AC10: =(0)/157.5 -> 0 | AD10: =(0)/157.5 -> 0 | AE10: =(0)/157.5 -> 0 | AF10: =(0)/157.5 -> 0 | ... AH10: =(0)/157.5 -> 0 | AI10: =0/165 -> 0 | AJ10: =0/165 -> 0 | AK10: =0/165 -> 0 | AL10: =0/165 -> 0 | AM10: =0/165 -> 0 | AN10: =0/165 -> 0 | AO10: =0/165 -> 0 | AP10: =0/165 -> 0 | ... AR10: =0/165 -> 0 | AS10: =0/157.5 -> 0 | AT10: =0/157.5 -> 0 | AU10: =0/157.5 -> 0 | AV10: =0/157.5 -> 0 | AW10: =0/157.5 -> 0 | AX10: =0/165 -> 0 | AY10: =0/165 -> 0 | AZ10: =0/165 -> 0 | BA10: =0/165 -> 0 | BB10: =0/165 -> 0 | BC10: =0/157.5 -> 0 | BD10: =0/157.5 -> 0 | BE10: =0/157.5 -> 0 | BF10: =0/157.5 -> 0 | BG10: =0/157.5 -> 0 | BH10: =0/157.5 -> 0 | BI10: =0/157.5 -> 0 | BJ10: =0/165 -> 0 | BK10: =0/165 -> 0 | BL10: =0/165 -> 0 | BM10: =0/172.5 -> 0 | BN10: =0/172.5 -> 0 | BO10: =0/172.5 -> 0 | BP10: =0/172.5 -> 0 | BQ10: =0/172.5 -> 0 | BR10: =0/172.5 -> 0 | BS10: =0/172.5 -> 0 | BV10: =0/172.5 -> 0 | BW10: =0/142.5 -> 0 | BX10: =(0)/165 -> 0 | BY10: =(0)/165 -> 0 | BZ10: =(0)/165 -> 0 | CA10: =(0)/165 -> 0 | CB10: =(0)/165 -> 0 | CC10: =(0)/165 -> 0 | CD10: =(0)/165 -> 0 | CE10: =(0)/165 -> 0 | CF10: =(0)/165 -> 0 | CG10: =0/142.5 -> 0 | CH10: =0/142.5 -> 0 | CI10: =0/142.5 -> 0 | CJ10: =0/142.5 -> 0 | CK10: =0/142.5 -> 0 | CL10: =0/172.5 -> 0 | CM10: =0/172.5 -> 0 | CN10: =0/172.5 -> 0 | CO10: =0/172.5 -> 0 | CP10: =0/172.5 -> 0 | CQ10: =0/157.5 -> 0 | CR10: =0/157.5 -> 0 | CS10: =0/157.5 -> 0 | CT10: =0/157.5 -> 0 | CU10: =0/157.5 -> 0 | CV10: =0/172.5 -> 0 | CW10: =0/172.5 -> 0 | CX10: =0/157.5 -> 0 | CY10: =0/157.5 -> 0 | CZ10: =0/157.5 -> 0 | DA10: =0/157.5 -> 0 | DB10: =0/157.5 -> 0 | DC10: =0/172.5 -> 0 | DD10: =0/172.5 -> 0 | DE10: =0/127.5 -> 0 | DF10: =0/127.5 -> 0 | DG10: =0/127.5 -> 0 | DH10: =0/127.5 -> 0 | DI10: =0/127.5 -> 0 | DJ10: =0/172.5 -> 0 | DK10: =0/172.5 -> 0 | DL10: =0/142.5 -> 0 | DM10: =0/142.5 -> 0 | DN10: =0/142.5 -> 0 | DO10: =0/142.5 -> 0 | DP10: =0/142.5 -> 0 | DQ10: =0/172.5 -> 0 | DR10: =0/172.5 -> 0 | DS10: =0/172.5 -> 0
A11: 3 | B11: 完了 | C11: その他 | D11: 山本 | E11: WA2 | G11: 【開発依頼】作業の自動化_UATヘルスチェック | H11: =SUM(CG11:CP11) -> 0 | I11: =SUM(CG12:CP12) -> 0 | N11: 計画 | O11: =(0)/120 -> 0 | P11: =(0)/120 -> 0 | Q11: =(39.25)/120 -> 0.32708333 | R11: =(39.25)/120 -> 0.32708333 | S11: =(0)/120 -> 0 | T11: =(0)/120 -> 0 | U11: =(39.25)/120 -> 0.32708333 | V11: =(0)/120 -> 0 | W11: =(39.25)/120 -> 0.32708333 | X11: =(0)/120 -> 0 | Y11: =(30)/157.5 -> 0.19047619 | Z11: =(30)/157.5 -> 0.19047619 | AA11: =(30)/157.5 -> 0.19047619 | AB11: =(0)/157.5 -> 0 | AC11: =(30)/157.5 -> 0.19047619 | AD11: =(30)/157.5 -> 0.19047619 | AE11: =(60)/157.5 -> 0.38095238 | AF11: =(30)/157.5 -> 0.19047619 | AG11: =(70)/157.5 -> 0.44444444 | AH11: =(0)/157.5 -> 0 | AI11: =(0)/157.5 -> 0 | AJ11: =(0)/157.5 -> 0 | AK11: =(0)/157.5 -> 0 | AL11: =(0)/157.5 -> 0 | AM11: =(0)/157.5 -> 0 | AN11: =(0)/157.5 -> 0 | AO11: =(0)/157.5 -> 0 | AP11: =(0)/157.5 -> 0 | AQ11: =(3)/157.5 -> 0.019047619 | AR11: =(0)/157.5 -> 0 | AS11: =(0)/165 -> 0 | AT11: =(0)/165 -> 0 | AU11: =(37.5)/165 -> 0.22727273 | AV11: =(0)/165 -> 0 | AW11: =(0)/165 -> 0 | AX11: =(0)/165 -> 0 | AY11: =(0)/165 -> 0 | AZ11: =(0)/165 -> 0 | BA11: =(37.5)/165 -> 0.22727273 | BB11: =(0)/165 -> 0 | BC11: =(0)/157.5 -> 0 | BD11: =(0)/157.5 -> 0 | BE11: =(22.5)/157.5 -> 0.14285714 | BF11: =(0)/157.5 -> 0 | BG11: =(0)/157.5 -> 0 | BH11: =(0)/157.5 -> 0 | BI11: =(0)/157.5 -> 0 | BJ11: =(0)/157.5 -> 0 | BK11: =(22.5)/157.5 -> 0.14285714 | BL11: =(0)/157.5 -> 0 | BM11: =(0)/165 -> 0 | BN11: =(0)/165 -> 0 | BO11: =(50)/165 -> 0.3030303 | BP11: =(0)/165 -> 0 | BQ11: =(0)/165 -> 0 | BR11: =(0)/165 -> 0 | BS11: =(0)/165 -> 0 | BT11: =(0)/165 -> 0 | BU11: =(50)/165 -> 0.3030303 | BV11: =(0)/165 -> 0 | BW11: =(0)/150 -> 0 | BX11: =(0)/150 -> 0 | BY11: =(12)/150 -> 0.08 | BZ11: =(12)/150 -> 0.08 | CA11: =(0)/150 -> 0 | CB11: =(0)/150 -> 0 | CC11: =(0)/150 -> 0 | CD11: =(0)/150 -> 0 | CE11: =(21)/150 -> 0.14 | CF11: =(0)/150 -> 0 | CG11: =(0)/135 -> 0 | CH11: =(0)/135 -> 0 | CI11: =(0)/135 -> 0 | CJ11: =(0)/135 -> 0 | CK11: =(0)/135 -> 0 | CL11: =(0)/135 -> 0 | CM11: =(0)/135 -> 0 | CN11: =(0)/135 -> 0 | ... CP11: =(0)/135 -> 0 | CQ11: =0/157.5 -> 0 | CR11: =0/157.5 -> 0 | CS11: =0/157.5 -> 0 | CT11: =0/157.5 -> 0 | CU11: =0/157.5 -> 0 | CV11: =0/172.5 -> 0 | CW11: =0/172.5 -> 0 | CX11: =0/157.5 -> 0 | CY11: =0/157.5 -> 0 | CZ11: =0/157.5 -> 0 | DA11: =0/157.5 -> 0 | DB11: =0/157.5 -> 0 | DC11: =0/172.5 -> 0 | DD11: =0/172.5 -> 0 | DE11: =0/127.5 -> 0 | DF11: =0/127.5 -> 0 | DG11: =0/127.5 -> 0 | DH11: =0/127.5 -> 0 | DI11: =0/127.5 -> 0 | DJ11: =0/172.5 -> 0 | DK11: =0/172.5 -> 0 | DL11: =0/142.5 -> 0 | DM11: =0/142.5 -> 0 | DN11: =0/142.5 -> 0 | DO11: =0/142.5 -> 0 | DP11: =0/142.5 -> 0 | DQ11: =0/172.5 -> 0 | DR11: =0/172.5 -> 0 | DS11: =0/172.5 -> 0
N12: 実績 | O12: =(0)/120 -> 0 | P12: =(0)/120 -> 0 | Q12: =(0+7+13.5+7+28)/120 -> 0.4625 | R12: =(0+5)/120 -> 0.041666667 | S12: =(0)/120 -> 0 | T12: =(0)/120 -> 0 | U12: =(0+12+14+14+33)/120 -> 0.60833333 | V12: =(0)/120 -> 0 | W12: =(19)/120 -> 0.15833333 | X12: =(0)/120 -> 0 | Y12: =(0+1.5+2.5+11.5)/157.5 -> 0.098412698 | Z12: =(0+12+3.5)/157.5 -> 0.098412698 | AA12: =(17+15+24.5+34.5)/157.5 -> 0.57777778 | AB12: =(0)/157.5 -> 0 | AC12: =(0+15+5.5)/157.5 -> 0.13015873 | AD12: =(0+5+4.5)/157.5 -> 0.06031746 | AE12: =(17.5+8+21.5+18.5)/157.5 -> 0.41587302 | AF12: =(0+15)/157.5 -> 0.095238095 | AG12: =(18+21+14+19.5+2)/157.5 -> 0.47301587 | AH12: =(0)/157.5 -> 0 | AI12: =(0)/157.5 -> 0 | AJ12: =(0)/157.5 -> 0 | AK12: =(0)/157.5 -> 0 | AL12: =(0)/157.5 -> 0 | AM12: =(0)/157.5 -> 0 | AN12: =(0)/157.5 -> 0 | AO12: =(0)/157.5 -> 0 | AP12: =(0)/157.5 -> 0 | AQ12: =(0+2.5)/157.5 -> 0.015873016 | AR12: =(0)/157.5 -> 0 | AS12: =(0)/165 -> 0 | AT12: =(0)/165 -> 0 | AU12: =(6+6+7+14.5+2)/165 -> 0.21515152 | AV12: =(0)/165 -> 0 | AW12: =(0)/165 -> 0 | AX12: =(0)/165 -> 0 | AY12: =(0)/165 -> 0 | AZ12: =(0)/165 -> 0 | BA12: =(3+8.5+8+8+6+3)/165 -> 0.22121212 | BB12: =(0)/165 -> 0 | BC12: =(0)/157.5 -> 0 | BD12: =(0)/157.5 -> 0 | BE12: =(13+3+5)/157.5 -> 0.13333333 | BF12: =(0)/157.5 -> 0 | BG12: =(0)/157.5 -> 0 | BH12: =(0)/157.5 -> 0 | BI12: =(0)/157.5 -> 0 | BJ12: =(0)/157.5 -> 0 | BK12: =(13.5+6.5)/157.5 -> 0.12698413 | BL12: =(0)/157.5 -> 0 | BM12: =(1+5.5+8.5)/165 -> 0.090909091 | BN12: =(0)/165 -> 0 | BO12: =(9+17+6.5)/165 -> 0.1969697 | BP12: =(0)/165 -> 0 | BQ12: =(0)/165 -> 0 | BR12: =(0)/165 -> 0 | BS12: =(0)/165 -> 0 | BT12: =(0)/165 -> 0 | BU12: =(11.5+33+10)/165 -> 0.33030303 | BV12: =(0)/165 -> 0 | BW12: =(0)/150 -> 0 | BX12: =(0)/150 -> 0 | BY12: =(0+3.5+9)/150 -> 0.083333333 | BZ12: =(0+9.5)/150 -> 0.063333333 | CA12: =(0)/150 -> 0 | CB12: =(0)/150 -> 0 | CC12: =(0)/150 -> 0 | CD12: =(0)/150 -> 0 | CE12: =(0+5+14+2)/150 -> 0.14 | CF12: =(0)/150 -> 0 | CG12: =(0)/135 -> 0 | CH12: =(0)/135 -> 0 | CI12: =(0)/135 -> 0 | CJ12: =(0)/135 -> 0 | CK12: =(0)/135 -> 0 | CL12: =(0)/135 -> 0 | CM12: =(0)/135 -> 0 | CN12: =(0)/135 -> 0 | ... CP12: =(0)/135 -> 0 | CQ12: =0/157.5 -> 0 | CR12: =0/157.5 -> 0 | CS12: =0/157.5 -> 0 | CT12: =0/157.5 -> 0 | CU12: =0/157.5 -> 0 | CV12: =0/172.5 -> 0 | CW12: =0/172.5 -> 0 | CX12: =0/157.5 -> 0 | CY12: =0/157.5 -> 0 | CZ12: =0/157.5 -> 0 | DA12: =0/157.5 -> 0 | DB12: =0/157.5 -> 0 | DC12: =0/172.5 -> 0 | DD12: =0/172.5 -> 0 | DE12: =0/127.5 -> 0 | DF12: =0/127.5 -> 0 | DG12: =0/127.5 -> 0 | DH12: =0/127.5 -> 0 | DI12: =0/127.5 -> 0 | DJ12: =0/172.5 -> 0 | DK12: =0/172.5 -> 0 | DL12: =0/142.5 -> 0 | DM12: =0/142.5 -> 0 | DN12: =0/142.5 -> 0 | DO12: =0/142.5 -> 0 | DP12: =0/142.5 -> 0 | DQ12: =0/172.5 -> 0 | DR12: =0/172.5 -> 0 | DS12: =0/172.5 -> 0
A13: 4 | B13: 完了 | C13: 定型 | D13: 山本 | E13: F180 | F13: PB00201841 | G13: 【定型】定時定額の注文画面での文言追加 | H13: =SUM(CG13:CP13) -> 0 | I13: =SUM(CG14:CP14) -> 0 | N13: 計画 | O13: =(0)/120 -> 0 | P13: =(9)/120 -> 0.075 | Q13: =(0)/120 -> 0 | R13: =(9)/120 -> 0.075 | S13: =(0)/120 -> 0 | T13: =(0)/120 -> 0 | U13: =(0)/120 -> 0 | V13: =(0)/120 -> 0 | W13: =(0)/120 -> 0 | X13: =(0)/120 -> 0 | Y13: =(0)/157.5 -> 0 | Z13: =(0)/157.5 -> 0 | AA13: =(0)/157.5 -> 0 | AB13: =(0)/157.5 -> 0 | AC13: =(0)/157.5 -> 0 | AD13: =(0)/157.5 -> 0 | AE13: =(0)/157.5 -> 0 | AF13: =(0)/157.5 -> 0 | ... AR13: =(0)/157.5 -> 0 | AS13: =(0)/165 -> 0 | AT13: =(0)/165 -> 0 | AU13: =(0)/165 -> 0 | AV13: =(0)/165 -> 0 | AW13: =(0)/165 -> 0 | AX13: =(0)/165 -> 0 | AY13: =(0)/165 -> 0 | AZ13: =(0)/165 -> 0 | ... BB13: =(0)/165 -> 0 | BC13: =(0)/157.5 -> 0 | BD13: =(0)/157.5 -> 0 | BE13: =(0)/157.5 -> 0 | BF13: =(0)/157.5 -> 0 | BG13: =(0)/157.5 -> 0 | BH13: =(0)/157.5 -> 0 | BI13: =(0)/157.5 -> 0 | BJ13: =(0)/157.5 -> 0 | ... BL13: =(0)/157.5 -> 0 | BM13: =(0)/165 -> 0 | BN13: =(0)/165 -> 0 | BO13: =(0)/165 -> 0 | BP13: =(0)/165 -> 0 | BQ13: =(0)/165 -> 0 | BR13: =(0)/165 -> 0 | BS13: =(0)/165 -> 0 | BT13: =(0)/165 -> 0 | ... BV13: =(0)/165 -> 0 | BW13: =(0)/150 -> 0 | BX13: =(0)/150 -> 0 | BY13: =(0)/150 -> 0 | BZ13: =(0)/150 -> 0 | CA13: =(0)/150 -> 0 | CB13: =(0)/150 -> 0 | CC13: =(0)/150 -> 0 | CD13: =(0)/150 -> 0 | ... CF13: =(0)/150 -> 0 | CG13: =(0)/135 -> 0 | CH13: =(0)/135 -> 0 | CI13: =(0)/135 -> 0 | CJ13: =(0)/135 -> 0 | CK13: =(0)/135 -> 0 | CL13: =(0)/135 -> 0 | CM13: =(0)/135 -> 0 | CN13: =(0)/135 -> 0 | ... CP13: =(0)/135 -> 0 | CQ13: =0/157.5 -> 0 | CR13: =0/157.5 -> 0 | CS13: =0/157.5 -> 0 | CT13: =0/157.5 -> 0 | CU13: =0/157.5 -> 0 | CV13: =0/172.5 -> 0 | CW13: =0/172.5 -> 0 | CX13: =0/157.5 -> 0 | CY13: =0/157.5 -> 0 | CZ13: =0/157.5 -> 0 | DA13: =0/157.5 -> 0 | DB13: =0/157.5 -> 0 | DC13: =0/172.5 -> 0 | DD13: =0/172.5 -> 0 | DE13: =0/127.5 -> 0 | DF13: =0/127.5 -> 0 | DG13: =0/127.5 -> 0 | DH13: =0/127.5 -> 0 | DI13: =0/127.5 -> 0 | DJ13: =0/172.5 -> 0 | DK13: =0/172.5 -> 0 | DL13: =0/142.5 -> 0 | DM13: =0/142.5 -> 0 | DN13: =0/142.5 -> 0 | DO13: =0/142.5 -> 0 | DP13: =0/142.5 -> 0 | DQ13: =0/172.5 -> 0 | DR13: =0/172.5 -> 0 | DS13: =0/172.5 -> 0
N14: 実績 | O14: =(0)/120 -> 0 | P14: =(0.5+1)/120 -> 0.0125 | Q14: =(0)/120 -> 0 | R14: =(14+1.5)/120 -> 0.12916667 | S14: =(0)/120 -> 0 | T14: =(0)/120 -> 0 | U14: =(0)/120 -> 0 | V14: =(0)/120 -> 0 | W14: =(0)/120 -> 0 | X14: =(0)/120 -> 0 | Y14: =(0)/157.5 -> 0 | Z14: =(0)/157.5 -> 0 | AA14: =(0)/157.5 -> 0 | AB14: =(0)/157.5 -> 0 | AC14: =(0)/157.5 -> 0 | AD14: =(0)/157.5 -> 0 | AE14: =(0)/157.5 -> 0 | AF14: =(0)/157.5 -> 0 | ... AR14: =(0)/157.5 -> 0 | AS14: =(0)/165 -> 0 | AT14: =(0)/165 -> 0 | AU14: =(0)/165 -> 0 | AV14: =(0)/165 -> 0 | AW14: =(0)/165 -> 0 | AX14: =(0)/165 -> 0 | AY14: =(0)/165 -> 0 | AZ14: =(0)/165 -> 0 | ... BB14: =(0)/165 -> 0 | BC14: =(0)/157.5 -> 0 | BD14: =(0)/157.5 -> 0 | BE14: =(0)/157.5 -> 0 | BF14: =(0)/157.5 -> 0 | BG14: =(0)/157.5 -> 0 | BH14: =(0)/157.5 -> 0 | BI14: =(0)/157.5 -> 0 | BJ14: =(0)/157.5 -> 0 | ... BL14: =(0)/157.5 -> 0 | BM14: =(0)/165 -> 0 | BN14: =(0)/165 -> 0 | BO14: =(0)/165 -> 0 | BP14: =(0)/165 -> 0 | BQ14: =(0)/165 -> 0 | BR14: =(0)/165 -> 0 | BS14: =(0)/165 -> 0 | BT14: =(0)/165 -> 0 | ... BV14: =(0)/165 -> 0 | BW14: =(0)/150 -> 0 | BX14: =(0)/150 -> 0 | BY14: =(0)/150 -> 0 | BZ14: =(0)/150 -> 0 | CA14: =(0)/150 -> 0 | CB14: =(0)/150 -> 0 | CC14: =(0)/150 -> 0 | CD14: =(0)/150 -> 0 | ... CF14: =(0)/150 -> 0 | CG14: =(0)/135 -> 0 | CH14: =(0)/135 -> 0 | CI14: =(0)/135 -> 0 | CJ14: =(0)/135 -> 0 | CK14: =(0)/135 -> 0 | CL14: =(0)/135 -> 0 | CM14: =(0)/135 -> 0 | CN14: =(0)/135 -> 0 | ... CP14: =(0)/135 -> 0 | CQ14: =0/157.5 -> 0 | CR14: =0/157.5 -> 0 | CS14: =0/157.5 -> 0 | CT14: =0/157.5 -> 0 | CU14: =0/157.5 -> 0 | CV14: =0/172.5 -> 0 | CW14: =0/172.5 -> 0 | CX14: =0/157.5 -> 0 | CY14: =0/157.5 -> 0 | CZ14: =0/157.5 -> 0 | DA14: =0/157.5 -> 0 | DB14: =0/157.5 -> 0 | DC14: =0/172.5 -> 0 | DD14: =0/172.5 -> 0 | DE14: =0/127.5 -> 0 | DF14: =0/127.5 -> 0 | DG14: =0/127.5 -> 0 | DH14: =0/127.5 -> 0 | DI14: =0/127.5 -> 0 | DJ14: =0/172.5 -> 0 | DK14: =0/172.5 -> 0 | DL14: =0/142.5 -> 0 | DM14: =0/142.5 -> 0 | DN14: =0/142.5 -> 0 | DO14: =0/142.5 -> 0 | DP14: =0/142.5 -> 0 | DQ14: =0/172.5 -> 0 | DR14: =0/172.5 -> 0 | DS14: =0/172.5 -> 0
A15: 5 | B15: 完了 | C15: 定型 | D15: 山田 | E15: F181 | F15: PB00201845 | G15: 【定型】CFDサービス終了に伴う画面修正 | H15: =SUM(CG15:CP15) -> 0 | I15: =SUM(CG16:CP16) -> 0 | N15: 計画 | O15: =(0)/120 -> 0 | P15: =(5)/120 -> 0.041666667 | Q15: =(0)/120 -> 0 | R15: =(0)/120 -> 0 | S15: =(15)/120 -> 0.125 | T15: =(15)/120 -> 0.125 | U15: =(0)/120 -> 0 | V15: =(0)/120 -> 0 | W15: =(0)/120 -> 0 | X15: =(0)/120 -> 0 | Y15: =(0)/157.5 -> 0 | Z15: =(0)/157.5 -> 0 | AA15: =(0)/157.5 -> 0 | AB15: =(0)/157.5 -> 0 | AC15: =(0)/157.5 -> 0 | AD15: =(0)/157.5 -> 0 | AE15: =(0)/157.5 -> 0 | AF15: =(0)/157.5 -> 0 | ... AR15: =(0)/157.5 -> 0 | AS15: =(0)/165 -> 0 | AT15: =(0)/165 -> 0 | AU15: =(0)/165 -> 0 | AV15: =(0)/165 -> 0 | AW15: =(0)/165 -> 0 | AX15: =(0)/165 -> 0 | AY15: =(0)/165 -> 0 | AZ15: =(0)/165 -> 0 | ... BB15: =(0)/165 -> 0 | BC15: =(0)/157.5 -> 0 | BD15: =(0)/157.5 -> 0 | BE15: =(0)/157.5 -> 0 | BF15: =(0)/157.5 -> 0 | BG15: =(0)/157.5 -> 0 | BH15: =(0)/157.5 -> 0 | BI15: =(0)/157.5 -> 0 | BJ15: =(0)/157.5 -> 0 | ... BL15: =(0)/157.5 -> 0 | BM15: =(0)/165 -> 0 | BN15: =(0)/165 -> 0 | BO15: =(0)/165 -> 0 | BP15: =(0)/165 -> 0 | BQ15: =(0)/165 -> 0 | BR15: =(0)/165 -> 0 | BS15: =(0)/165 -> 0 | BT15: =(0)/165 -> 0 | ... BV15: =(0)/165 -> 0 | BW15: =(0)/150 -> 0 | BX15: =(0)/150 -> 0 | BY15: =(0)/150 -> 0 | BZ15: =(0)/150 -> 0 | CA15: =(0)/150 -> 0 | CB15: =(0)/150 -> 0 | CC15: =(0)/150 -> 0 | CD15: =(0)/150 -> 0 | ... CF15: =(0)/150 -> 0 | CG15: =(0)/135 -> 0 | CH15: =(0)/135 -> 0 | CI15: =(0)/135 -> 0 | CJ15: =(0)/135 -> 0 | CK15: =(0)/135 -> 0 | CL15: =(0)/135 -> 0 | CM15: =(0)/135 -> 0 | CN15: =(0)/135 -> 0 | ... CP15: =(0)/135 -> 0 | CQ15: =0/157.5 -> 0 | CR15: =0/157.5 -> 0 | CS15: =0/157.5 -> 0 | CT15: =0/157.5 -> 0 | CU15: =0/157.5 -> 0 | CV15: =0/172.5 -> 0 | CW15: =0/172.5 -> 0 | CX15: =0/157.5 -> 0 | CY15: =0/157.5 -> 0 | CZ15: =0/157.5 -> 0 | DA15: =0/157.5 -> 0 | DB15: =0/157.5 -> 0 | DC15: =0/172.5 -> 0 | DD15: =0/172.5 -> 0 | DE15: =0/127.5 -> 0 | DF15: =0/127.5 -> 0 | DG15: =0/127.5 -> 0 | DH15: =0/127.5 -> 0 | DI15: =0/127.5 -> 0 | DJ15: =0/172.5 -> 0 | DK15: =0/172.5 -> 0 | DL15: =0/142.5 -> 0 | DM15: =0/142.5 -> 0 | DN15: =0/142.5 -> 0 | DO15: =0/142.5 -> 0 | DP15: =0/142.5 -> 0 | DQ15: =0/172.5 -> 0 | DR15: =0/172.5 -> 0 | DS15: =0/172.5 -> 0
N16: 実績 | O16: =(0)/120 -> 0 | P16: =(0.5+3+1)/120 -> 0.0375 | Q16: =(0)/120 -> 0 | R16: =(0)/120 -> 0 | S16: =(5+9.5)/120 -> 0.12083333 | T16: =(12+3)/120 -> 0.125 | U16: =(0)/120 -> 0 | V16: =(0)/120 -> 0 | W16: =(0)/120 -> 0 | X16: =(0)/120 -> 0 | Y16: =(0)/157.5 -> 0 | Z16: =(0)/157.5 -> 0 | AA16: =(0)/157.5 -> 0 | AB16: =(0)/157.5 -> 0 | AC16: =(0)/157.5 -> 0 | AD16: =(0)/157.5 -> 0 | AE16: =(0)/157.5 -> 0 | AF16: =(0)/157.5 -> 0 | ... AR16: =(0)/157.5 -> 0 | AS16: =(0)/165 -> 0 | AT16: =(0)/165 -> 0 | AU16: =(0)/165 -> 0 | AV16: =(0)/165 -> 0 | AW16: =(0)/165 -> 0 | AX16: =(0)/165 -> 0 | AY16: =(0)/165 -> 0 | AZ16: =(0)/165 -> 0 | ... BB16: =(0)/165 -> 0 | BC16: =(0)/157.5 -> 0 | BD16: =(0)/157.5 -> 0 | BE16: =(0)/157.5 -> 0 | BF16: =(0)/157.5 -> 0 | BG16: =(0)/157.5 -> 0 | BH16: =(0)/157.5 -> 0 | BI16: =(0)/157.5 -> 0 | BJ16: =(0)/157.5 -> 0 | ... BL16: =(0)/157.5 -> 0 | BM16: =(0)/165 -> 0 | BN16: =(0)/165 -> 0 | BO16: =(0)/165 -> 0 | BP16: =(0)/165 -> 0 | BQ16: =(0)/165 -> 0 | BR16: =(0)/165 -> 0 | BS16: =(0)/165 -> 0 | BT16: =(0)/165 -> 0 | ... BV16: =(0)/165 -> 0 | BW16: =(0)/150 -> 0 | BX16: =(0)/150 -> 0 | BY16: =(0)/150 -> 0 | BZ16: =(0)/150 -> 0 | CA16: =(0)/150 -> 0 | CB16: =(0)/150 -> 0 | CC16: =(0)/150 -> 0 | CD16: =(0)/150 -> 0 | ... CF16: =(0)/150 -> 0 | CG16: =(0)/135 -> 0 | CH16: =(0)/135 -> 0 | CI16: =(0)/135 -> 0 | CJ16: =(0)/135 -> 0 | CK16: =(0)/135 -> 0 | CL16: =(0)/135 -> 0 | CM16: =(0)/135 -> 0 | CN16: =(0)/135 -> 0 | ... CP16: =(0)/135 -> 0 | CQ16: =0/157.5 -> 0 | CR16: =0/157.5 -> 0 | CS16: =0/157.5 -> 0 | CT16: =0/157.5 -> 0 | CU16: =0/157.5 -> 0 | CV16: =0/172.5 -> 0 | CW16: =0/172.5 -> 0 | CX16: =0/157.5 -> 0 | CY16: =0/157.5 -> 0 | CZ16: =0/157.5 -> 0 | DA16: =0/157.5 -> 0 | DB16: =0/157.5 -> 0 | DC16: =0/172.5 -> 0 | DD16: =0/172.5 -> 0 | DE16: =0/127.5 -> 0 | DF16: =0/127.5 -> 0 | DG16: =0/127.5 -> 0 | DH16: =0/127.5 -> 0 | DI16: =0/127.5 -> 0 | DJ16: =0/172.5 -> 0 | DK16: =0/172.5 -> 0 | DL16: =0/142.5 -> 0 | DM16: =0/142.5 -> 0 | DN16: =0/142.5 -> 0 | DO16: =0/142.5 -> 0 | DP16: =0/142.5 -> 0 | DQ16: =0/172.5 -> 0 | DR16: =0/172.5 -> 0 | DS16: =0/172.5 -> 0
A17: 6 | B17: 完了 | C17: 定型 | D17: 山田 | E17: F182 | F17: PB00201860 | G17: 【定型】WB4ログイン画面ロゴ画像の変更 | H17: =SUM(CG17:CP17) -> 0 | I17: =SUM(CG18:CP18) -> 0 | N17: 計画 | O17: =(0)/120 -> 0 | P17: =(20)/120 -> 0.16666667 | Q17: =(0)/120 -> 0 | R17: =(0)/120 -> 0 | S17: =(5)/120 -> 0.041666667 | T17: =(20)/120 -> 0.16666667 | U17: =(5)/120 -> 0.041666667 | V17: =(20)/120 -> 0.16666667 | W17: =(20)/120 -> 0.16666667 | X17: =(5)/120 -> 0.041666667 | Y17: =(0)/157.5 -> 0 | Z17: =(0)/157.5 -> 0 | AA17: =(0)/157.5 -> 0 | AB17: =(0)/157.5 -> 0 | AC17: =(0)/157.5 -> 0 | AD17: =(0)/157.5 -> 0 | AE17: =(0)/157.5 -> 0 | AF17: =(0)/157.5 -> 0 | ... AR17: =(0)/157.5 -> 0 | AS17: =(0)/165 -> 0 | AT17: =(0)/165 -> 0 | AU17: =(0)/165 -> 0 | AV17: =(0)/165 -> 0 | AW17: =(0)/165 -> 0 | AX17: =(0)/165 -> 0 | AY17: =(0)/165 -> 0 | AZ17: =(0)/165 -> 0 | ... BB17: =(0)/165 -> 0 | BC17: =(0)/157.5 -> 0 | BD17: =(0)/157.5 -> 0 | BE17: =(0)/157.5 -> 0 | BF17: =(0)/157.5 -> 0 | BG17: =(0)/157.5 -> 0 | BH17: =(0)/157.5 -> 0 | BI17: =(0)/157.5 -> 0 | BJ17: =(0)/157.5 -> 0 | ... BL17: =(0)/157.5 -> 0 | BM17: =(0)/165 -> 0 | BN17: =(0)/165 -> 0 | BO17: =(0)/165 -> 0 | BP17: =(0)/165 -> 0 | BQ17: =(0)/165 -> 0 | BR17: =(0)/165 -> 0 | BS17: =(0)/165 -> 0 | BT17: =(0)/165 -> 0 | ... BV17: =(0)/165 -> 0 | BW17: =(0)/150 -> 0 | BX17: =(0)/150 -> 0 | BY17: =(0)/150 -> 0 | BZ17: =(0)/150 -> 0 | CA17: =(0)/150 -> 0 | CB17: =(0)/150 -> 0 | CC17: =(0)/150 -> 0 | CD17: =(0)/150 -> 0 | ... CF17: =(0)/150 -> 0 | CG17: =(0)/135 -> 0 | CH17: =(0)/135 -> 0 | CI17: =(0)/135 -> 0 | CJ17: =(0)/135 -> 0 | CK17: =(0)/135 -> 0 | CL17: =(0)/135 -> 0 | CM17: =(0)/135 -> 0 | CN17: =(0)/135 -> 0 | ... CP17: =(0)/135 -> 0 | CQ17: =0/157.5 -> 0 | CR17: =0/157.5 -> 0 | CS17: =0/157.5 -> 0 | CT17: =0/157.5 -> 0 | CU17: =0/157.5 -> 0 | CV17: =0/172.5 -> 0 | CW17: =0/172.5 -> 0 | CX17: =0/157.5 -> 0 | CY17: =0/157.5 -> 0 | CZ17: =0/157.5 -> 0 | DA17: =0/157.5 -> 0 | DB17: =0/157.5 -> 0 | DC17: =0/172.5 -> 0 | DD17: =0/172.5 -> 0 | DE17: =0/127.5 -> 0 | DF17: =0/127.5 -> 0 | DG17: =0/127.5 -> 0 | DH17: =0/127.5 -> 0 | DI17: =0/127.5 -> 0 | DJ17: =0/172.5 -> 0 | DK17: =0/172.5 -> 0 | DL17: =0/142.5 -> 0 | DM17: =0/142.5 -> 0 | DN17: =0/142.5 -> 0 | DO17: =0/142.5 -> 0 | DP17: =0/142.5 -> 0 | DQ17: =0/172.5 -> 0 | DR17: =0/172.5 -> 0 | DS17: =0/172.5 -> 0
N18: 実績 | O18: =(0)/120 -> 0 | P18: =(11.5+1+1+2.5)/120 -> 0.13333333 | Q18: =(0)/120 -> 0 | R18: =(0)/120 -> 0 | S18: =(4)/120 -> 0.033333333 | T18: =(13.5+2+1)/120 -> 0.1375 | U18: =(10)/120 -> 0.083333333 | V18: =(8.5+8.5+3)/120 -> 0.16666667 | W18: =(13.5)/120 -> 0.1125 | X18: =(13.5)/120 -> 0.1125 | Y18: =(0)/157.5 -> 0 | Z18: =(0)/157.5 -> 0 | AA18: =(0)/157.5 -> 0 | AB18: =(0)/157.5 -> 0 | AC18: =(0)/157.5 -> 0 | AD18: =(0)/157.5 -> 0 | AE18: =(0)/157.5 -> 0 | AF18: =(0)/157.5 -> 0 | ... AR18: =(0)/157.5 -> 0 | AS18: =(0)/165 -> 0 | AT18: =(0)/165 -> 0 | AU18: =(0)/165 -> 0 | AV18: =(0)/165 -> 0 | AW18: =(0)/165 -> 0 | AX18: =(0)/165 -> 0 | AY18: =(0)/165 -> 0 | AZ18: =(0)/165 -> 0 | ... BB18: =(0)/165 -> 0 | BC18: =(0)/157.5 -> 0 | BD18: =(0)/157.5 -> 0 | BE18: =(0)/157.5 -> 0 | BF18: =(0)/157.5 -> 0 | BG18: =(0)/157.5 -> 0 | BH18: =(0)/157.5 -> 0 | BI18: =(0)/157.5 -> 0 | BJ18: =(0)/157.5 -> 0 | ... BL18: =(0)/157.5 -> 0 | BM18: =(0)/165 -> 0 | BN18: =(0)/165 -> 0 | BO18: =(0)/165 -> 0 | BP18: =(0)/165 -> 0 | BQ18: =(0)/165 -> 0 | BR18: =(0)/165 -> 0 | BS18: =(0)/165 -> 0 | BT18: =(0)/165 -> 0 | ... BV18: =(0)/165 -> 0 | BW18: =(0)/150 -> 0 | BX18: =(0)/150 -> 0 | BY18: =(0)/150 -> 0 | BZ18: =(0)/150 -> 0 | CA18: =(0)/150 -> 0 | CB18: =(0)/150 -> 0 | CC18: =(0)/150 -> 0 | CD18: =(0)/150 -> 0 | ... CF18: =(0)/150 -> 0 | CG18: =(0)/135 -> 0 | CH18: =(0)/135 -> 0 | CI18: =(0)/135 -> 0 | CJ18: =(0)/135 -> 0 | CK18: =(0)/135 -> 0 | CL18: =(0)/135 -> 0 | CM18: =(0)/135 -> 0 | CN18: =(0)/135 -> 0 | ... CP18: =(0)/135 -> 0 | CQ18: =0/157.5 -> 0 | CR18: =0/157.5 -> 0 | CS18: =0/157.5 -> 0 | CT18: =0/157.5 -> 0 | CU18: =0/157.5 -> 0 | CV18: =0/172.5 -> 0 | CW18: =0/172.5 -> 0 | CX18: =0/157.5 -> 0 | CY18: =0/157.5 -> 0 | CZ18: =0/157.5 -> 0 | DA18: =0/157.5 -> 0 | DB18: =0/157.5 -> 0 | DC18: =0/172.5 -> 0 | DD18: =0/172.5 -> 0 | DE18: =0/127.5 -> 0 | DF18: =0/127.5 -> 0 | DG18: =0/127.5 -> 0 | DH18: =0/127.5 -> 0 | DI18: =0/127.5 -> 0 | DJ18: =0/172.5 -> 0 | DK18: =0/172.5 -> 0 | DL18: =0/142.5 -> 0 | DM18: =0/142.5 -> 0 | DN18: =0/142.5 -> 0 | DO18: =0/142.5 -> 0 | DP18: =0/142.5 -> 0 | DQ18: =0/172.5 -> 0 | DR18: =0/172.5 -> 0 | DS18: =0/172.5 -> 0
A19: 7 | B19: 完了 | C19: その他 | D19: 寺澤 | E19: MSC1 | G19: 【MSC】画面設計書最新化対応のお願い | H19: =SUM(CG19:CP19) -> 0 | I19: =SUM(CG20:CP20) -> 0 | N19: 計画 | O19: =(0)/120 -> 0 | P19: =(20)/120 -> 0.16666667 | Q19: =(20)/120 -> 0.16666667 | R19: =(0)/120 -> 0 | S19: =(0)/120 -> 0 | T19: =(20)/120 -> 0.16666667 | U19: =(5)/120 -> 0.041666667 | V19: =(5)/120 -> 0.041666667 | W19: =(5)/120 -> 0.041666667 | X19: =(10)/120 -> 0.083333333 | Y19: =(0)/157.5 -> 0 | Z19: =(0)/157.5 -> 0 | AA19: =(0)/157.5 -> 0 | AB19: =(0)/157.5 -> 0 | AC19: =(0)/157.5 -> 0 | AD19: =(0)/157.5 -> 0 | AE19: =(0)/157.5 -> 0 | AF19: =(0)/157.5 -> 0 | ... AR19: =(0)/157.5 -> 0 | AS19: =(0)/165 -> 0 | AT19: =(0)/165 -> 0 | AU19: =(0)/165 -> 0 | AV19: =(0)/165 -> 0 | AW19: =(0)/165 -> 0 | AX19: =(0)/165 -> 0 | AY19: =(0)/165 -> 0 | AZ19: =(0)/165 -> 0 | ... BB19: =(0)/165 -> 0 | BC19: =(0)/157.5 -> 0 | BD19: =(0)/157.5 -> 0 | BE19: =(0)/157.5 -> 0 | BF19: =(0)/157.5 -> 0 | BG19: =(0)/157.5 -> 0 | BH19: =(0)/157.5 -> 0 | BI19: =(0)/157.5 -> 0 | BJ19: =(0)/157.5 -> 0 | ... BL19: =(0)/157.5 -> 0 | BM19: =(0)/165 -> 0 | BN19: =(0)/165 -> 0 | BO19: =(0)/165 -> 0 | BP19: =(0)/165 -> 0 | BQ19: =(0)/165 -> 0 | BR19: =(0)/165 -> 0 | BS19: =(0)/165 -> 0 | BT19: =(0)/165 -> 0 | ... BV19: =(0)/165 -> 0 | BW19: =(0)/150 -> 0 | BX19: =(0)/150 -> 0 | BY19: =(0)/150 -> 0 | BZ19: =(0)/150 -> 0 | CA19: =(0)/150 -> 0 | CB19: =(0)/150 -> 0 | CC19: =(0)/150 -> 0 | CD19: =(0)/150 -> 0 | ... CF19: =(0)/150 -> 0 | CG19: =(0)/135 -> 0 | CH19: =(0)/135 -> 0 | CI19: =(0)/135 -> 0 | CJ19: =(0)/135 -> 0 | CK19: =(0)/135 -> 0 | CL19: =(0)/135 -> 0 | CM19: =(0)/135 -> 0 | CN19: =(0)/135 -> 0 | ... CP19: =(0)/135 -> 0 | CQ19: =0/157.5 -> 0 | CR19: =0/157.5 -> 0 | CS19: =0/157.5 -> 0 | CT19: =0/157.5 -> 0 | CU19: =0/157.5 -> 0 | CV19: =0/172.5 -> 0 | CW19: =0/172.5 -> 0 | CX19: =0/157.5 -> 0 | CY19: =0/157.5 -> 0 | CZ19: =0/157.5 -> 0 | DA19: =0/157.5 -> 0 | DB19: =0/157.5 -> 0 | DC19: =0/172.5 -> 0 | DD19: =0/172.5 -> 0 | DE19: =0/127.5 -> 0 | DF19: =0/127.5 -> 0 | DG19: =0/127.5 -> 0 | DH19: =0/127.5 -> 0 | DI19: =0/127.5 -> 0 | DJ19: =0/172.5 -> 0 | DK19: =0/172.5 -> 0 | DL19: =0/142.5 -> 0 | DM19: =0/142.5 -> 0 | DN19: =0/142.5 -> 0 | DO19: =0/142.5 -> 0 | DP19: =0/142.5 -> 0 | DQ19: =0/172.5 -> 0 | DR19: =0/172.5 -> 0 | DS19: =0/172.5 -> 0
N20: 実績 | O20: =(0)/120 -> 0 | P20: =(13)/120 -> 0.10833333 | Q20: =(14)/120 -> 0.11666667 | R20: =(0)/120 -> 0 | S20: =(0)/120 -> 0 | T20: =(14)/120 -> 0.11666667 | U20: =(6.5)/120 -> 0.054166667 | V20: =(8)/120 -> 0.066666667 | W20: =(14)/120 -> 0.11666667 | X20: =(14)/120 -> 0.11666667 | Y20: =(0)/157.5 -> 0 | Z20: =(0)/157.5 -> 0 | AA20: =(0)/157.5 -> 0 | AB20: =(0)/157.5 -> 0 | AC20: =(0)/157.5 -> 0 | AD20: =(0)/157.5 -> 0 | AE20: =(0)/157.5 -> 0 | AF20: =(0)/157.5 -> 0 | ... AR20: =(0)/157.5 -> 0 | AS20: =(0)/165 -> 0 | AT20: =(0)/165 -> 0 | AU20: =(0)/165 -> 0 | AV20: =(0)/165 -> 0 | AW20: =(0)/165 -> 0 | AX20: =(0)/165 -> 0 | AY20: =(0)/165 -> 0 | AZ20: =(0)/165 -> 0 | ... BB20: =(0)/165 -> 0 | BC20: =(0)/157.5 -> 0 | BD20: =(0)/157.5 -> 0 | BE20: =(0)/157.5 -> 0 | BF20: =(0)/157.5 -> 0 | BG20: =(0)/157.5 -> 0 | BH20: =(0)/157.5 -> 0 | BI20: =(0)/157.5 -> 0 | BJ20: =(0)/157.5 -> 0 | ... BL20: =(0)/157.5 -> 0 | BM20: =(0)/165 -> 0 | BN20: =(0)/165 -> 0 | BO20: =(0)/165 -> 0 | BP20: =(0)/165 -> 0 | BQ20: =(0)/165 -> 0 | BR20: =(0)/165 -> 0 | BS20: =(0)/165 -> 0 | BT20: =(0)/165 -> 0 | ... BV20: =(0)/165 -> 0 | BW20: =(0)/150 -> 0 | BX20: =(0)/150 -> 0 | BY20: =(0)/150 -> 0 | BZ20: =(0)/150 -> 0 | CA20: =(0)/150 -> 0 | CB20: =(0)/150 -> 0 | CC20: =(0)/150 -> 0 | CD20: =(0)/150 -> 0 | ... CF20: =(0)/150 -> 0 | CG20: =(0)/135 -> 0 | CH20: =(0)/135 -> 0 | CI20: =(0)/135 -> 0 | CJ20: =(0)/135 -> 0 | CK20: =(0)/135 -> 0 | CL20: =(0)/135 -> 0 | CM20: =(0)/135 -> 0 | CN20: =(0)/135 -> 0 | ... CP20: =(0)/135 -> 0 | CQ20: =0/157.5 -> 0 | CR20: =0/157.5 -> 0 | CS20: =0/157.5 -> 0 | CT20: =0/157.5 -> 0 | CU20: =0/157.5 -> 0 | CV20: =0/172.5 -> 0 | CW20: =0/172.5 -> 0 | CX20: =0/157.5 -> 0 | CY20: =0/157.5 -> 0 | CZ20: =0/157.5 -> 0 | DA20: =0/157.5 -> 0 | DB20: =0/157.5 -> 0 | DC20: =0/172.5 -> 0 | DD20: =0/172.5 -> 0 | DE20: =0/127.5 -> 0 | DF20: =0/127.5 -> 0 | DG20: =0/127.5 -> 0 | DH20: =0/127.5 -> 0 | DI20: =0/127.5 -> 0 | DJ20: =0/172.5 -> 0 | DK20: =0/172.5 -> 0 | DL20: =0/142.5 -> 0 | DM20: =0/142.5 -> 0 | DN20: =0/142.5 -> 0 | DO20: =0/142.5 -> 0 | DP20: =0/142.5 -> 0 | DQ20: =0/172.5 -> 0 | DR20: =0/172.5 -> 0 | DS20: =0/172.5 -> 0
A21: 8 | B21: 完了 | C21: その他 | D21: 田中 | E21: AH24 | G21: 【案件依頼】【ツール開発】シェルが稼働しているジョブネットの一覧作成 | H21: =SUM(CG21:CP21) -> 0 | I21: =SUM(CG22:CP22) -> 0 | N21: 計画 | O21: =(0)/120 -> 0 | P21: =(35)/120 -> 0.29166667 | Q21: =(35)/120 -> 0.29166667 | R21: =(35)/120 -> 0.29166667 | S21: =(0)/120 -> 0 | T21: =(35)/120 -> 0.29166667 | U21: =(35)/120 -> 0.29166667 | V21: =(35)/120 -> 0.29166667 | W21: =(0)/120 -> 0 | X21: =(0)/120 -> 0 | Y21: =(0)/157.5 -> 0 | Z21: =(30)/157.5 -> 0.19047619 | AA21: =(0)/157.5 -> 0 | AB21: =(60)/157.5 -> 0.38095238 | AC21: =(0)/157.5 -> 0 | AD21: =(60)/157.5 -> 0.38095238 | AE21: =(0)/157.5 -> 0 | AF21: =(60)/157.5 -> 0.38095238 | AG21: =(0)/157.5 -> 0 | AH21: =(60)/157.5 -> 0.38095238 | AI21: =(0)/157.5 -> 0 | AJ21: =(0)/157.5 -> 0 | AK21: =(0)/157.5 -> 0 | AL21: =(0)/157.5 -> 0 | AM21: =(0)/157.5 -> 0 | AN21: =(0)/157.5 -> 0 | AO21: =(0)/157.5 -> 0 | AP21: =(0)/157.5 -> 0 | ... AR21: =(0)/157.5 -> 0 | AS21: =(0)/165 -> 0 | AT21: =(0)/165 -> 0 | AU21: =(0)/165 -> 0 | AV21: =(0)/165 -> 0 | AW21: =(0)/165 -> 0 | AX21: =(0)/165 -> 0 | AY21: =(0)/165 -> 0 | AZ21: =(0)/165 -> 0 | ... BB21: =(0)/165 -> 0 | BC21: =(0)/157.5 -> 0 | BD21: =(0)/157.5 -> 0 | BE21: =(0)/157.5 -> 0 | BF21: =(0)/157.5 -> 0 | BG21: =(0)/157.5 -> 0 | BH21: =(0)/157.5 -> 0 | BI21: =(0)/157.5 -> 0 | BJ21: =(0)/157.5 -> 0 | ... BL21: =(0)/157.5 -> 0 | BM21: =(0)/165 -> 0 | BN21: =(0)/165 -> 0 | BO21: =(0)/165 -> 0 | BP21: =(0)/165 -> 0 | BQ21: =(0)/165 -> 0 | BR21: =(0)/165 -> 0 | BS21: =(0)/165 -> 0 | BT21: =(0)/165 -> 0 | ... BV21: =(0)/165 -> 0 | BW21: =(0)/150 -> 0 | BX21: =(0)/150 -> 0 | BY21: =(0)/150 -> 0 | BZ21: =(0)/150 -> 0 | CA21: =(0)/150 -> 0 | CB21: =(0)/150 -> 0 | CC21: =(0)/150 -> 0 | CD21: =(0)/150 -> 0 | ... CF21: =(0)/150 -> 0 | CG21: =(0)/135 -> 0 | CH21: =(0)/135 -> 0 | CI21: =(0)/135 -> 0 | CJ21: =(0)/135 -> 0 | CK21: =(0)/135 -> 0 | CL21: =(0)/135 -> 0 | CM21: =(0)/135 -> 0 | CN21: =(0)/135 -> 0 | ... CP21: =(0)/135 -> 0 | CQ21: =0/157.5 -> 0 | CR21: =0/157.5 -> 0 | CS21: =0/157.5 -> 0 | CT21: =0/157.5 -> 0 | CU21: =0/157.5 -> 0 | CV21: =0/172.5 -> 0 | CW21: =0/172.5 -> 0 | CX21: =0/157.5 -> 0 | CY21: =0/157.5 -> 0 | CZ21: =0/157.5 -> 0 | DA21: =0/157.5 -> 0 | DB21: =0/157.5 -> 0 | DC21: =0/172.5 -> 0 | DD21: =0/172.5 -> 0 | DE21: =0/127.5 -> 0 | DF21: =0/127.5 -> 0 | DG21: =0/127.5 -> 0 | DH21: =0/127.5 -> 0 | DI21: =0/127.5 -> 0 | DJ21: =0/172.5 -> 0 | DK21: =0/172.5 -> 0 | DL21: =0/142.5 -> 0 | DM21: =0/142.5 -> 0 | DN21: =0/142.5 -> 0 | DO21: =0/142.5 -> 0 | DP21: =0/142.5 -> 0 | DQ21: =0/172.5 -> 0 | DR21: =0/172.5 -> 0 | DS21: =0/172.5 -> 0
N22: 実績 | O22: =(0)/120 -> 0 | P22: =(0+6+7)/120 -> 0.10833333 | Q22: =(0+20.5+7+6.5)/120 -> 0.28333333 | R22: =(0+22+9.5+6+26)/120 -> 0.52916667 | S22: =(0)/120 -> 0 | T22: =(0+9+10.5+12+33.5)/120 -> 0.54166667 | U22: =(0+9)/120 -> 0.075 | V22: =(0+3+2)/120 -> 0.041666667 | W22: =(0)/120 -> 0 | X22: =(19.5)/120 -> 0.1625 | Y22: =(0+2+2)/157.5 -> 0.025396825 | Z22: =(9.5+4+10.5+2)/157.5 -> 0.16507937 | AA22: =(0)/157.5 -> 0 | AB22: =(17.5+26.5+23.5+4.5)/157.5 -> 0.45714286 | AC22: =(0)/157.5 -> 0 | AD22: =(28+32.5+19)/157.5 -> 0.5047619 | AE22: =(0)/157.5 -> 0 | AF22: =(6+1)/157.5 -> 0.044444444 | AG22: =(0)/157.5 -> 0 | AH22: =(22+24.5+24.5+5.5)/157.5 -> 0.48571429 | AI22: =(0)/157.5 -> 0 | AJ22: =(0)/157.5 -> 0 | AK22: =(0)/157.5 -> 0 | AL22: =(0)/157.5 -> 0 | AM22: =(0)/157.5 -> 0 | AN22: =(0)/157.5 -> 0 | AO22: =(0)/157.5 -> 0 | AP22: =(0)/157.5 -> 0 | ... AR22: =(0)/157.5 -> 0 | AS22: =(0)/165 -> 0 | AT22: =(0)/165 -> 0 | AU22: =(0)/165 -> 0 | AV22: =(0)/165 -> 0 | AW22: =(0)/165 -> 0 | AX22: =(0)/165 -> 0 | AY22: =(0)/165 -> 0 | AZ22: =(0)/165 -> 0 | ... BB22: =(0)/165 -> 0 | BC22: =(0)/157.5 -> 0 | BD22: =(0)/157.5 -> 0 | BE22: =(0)/157.5 -> 0 | BF22: =(0)/157.5 -> 0 | BG22: =(0)/157.5 -> 0 | BH22: =(0)/157.5 -> 0 | BI22: =(0)/157.5 -> 0 | BJ22: =(0)/157.5 -> 0 | ... BL22: =(0)/157.5 -> 0 | BM22: =(0)/165 -> 0 | BN22: =(0)/165 -> 0 | BO22: =(0)/165 -> 0 | BP22: =(0)/165 -> 0 | BQ22: =(0)/165 -> 0 | BR22: =(0)/165 -> 0 | BS22: =(0)/165 -> 0 | BT22: =(0)/165 -> 0 | ... BV22: =(0)/165 -> 0 | BW22: =(0)/150 -> 0 | BX22: =(0)/150 -> 0 | BY22: =(0)/150 -> 0 | BZ22: =(0)/150 -> 0 | CA22: =(0)/150 -> 0 | CB22: =(0)/150 -> 0 | CC22: =(0)/150 -> 0 | CD22: =(0)/150 -> 0 | ... CF22: =(0)/150 -> 0 | CG22: =(0)/135 -> 0 | CH22: =(0)/135 -> 0 | CI22: =(0)/135 -> 0 | CJ22: =(0)/135 -> 0 | CK22: =(0)/135 -> 0 | CL22: =(0)/135 -> 0 | CM22: =(0)/135 -> 0 | CN22: =(0)/135 -> 0 | ... CP22: =(0)/135 -> 0 | CQ22: =0/157.5 -> 0 | CR22: =0/157.5 -> 0 | CS22: =0/157.5 -> 0 | CT22: =0/157.5 -> 0 | CU22: =0/157.5 -> 0 | CV22: =0/172.5 -> 0 | CW22: =0/172.5 -> 0 | CX22: =0/157.5 -> 0 | CY22: =0/157.5 -> 0 | CZ22: =0/157.5 -> 0 | DA22: =0/157.5 -> 0 | DB22: =0/157.5 -> 0 | DC22: =0/172.5 -> 0 | DD22: =0/172.5 -> 0 | DE22: =0/127.5 -> 0 | DF22: =0/127.5 -> 0 | DG22: =0/127.5 -> 0 | DH22: =0/127.5 -> 0 | DI22: =0/127.5 -> 0 | DJ22: =0/172.5 -> 0 | DK22: =0/172.5 -> 0 | DL22: =0/142.5 -> 0 | DM22: =0/142.5 -> 0 | DN22: =0/142.5 -> 0 | DO22: =0/142.5 -> 0 | DP22: =0/142.5 -> 0 | DQ22: =0/172.5 -> 0 | DR22: =0/172.5 -> 0 | DS22: =0/172.5 -> 0
A23: 9 | B23: 完了 | C23: その他 | D23: 田中 | E23: AH26 | G23: 【ツール開発】WB4結合環境の状況リスト一覧の作成 | H23: =SUM(CG23:CP23) -> 0 | I23: =SUM(CG24:CP24) -> 0 | N23: 計画 | O23: =(0)/120 -> 0 | P23: =(27.5)/120 -> 0.22916667 | Q23: =(0)/120 -> 0 | R23: =(0)/120 -> 0 | S23: =(27.5)/120 -> 0.22916667 | T23: =(0)/120 -> 0 | U23: =(0)/120 -> 0 | V23: =(27.5)/120 -> 0.22916667 | W23: =(27.5)/120 -> 0.22916667 | X23: =(0)/120 -> 0 | Y23: =(0)/157.5 -> 0 | Z23: =(5)/157.5 -> 0.031746032 | AA23: =(0)/157.5 -> 0 | AB23: =(0)/157.5 -> 0 | AC23: =(5)/157.5 -> 0.031746032 | AD23: =(0)/157.5 -> 0 | AE23: =(0)/157.5 -> 0 | AF23: =(0)/157.5 -> 0 | AG23: =(5)/157.5 -> 0.031746032 | AH23: =(0)/157.5 -> 0 | AI23: =(0)/157.5 -> 0 | AJ23: =(0)/157.5 -> 0 | AK23: =(0)/157.5 -> 0 | AL23: =(0)/157.5 -> 0 | AM23: =(0)/157.5 -> 0 | AN23: =(0)/157.5 -> 0 | AO23: =(0)/157.5 -> 0 | ... AR23: =(0)/157.5 -> 0 | AS23: =(0)/165 -> 0 | AT23: =(0)/165 -> 0 | AU23: =(0)/165 -> 0 | AV23: =(0)/165 -> 0 | AW23: =(0)/165 -> 0 | AX23: =(0)/165 -> 0 | AY23: =(0)/165 -> 0 | AZ23: =(0)/165 -> 0 | ... BB23: =(0)/165 -> 0 | BC23: =(0)/157.5 -> 0 | BD23: =(0)/157.5 -> 0 | BE23: =(0)/157.5 -> 0 | BF23: =(0)/157.5 -> 0 | BG23: =(0)/157.5 -> 0 | BH23: =(0)/157.5 -> 0 | BI23: =(0)/157.5 -> 0 | BJ23: =(0)/157.5 -> 0 | ... BL23: =(0)/157.5 -> 0 | BM23: =(0)/165 -> 0 | BN23: =(0)/165 -> 0 | BO23: =(0)/165 -> 0 | BP23: =(0)/165 -> 0 | BQ23: =(0)/165 -> 0 | BR23: =(0)/165 -> 0 | BS23: =(0)/165 -> 0 | BT23: =(0)/165 -> 0 | ... BV23: =(0)/165 -> 0 | BW23: =(0)/150 -> 0 | BX23: =(0)/150 -> 0 | BY23: =(0)/150 -> 0 | BZ23: =(0)/150 -> 0 | CA23: =(0)/150 -> 0 | CB23: =(0)/150 -> 0 | CC23: =(0)/150 -> 0 | CD23: =(0)/150 -> 0 | ... CF23: =(0)/150 -> 0 | CG23: =(0)/135 -> 0 | CH23: =(0)/135 -> 0 | CI23: =(0)/135 -> 0 | CJ23: =(0)/135 -> 0 | CK23: =(0)/135 -> 0 | CL23: =(0)/135 -> 0 | CM23: =(0)/135 -> 0 | CN23: =(0)/135 -> 0 | ... CP23: =(0)/135 -> 0 | CQ23: =0/157.5 -> 0 | CR23: =0/157.5 -> 0 | CS23: =0/157.5 -> 0 | CT23: =0/157.5 -> 0 | CU23: =0/157.5 -> 0 | CV23: =0/172.5 -> 0 | CW23: =0/172.5 -> 0 | CX23: =0/157.5 -> 0 | CY23: =0/157.5 -> 0 | CZ23: =0/157.5 -> 0 | DA23: =0/157.5 -> 0 | DB23: =0/157.5 -> 0 | DC23: =0/172.5 -> 0 | DD23: =0/172.5 -> 0 | DE23: =0/127.5 -> 0 | DF23: =0/127.5 -> 0 | DG23: =0/127.5 -> 0 | DH23: =0/127.5 -> 0 | DI23: =0/127.5 -> 0 | DJ23: =0/172.5 -> 0 | DK23: =0/172.5 -> 0 | DL23: =0/142.5 -> 0 | DM23: =0/142.5 -> 0 | DN23: =0/142.5 -> 0 | DO23: =0/142.5 -> 0 | DP23: =0/142.5 -> 0 | DQ23: =0/172.5 -> 0 | DR23: =0/172.5 -> 0 | DS23: =0/172.5 -> 0
N24: 実績 | O24: =(0)/120 -> 0 | P24: =(12+4.5+7.5+0.5)/120 -> 0.20416667 | Q24: =(0)/120 -> 0 | R24: =(0)/120 -> 0 | S24: =(7+6+6.5)/120 -> 0.1625 | T24: =(0)/120 -> 0 | U24: =(0)/120 -> 0 | V24: =(18+5+2)/120 -> 0.20833333 | W24: =(12+8.5+9+3.5)/120 -> 0.275 | X24: =(0)/120 -> 0 | Y24: =(0)/157.5 -> 0 | Z24: =(0+1)/157.5 -> 0.0063492063 | AA24: =(0)/157.5 -> 0 | AB24: =(0)/157.5 -> 0 | AC24: =(4.5+2.5)/157.5 -> 0.044444444 | AD24: =(0)/157.5 -> 0 | AE24: =(0)/157.5 -> 0 | AF24: =(0)/157.5 -> 0 | AG24: =(2.5+2.5)/157.5 -> 0.031746032 | AH24: =(0)/157.5 -> 0 | AI24: =(0)/157.5 -> 0 | AJ24: =(0)/157.5 -> 0 | AK24: =(0)/157.5 -> 0 | AL24: =(0)/157.5 -> 0 | AM24: =(0)/157.5 -> 0 | AN24: =(0)/157.5 -> 0 | AO24: =(0)/157.5 -> 0 | ... AR24: =(0)/157.5 -> 0 | AS24: =(0)/165 -> 0 | AT24: =(0)/165 -> 0 | AU24: =(0)/165 -> 0 | AV24: =(0)/165 -> 0 | AW24: =(0)/165 -> 0 | AX24: =(0)/165 -> 0 | AY24: =(0)/165 -> 0 | AZ24: =(0)/165 -> 0 | ... BB24: =(0)/165 -> 0 | BC24: =(0)/157.5 -> 0 | BD24: =(0)/157.5 -> 0 | BE24: =(0)/157.5 -> 0 | BF24: =(0)/157.5 -> 0 | BG24: =(0)/157.5 -> 0 | BH24: =(0)/157.5 -> 0 | BI24: =(0)/157.5 -> 0 | BJ24: =(0)/157.5 -> 0 | ... BL24: =(0)/157.5 -> 0 | BM24: =(0)/165 -> 0 | BN24: =(0)/165 -> 0 | BO24: =(0)/165 -> 0 | BP24: =(0)/165 -> 0 | BQ24: =(0)/165 -> 0 | BR24: =(0)/165 -> 0 | BS24: =(0)/165 -> 0 | BT24: =(0)/165 -> 0 | ... BV24: =(0)/165 -> 0 | BW24: =(0)/150 -> 0 | BX24: =(0)/150 -> 0 | BY24: =(0)/150 -> 0 | BZ24: =(0)/150 -> 0 | CA24: =(0)/150 -> 0 | CB24: =(0)/150 -> 0 | CC24: =(0)/150 -> 0 | CD24: =(0)/150 -> 0 | ... CF24: =(0)/150 -> 0 | CG24: =(0)/135 -> 0 | CH24: =(0)/135 -> 0 | CI24: =(0)/135 -> 0 | CJ24: =(0)/135 -> 0 | CK24: =(0)/135 -> 0 | CL24: =(0)/135 -> 0 | CM24: =(0)/135 -> 0 | CN24: =(0)/135 -> 0 | ... CP24: =(0)/135 -> 0 | CQ24: =0/157.5 -> 0 | CR24: =0/157.5 -> 0 | CS24: =0/157.5 -> 0 | CT24: =0/157.5 -> 0 | CU24: =0/157.5 -> 0 | CV24: =0/172.5 -> 0 | CW24: =0/172.5 -> 0 | CX24: =0/157.5 -> 0 | CY24: =0/157.5 -> 0 | CZ24: =0/157.5 -> 0 | DA24: =0/157.5 -> 0 | DB24: =0/157.5 -> 0 | DC24: =0/172.5 -> 0 | DD24: =0/172.5 -> 0 | DE24: =0/127.5 -> 0 | DF24: =0/127.5 -> 0 | DG24: =0/127.5 -> 0 | DH24: =0/127.5 -> 0 | DI24: =0/127.5 -> 0 | DJ24: =0/172.5 -> 0 | DK24: =0/172.5 -> 0 | DL24: =0/142.5 -> 0 | DM24: =0/142.5 -> 0 | DN24: =0/142.5 -> 0 | DO24: =0/142.5 -> 0 | DP24: =0/142.5 -> 0 | DQ24: =0/172.5 -> 0 | DR24: =0/172.5 -> 0 | DS24: =0/172.5 -> 0
A25: 10 | B25: 完了 | C25: 定型 | D25: 谷口 | E25: F183 | F25: PB00201788 | G25: 【定型】(53)820部店の対面WEB利用 | H25: =SUM(CG25:CP25) -> 0 | I25: =SUM(CG26:CP26) -> 0 | N25: 計画 | O25: =(0)/120 -> 0 | P25: =(6)/120 -> 0.05 | Q25: =(0)/120 -> 0 | R25: =(7)/120 -> 0.058333333 | S25: =(0)/120 -> 0 | T25: =(0)/120 -> 0 | U25: =(0)/120 -> 0 | V25: =(0)/120 -> 0 | W25: =(7)/120 -> 0.058333333 | X25: =(0)/120 -> 0 | Y25: =(0)/157.5 -> 0 | Z25: =(3)/157.5 -> 0.019047619 | AA25: =(0)/157.5 -> 0 | AB25: =(3)/157.5 -> 0.019047619 | AC25: =(0)/157.5 -> 0 | AD25: =(0)/157.5 -> 0 | AE25: =(0)/157.5 -> 0 | AF25: =(0)/157.5 -> 0 | AG25: =(3)/157.5 -> 0.019047619 | AH25: =(0)/157.5 -> 0 | AI25: =(0)/157.5 -> 0 | AJ25: =(0)/157.5 -> 0 | AK25: =(0)/157.5 -> 0 | AL25: =(0)/157.5 -> 0 | AM25: =(0)/157.5 -> 0 | AN25: =(0)/157.5 -> 0 | AO25: =(0)/157.5 -> 0 | ... AR25: =(0)/157.5 -> 0 | AS25: =(0)/165 -> 0 | AT25: =(0)/165 -> 0 | AU25: =(0)/165 -> 0 | AV25: =(0)/165 -> 0 | AW25: =(0)/165 -> 0 | AX25: =(0)/165 -> 0 | AY25: =(0)/165 -> 0 | AZ25: =(0)/165 -> 0 | ... BB25: =(0)/165 -> 0 | BC25: =(0)/157.5 -> 0 | BD25: =(0)/157.5 -> 0 | BE25: =(0)/157.5 -> 0 | BF25: =(0)/157.5 -> 0 | BG25: =(0)/157.5 -> 0 | BH25: =(0)/157.5 -> 0 | BI25: =(0)/157.5 -> 0 | BJ25: =(0)/157.5 -> 0 | ... BL25: =(0)/157.5 -> 0 | BM25: =(0)/165 -> 0 | BN25: =(0)/165 -> 0 | BO25: =(0)/165 -> 0 | BP25: =(0)/165 -> 0 | BQ25: =(0)/165 -> 0 | BR25: =(0)/165 -> 0 | BS25: =(0)/165 -> 0 | BT25: =(0)/165 -> 0 | ... BV25: =(0)/165 -> 0 | BW25: =(0)/150 -> 0 | BX25: =(0)/150 -> 0 | BY25: =(0)/150 -> 0 | BZ25: =(0)/150 -> 0 | CA25: =(0)/150 -> 0 | CB25: =(0)/150 -> 0 | CC25: =(0)/150 -> 0 | CD25: =(0)/150 -> 0 | ... CF25: =(0)/150 -> 0 | CG25: =(0)/135 -> 0 | CH25: =(0)/135 -> 0 | CI25: =(0)/135 -> 0 | CJ25: =(0)/135 -> 0 | CK25: =(0)/135 -> 0 | CL25: =(0)/135 -> 0 | CM25: =(0)/135 -> 0 | CN25: =(0)/135 -> 0 | ... CP25: =(0)/135 -> 0 | CQ25: =0/157.5 -> 0 | CR25: =0/157.5 -> 0 | CS25: =0/157.5 -> 0 | CT25: =0/157.5 -> 0 | CU25: =0/157.5 -> 0 | CV25: =0/172.5 -> 0 | CW25: =0/172.5 -> 0 | CX25: =0/157.5 -> 0 | CY25: =0/157.5 -> 0 | CZ25: =0/157.5 -> 0 | DA25: =0/157.5 -> 0 | DB25: =0/157.5 -> 0 | DC25: =0/172.5 -> 0 | DD25: =0/172.5 -> 0 | DE25: =0/127.5 -> 0 | DF25: =0/127.5 -> 0 | DG25: =0/127.5 -> 0 | DH25: =0/127.5 -> 0 | DI25: =0/127.5 -> 0 | DJ25: =0/172.5 -> 0 | DK25: =0/172.5 -> 0 | DL25: =0/142.5 -> 0 | DM25: =0/142.5 -> 0 | DN25: =0/142.5 -> 0 | DO25: =0/142.5 -> 0 | DP25: =0/142.5 -> 0 | DQ25: =0/172.5 -> 0 | DR25: =0/172.5 -> 0 | DS25: =0/172.5 -> 0
N26: 実績 | O26: =(0)/120 -> 0 | P26: =(1+1.5)/120 -> 0.020833333 | Q26: =(0)/120 -> 0 | R26: =(8+2.5)/120 -> 0.0875 | S26: =(0)/120 -> 0 | T26: =(0)/120 -> 0 | U26: =(0)/120 -> 0 | V26: =(0)/120 -> 0 | W26: =(5)/120 -> 0.041666667 | X26: =(0)/120 -> 0 | Y26: =(0)/157.5 -> 0 | Z26: =(2)/157.5 -> 0.012698413 | AA26: =(0)/157.5 -> 0 | AB26: =(0+2+1+1)/157.5 -> 0.025396825 | AC26: =(0)/157.5 -> 0 | AD26: =(0)/157.5 -> 0 | AE26: =(0)/157.5 -> 0 | AF26: =(0)/157.5 -> 0 | AG26: =(0+1+1)/157.5 -> 0.012698413 | AH26: =(0)/157.5 -> 0 | AI26: =(0)/157.5 -> 0 | AJ26: =(0)/157.5 -> 0 | AK26: =(0)/157.5 -> 0 | AL26: =(0)/157.5 -> 0 | AM26: =(0)/157.5 -> 0 | AN26: =(0)/157.5 -> 0 | AO26: =(0)/157.5 -> 0 | ... AR26: =(0)/157.5 -> 0 | AS26: =(0)/165 -> 0 | AT26: =(0)/165 -> 0 | AU26: =(0)/165 -> 0 | AV26: =(0)/165 -> 0 | AW26: =(0)/165 -> 0 | AX26: =(0)/165 -> 0 | AY26: =(0)/165 -> 0 | AZ26: =(0)/165 -> 0 | ... BB26: =(0)/165 -> 0 | BC26: =(0)/157.5 -> 0 | BD26: =(0)/157.5 -> 0 | BE26: =(0)/157.5 -> 0 | BF26: =(0)/157.5 -> 0 | BG26: =(0)/157.5 -> 0 | BH26: =(0)/157.5 -> 0 | BI26: =(0)/157.5 -> 0 | BJ26: =(0)/157.5 -> 0 | ... BL26: =(0)/157.5 -> 0 | BM26: =(0)/165 -> 0 | BN26: =(0)/165 -> 0 | BO26: =(0)/165 -> 0 | BP26: =(0)/165 -> 0 | BQ26: =(0)/165 -> 0 | BR26: =(0)/165 -> 0 | BS26: =(0)/165 -> 0 | BT26: =(0)/165 -> 0 | ... BV26: =(0)/165 -> 0 | BW26: =(0)/150 -> 0 | BX26: =(0)/150 -> 0 | BY26: =(0)/150 -> 0 | BZ26: =(0)/150 -> 0 | CA26: =(0)/150 -> 0 | CB26: =(0)/150 -> 0 | CC26: =(0)/150 -> 0 | CD26: =(0)/150 -> 0 | ... CF26: =(0)/150 -> 0 | CG26: =(0)/135 -> 0 | CH26: =(0)/135 -> 0 | CI26: =(0)/135 -> 0 | CJ26: =(0)/135 -> 0 | CK26: =(0)/135 -> 0 | CL26: =(0)/135 -> 0 | CM26: =(0)/135 -> 0 | CN26: =(0)/135 -> 0 | ... CP26: =(0)/135 -> 0 | CQ26: =0/157.5 -> 0 | CR26: =0/157.5 -> 0 | CS26: =0/157.5 -> 0 | CT26: =0/157.5 -> 0 | CU26: =0/157.5 -> 0 | CV26: =0/172.5 -> 0 | CW26: =0/172.5 -> 0 | CX26: =0/157.5 -> 0 | CY26: =0/157.5 -> 0 | CZ26: =0/157.5 -> 0 | DA26: =0/157.5 -> 0 | DB26: =0/157.5 -> 0 | DC26: =0/172.5 -> 0 | DD26: =0/172.5 -> 0 | DE26: =0/127.5 -> 0 | DF26: =0/127.5 -> 0 | DG26: =0/127.5 -> 0 | DH26: =0/127.5 -> 0 | DI26: =0/127.5 -> 0 | DJ26: =0/172.5 -> 0 | DK26: =0/172.5 -> 0 | DL26: =0/142.5 -> 0 | DM26: =0/142.5 -> 0 | DN26: =0/142.5 -> 0 | DO26: =0/142.5 -> 0 | DP26: =0/142.5 -> 0 | DQ26: =0/172.5 -> 0 | DR26: =0/172.5 -> 0 | DS26: =0/172.5 -> 0
A27: 11 | B27: 完了 | C27: 定型 | D27: 邵 | E27: F184 | F27: PB00201870 | G27: 【定型】（信用）担保処分に関する文言変更 | H27: =SUM(CG27:CP27) -> 0 | I27: =SUM(CG28:CP28) -> 0 | N27: 計画 | O27: =(0)/120 -> 0 | P27: =(33)/120 -> 0.275 | Q27: =(0)/120 -> 0 | R27: =(0)/120 -> 0 | S27: =(33)/120 -> 0.275 | T27: =(0)/120 -> 0 | U27: =(0)/120 -> 0 | V27: =(0)/120 -> 0 | W27: =(0)/120 -> 0 | X27: =(0)/120 -> 0 | Y27: =(0)/157.5 -> 0 | Z27: =(0)/157.5 -> 0 | AA27: =(0)/157.5 -> 0 | AB27: =(0)/157.5 -> 0 | AC27: =(2)/157.5 -> 0.012698413 | AD27: =(0)/157.5 -> 0 | AE27: =(0)/157.5 -> 0 | AF27: =(0)/157.5 -> 0 | AG27: =(0)/157.5 -> 0 | AH27: =(0)/157.5 -> 0 | AI27: =(0)/157.5 -> 0 | AJ27: =(0)/157.5 -> 0 | AK27: =(0)/157.5 -> 0 | ... AR27: =(0)/157.5 -> 0 | AS27: =(0)/165 -> 0 | AT27: =(0)/165 -> 0 | AU27: =(0)/165 -> 0 | AV27: =(0)/165 -> 0 | AW27: =(0)/165 -> 0 | AX27: =(0)/165 -> 0 | AY27: =(0)/165 -> 0 | AZ27: =(0)/165 -> 0 | ... BB27: =(0)/165 -> 0 | BC27: =(0)/157.5 -> 0 | BD27: =(0)/157.5 -> 0 | BE27: =(0)/157.5 -> 0 | BF27: =(0)/157.5 -> 0 | BG27: =(0)/157.5 -> 0 | BH27: =(0)/157.5 -> 0 | BI27: =(0)/157.5 -> 0 | BJ27: =(0)/157.5 -> 0 | ... BL27: =(0)/157.5 -> 0 | BM27: =(0)/165 -> 0 | BN27: =(0)/165 -> 0 | BO27: =(0)/165 -> 0 | BP27: =(0)/165 -> 0 | BQ27: =(0)/165 -> 0 | BR27: =(0)/165 -> 0 | BS27: =(0)/165 -> 0 | BT27: =(0)/165 -> 0 | ... BV27: =(0)/165 -> 0 | BW27: =(0)/150 -> 0 | BX27: =(0)/150 -> 0 | BY27: =(0)/150 -> 0 | BZ27: =(0)/150 -> 0 | CA27: =(0)/150 -> 0 | CB27: =(0)/150 -> 0 | CC27: =(0)/150 -> 0 | CD27: =(0)/150 -> 0 | ... CF27: =(0)/150 -> 0 | CG27: =(0)/135 -> 0 | CH27: =(0)/135 -> 0 | CI27: =(0)/135 -> 0 | CJ27: =(0)/135 -> 0 | CK27: =(0)/135 -> 0 | CL27: =(0)/135 -> 0 | CM27: =(0)/135 -> 0 | CN27: =(0)/135 -> 0 | ... CP27: =(0)/135 -> 0 | CQ27: =0/157.5 -> 0 | CR27: =0/157.5 -> 0 | CS27: =0/157.5 -> 0 | CT27: =0/157.5 -> 0 | CU27: =0/157.5 -> 0 | CV27: =0/172.5 -> 0 | CW27: =0/172.5 -> 0 | CX27: =0/157.5 -> 0 | CY27: =0/157.5 -> 0 | CZ27: =0/157.5 -> 0 | DA27: =0/157.5 -> 0 | DB27: =0/157.5 -> 0 | DC27: =0/172.5 -> 0 | DD27: =0/172.5 -> 0 | DE27: =0/127.5 -> 0 | DF27: =0/127.5 -> 0 | DG27: =0/127.5 -> 0 | DH27: =0/127.5 -> 0 | DI27: =0/127.5 -> 0 | DJ27: =0/172.5 -> 0 | DK27: =0/172.5 -> 0 | DL27: =0/142.5 -> 0 | DM27: =0/142.5 -> 0 | DN27: =0/142.5 -> 0 | DO27: =0/142.5 -> 0 | DP27: =0/142.5 -> 0 | DQ27: =0/172.5 -> 0 | DR27: =0/172.5 -> 0 | DS27: =0/172.5 -> 0
N28: 実績 | O28: =(0)/120 -> 0 | P28: =(4.5+5.5)/120 -> 0.083333333 | Q28: =(0)/120 -> 0 | R28: =(0)/120 -> 0 | S28: =(6+18)/120 -> 0.2 | T28: =(0)/120 -> 0 | U28: =(0)/120 -> 0 | V28: =(0)/120 -> 0 | W28: =(0)/120 -> 0 | X28: =(14+15)/120 -> 0.24166667 | Y28: =(0)/157.5 -> 0 | Z28: =(0)/157.5 -> 0 | AA28: =(0)/157.5 -> 0 | AB28: =(0)/157.5 -> 0 | AC28: =(1)/157.5 -> 0.0063492063 | AD28: =(0)/157.5 -> 0 | AE28: =(0)/157.5 -> 0 | AF28: =(0)/157.5 -> 0 | AG28: =(0)/157.5 -> 0 | AH28: =(0)/157.5 -> 0 | AI28: =(0)/157.5 -> 0 | AJ28: =(0)/157.5 -> 0 | AK28: =(0)/157.5 -> 0 | ... AR28: =(0)/157.5 -> 0 | AS28: =(0)/165 -> 0 | AT28: =(0)/165 -> 0 | AU28: =(0)/165 -> 0 | AV28: =(0)/165 -> 0 | AW28: =(0)/165 -> 0 | AX28: =(0)/165 -> 0 | AY28: =(0)/165 -> 0 | AZ28: =(0)/165 -> 0 | ... BB28: =(0)/165 -> 0 | BC28: =(0)/157.5 -> 0 | BD28: =(0)/157.5 -> 0 | BE28: =(0)/157.5 -> 0 | BF28: =(0)/157.5 -> 0 | BG28: =(0)/157.5 -> 0 | BH28: =(0)/157.5 -> 0 | BI28: =(0)/157.5 -> 0 | BJ28: =(0)/157.5 -> 0 | ... BL28: =(0)/157.5 -> 0 | BM28: =(0)/165 -> 0 | BN28: =(0)/165 -> 0 | BO28: =(0)/165 -> 0 | BP28: =(0)/165 -> 0 | BQ28: =(0)/165 -> 0 | BR28: =(0)/165 -> 0 | BS28: =(0)/165 -> 0 | BT28: =(0)/165 -> 0 | ... BV28: =(0)/165 -> 0 | BW28: =(0)/150 -> 0 | BX28: =(0)/150 -> 0 | BY28: =(0)/150 -> 0 | BZ28: =(0)/150 -> 0 | CA28: =(0)/150 -> 0 | CB28: =(0)/150 -> 0 | CC28: =(0)/150 -> 0 | CD28: =(0)/150 -> 0 | ... CF28: =(0)/150 -> 0 | CG28: =(0)/135 -> 0 | CH28: =(0)/135 -> 0 | CI28: =(0)/135 -> 0 | CJ28: =(0)/135 -> 0 | CK28: =(0)/135 -> 0 | CL28: =(0)/135 -> 0 | CM28: =(0)/135 -> 0 | CN28: =(0)/135 -> 0 | ... CP28: =(0)/135 -> 0 | CQ28: =0/157.5 -> 0 | CR28: =0/157.5 -> 0 | CS28: =0/157.5 -> 0 | CT28: =0/157.5 -> 0 | CU28: =0/157.5 -> 0 | CV28: =0/172.5 -> 0 | CW28: =0/172.5 -> 0 | CX28: =0/157.5 -> 0 | CY28: =0/157.5 -> 0 | CZ28: =0/157.5 -> 0 | DA28: =0/157.5 -> 0 | DB28: =0/157.5 -> 0 | DC28: =0/172.5 -> 0 | DD28: =0/172.5 -> 0 | DE28: =0/127.5 -> 0 | DF28: =0/127.5 -> 0 | DG28: =0/127.5 -> 0 | DH28: =0/127.5 -> 0 | DI28: =0/127.5 -> 0 | DJ28: =0/172.5 -> 0 | DK28: =0/172.5 -> 0 | DL28: =0/142.5 -> 0 | DM28: =0/142.5 -> 0 | DN28: =0/142.5 -> 0 | DO28: =0/142.5 -> 0 | DP28: =0/142.5 -> 0 | DQ28: =0/172.5 -> 0 | DR28: =0/172.5 -> 0 | DS28: =0/172.5 -> 0
A29: 12 | B29: 完了 | C29: その他 | D29: 田中 | E29: AH21 | G29: 【ツール開発】HULFTログからの一覧作成 | H29: =SUM(CG29:CP29) -> 0 | I29: =SUM(CG30:CP30) -> 0 | N29: 計画 | O29: =(0)/120 -> 0 | P29: =(6)/120 -> 0.05 | Q29: =(0)/120 -> 0 | R29: =(0)/120 -> 0 | S29: =(0)/120 -> 0 | T29: =(0)/120 -> 0 | U29: =(0)/120 -> 0 | V29: =(5)/120 -> 0.041666667 | W29: =(0)/120 -> 0 | X29: =(0)/120 -> 0 | Y29: =(0)/150 -> 0 | Z29: =(0)/150 -> 0 | AA29: =(0)/150 -> 0 | AB29: =(0)/150 -> 0 | AC29: =(0)/150 -> 0 | AD29: =(0)/150 -> 0 | AE29: =(0)/150 -> 0 | AF29: =(0)/150 -> 0 | ... AH29: =(0)/150 -> 0 | AI29: =(0)/157.5 -> 0 | AJ29: =(0)/157.5 -> 0 | AK29: =(0)/157.5 -> 0 | AL29: =(0)/157.5 -> 0 | AM29: =(0)/157.5 -> 0 | AN29: =(0)/157.5 -> 0 | AO29: =(0)/157.5 -> 0 | AP29: =(0)/157.5 -> 0 | ... AR29: =(0)/157.5 -> 0 | AS29: =(0)/165 -> 0 | AT29: =(0)/165 -> 0 | AU29: =(0)/165 -> 0 | AV29: =(0)/165 -> 0 | AW29: =(0)/165 -> 0 | AX29: =(0)/165 -> 0 | AY29: =(0)/165 -> 0 | AZ29: =(0)/165 -> 0 | ... BB29: =(0)/165 -> 0 | BC29: =(0)/157.5 -> 0 | BD29: =(0)/157.5 -> 0 | BE29: =(0)/157.5 -> 0 | BF29: =(0)/157.5 -> 0 | BG29: =(0)/157.5 -> 0 | BH29: =(0)/157.5 -> 0 | BI29: =(0)/157.5 -> 0 | BJ29: =(0)/157.5 -> 0 | ... BL29: =(0)/157.5 -> 0 | BM29: =(0)/165 -> 0 | BN29: =(0)/165 -> 0 | BO29: =(0)/165 -> 0 | BP29: =(0)/165 -> 0 | BQ29: =(0)/165 -> 0 | BR29: =(0)/165 -> 0 | BS29: =(0)/165 -> 0 | BT29: =(0)/165 -> 0 | ... BV29: =(0)/165 -> 0 | BW29: =(0)/150 -> 0 | BX29: =(0)/150 -> 0 | BY29: =(0)/150 -> 0 | BZ29: =(0)/150 -> 0 | CA29: =(0)/150 -> 0 | CB29: =(0)/150 -> 0 | CC29: =(0)/150 -> 0 | CD29: =(0)/150 -> 0 | ... CF29: =(0)/150 -> 0 | CG29: =(0)/135 -> 0 | CH29: =(0)/135 -> 0 | CI29: =(0)/135 -> 0 | CJ29: =(0)/135 -> 0 | CK29: =(0)/135 -> 0 | CL29: =(0)/135 -> 0 | CM29: =(0)/135 -> 0 | CN29: =(0)/135 -> 0 | ... CP29: =(0)/135 -> 0 | CQ29: =0/157.5 -> 0 | CR29: =0/157.5 -> 0 | CS29: =0/157.5 -> 0 | CT29: =0/157.5 -> 0 | CU29: =0/157.5 -> 0 | CV29: =0/172.5 -> 0 | CW29: =0/172.5 -> 0 | CX29: =0/157.5 -> 0 | CY29: =0/157.5 -> 0 | CZ29: =0/157.5 -> 0 | DA29: =0/157.5 -> 0 | DB29: =0/157.5 -> 0 | DC29: =0/172.5 -> 0 | DD29: =0/172.5 -> 0 | DE29: =0/127.5 -> 0 | DF29: =0/127.5 -> 0 | DG29: =0/127.5 -> 0 | DH29: =0/127.5 -> 0 | DI29: =0/127.5 -> 0 | DJ29: =0/172.5 -> 0 | DK29: =0/172.5 -> 0 | DL29: =0/142.5 -> 0 | DM29: =0/142.5 -> 0 | DN29: =0/142.5 -> 0 | DO29: =0/142.5 -> 0 | DP29: =0/142.5 -> 0 | DQ29: =0/172.5 -> 0 | DR29: =0/172.5 -> 0 | DS29: =0/172.5 -> 0
N30: 実績 | O30: =(0)/120 -> 0 | P30: =(4.5)/120 -> 0.0375 | Q30: =(0)/120 -> 0 | R30: =(0)/120 -> 0 | S30: =(0)/120 -> 0 | T30: =(0)/120 -> 0 | U30: =(0)/120 -> 0 | V30: =(4)/120 -> 0.033333333 | W30: =(0)/120 -> 0 | X30: =(0)/120 -> 0 | Y30: =(0)/150 -> 0 | Z30: =(0)/150 -> 0 | AA30: =(0)/150 -> 0 | AB30: =(0)/150 -> 0 | AC30: =(0)/150 -> 0 | AD30: =(0)/150 -> 0 | AE30: =(0)/150 -> 0 | AF30: =(0)/150 -> 0 | ... AH30: =(0)/150 -> 0 | AI30: =(0)/157.5 -> 0 | AJ30: =(0)/157.5 -> 0 | AK30: =(0)/157.5 -> 0 | AL30: =(0)/157.5 -> 0 | AM30: =(0)/157.5 -> 0 | AN30: =(0)/157.5 -> 0 | AO30: =(0)/157.5 -> 0 | AP30: =(0)/157.5 -> 0 | ... AR30: =(0)/157.5 -> 0 | AS30: =(0)/165 -> 0 | AT30: =(0)/165 -> 0 | AU30: =(0)/165 -> 0 | AV30: =(0)/165 -> 0 | AW30: =(0)/165 -> 0 | AX30: =(0)/165 -> 0 | AY30: =(0)/165 -> 0 | AZ30: =(0)/165 -> 0 | ... BB30: =(0)/165 -> 0 | BC30: =(0)/157.5 -> 0 | BD30: =(0)/157.5 -> 0 | BE30: =(0)/157.5 -> 0 | BF30: =(0)/157.5 -> 0 | BG30: =(0)/157.5 -> 0 | BH30: =(0)/157.5 -> 0 | BI30: =(0)/157.5 -> 0 | BJ30: =(0)/157.5 -> 0 | ... BL30: =(0)/157.5 -> 0 | BM30: =(0)/165 -> 0 | BN30: =(0)/165 -> 0 | BO30: =(0)/165 -> 0 | BP30: =(0)/165 -> 0 | BQ30: =(0)/165 -> 0 | BR30: =(0)/165 -> 0 | BS30: =(0)/165 -> 0 | BT30: =(0)/165 -> 0 | ... BV30: =(0)/165 -> 0 | BW30: =(0)/150 -> 0 | BX30: =(0)/150 -> 0 | BY30: =(0)/150 -> 0 | BZ30: =(0)/150 -> 0 | CA30: =(0)/150 -> 0 | CB30: =(0)/150 -> 0 | CC30: =(0)/150 -> 0 | CD30: =(0)/150 -> 0 | ... CF30: =(0)/150 -> 0 | CG30: =(0)/135 -> 0 | CH30: =(0)/135 -> 0 | CI30: =(0)/135 -> 0 | CJ30: =(0)/135 -> 0 | CK30: =(0)/135 -> 0 | CL30: =(0)/135 -> 0 | CM30: =(0)/135 -> 0 | CN30: =(0)/135 -> 0 | ... CP30: =(0)/135 -> 0 | CQ30: =0/157.5 -> 0 | CR30: =0/157.5 -> 0 | CS30: =0/157.5 -> 0 | CT30: =0/157.5 -> 0 | CU30: =0/157.5 -> 0 | CV30: =0/172.5 -> 0 | CW30: =0/172.5 -> 0 | CX30: =0/157.5 -> 0 | CY30: =0/157.5 -> 0 | CZ30: =0/157.5 -> 0 | DA30: =0/157.5 -> 0 | DB30: =0/157.5 -> 0 | DC30: =0/172.5 -> 0 | DD30: =0/172.5 -> 0 | DE30: =0/127.5 -> 0 | DF30: =0/127.5 -> 0 | DG30: =0/127.5 -> 0 | DH30: =0/127.5 -> 0 | DI30: =0/127.5 -> 0 | DJ30: =0/172.5 -> 0 | DK30: =0/172.5 -> 0 | DL30: =0/142.5 -> 0 | DM30: =0/142.5 -> 0 | DN30: =0/142.5 -> 0 | DO30: =0/142.5 -> 0 | DP30: =0/142.5 -> 0 | DQ30: =0/172.5 -> 0 | DR30: =0/172.5 -> 0 | DS30: =0/172.5 -> 0
A31: 13 | B31: 完了 | C31: その他 | D31: 安藤 | E31: WA1 | G31: 【WB4】【開発依頼】作業の自動化 | H31: =SUM(CG31:CP31) -> 0 | I31: =SUM(CG32:CP32) -> 0 | N31: 計画 | O31: =0/127.5 -> 0 | P31: =0/127.5 -> 0 | Q31: =0/127.5 -> 0 | R31: =0/127.5 -> 0 | S31: =0/127.5 -> 0 | T31: =0/127.5 -> 0 | U31: =0/127.5 -> 0 | V31: =0/127.5 -> 0 | ... X31: =0/127.5 -> 0 | Y31: =(5)/157.5 -> 0.031746032 | Z31: =(35)/157.5 -> 0.22222222 | AA31: =(0)/157.5 -> 0 | AB31: =(0)/157.5 -> 0 | AC31: =(15)/157.5 -> 0.095238095 | AD31: =(0)/157.5 -> 0 | AE31: =(10)/157.5 -> 0.063492063 | AF31: =(10)/157.5 -> 0.063492063 | AG31: =(0)/157.5 -> 0 | AH31: =(0)/157.5 -> 0 | AI31: =(0)/157.5 -> 0 | AJ31: =(16.5)/157.5 -> 0.1047619 | AK31: =(0)/157.5 -> 0 | AL31: =(0)/157.5 -> 0 | AM31: =(0)/157.5 -> 0 | AN31: =(0)/157.5 -> 0 | AO31: =(16.5)/157.5 -> 0.1047619 | AP31: =(0)/157.5 -> 0 | AQ31: =(0)/157.5 -> 0 | AR31: =(0)/157.5 -> 0 | AS31: =(0)/165 -> 0 | AT31: =(0)/165 -> 0 | AU31: =(0)/165 -> 0 | AV31: =(0)/165 -> 0 | AW31: =(0)/165 -> 0 | AX31: =(0)/165 -> 0 | AY31: =(0)/165 -> 0 | AZ31: =(0)/165 -> 0 | ... BB31: =(0)/165 -> 0 | BC31: =(0)/157.5 -> 0 | BD31: =(0)/157.5 -> 0 | BE31: =(0)/157.5 -> 0 | BF31: =(0)/157.5 -> 0 | BG31: =(0)/157.5 -> 0 | BH31: =(0)/157.5 -> 0 | BI31: =(0)/157.5 -> 0 | BJ31: =(0)/157.5 -> 0 | ... BL31: =(0)/157.5 -> 0 | BM31: =(0)/165 -> 0 | BN31: =(0)/165 -> 0 | BO31: =(0)/165 -> 0 | BP31: =(0)/165 -> 0 | BQ31: =(0)/165 -> 0 | BR31: =(0)/165 -> 0 | BS31: =(0)/165 -> 0 | BT31: =(0)/165 -> 0 | ... BV31: =(0)/165 -> 0 | BW31: =(0)/150 -> 0 | BX31: =(0)/150 -> 0 | BY31: =(0)/150 -> 0 | BZ31: =(0)/150 -> 0 | CA31: =(0)/150 -> 0 | CB31: =(0)/150 -> 0 | CC31: =(0)/150 -> 0 | CD31: =(0)/150 -> 0 | ... CF31: =(0)/150 -> 0 | CG31: =(0)/135 -> 0 | CH31: =(0)/135 -> 0 | CI31: =(0)/135 -> 0 | CJ31: =(0)/135 -> 0 | CK31: =(0)/135 -> 0 | CL31: =(0)/135 -> 0 | CM31: =(0)/135 -> 0 | CN31: =(0)/135 -> 0 | ... CP31: =(0)/135 -> 0 | CQ31: =0/157.5 -> 0 | CR31: =0/157.5 -> 0 | CS31: =0/157.5 -> 0 | CT31: =0/157.5 -> 0 | CU31: =0/157.5 -> 0 | CV31: =0/172.5 -> 0 | CW31: =0/172.5 -> 0 | CX31: =0/157.5 -> 0 | CY31: =0/157.5 -> 0 | CZ31: =0/157.5 -> 0 | DA31: =0/157.5 -> 0 | DB31: =0/157.5 -> 0 | DC31: =0/172.5 -> 0 | DD31: =0/172.5 -> 0 | DE31: =0/127.5 -> 0 | DF31: =0/127.5 -> 0 | DG31: =0/127.5 -> 0 | DH31: =0/127.5 -> 0 | DI31: =0/127.5 -> 0 | DJ31: =0/172.5 -> 0 | DK31: =0/172.5 -> 0 | DL31: =0/142.5 -> 0 | DM31: =0/142.5 -> 0 | DN31: =0/142.5 -> 0 | DO31: =0/142.5 -> 0 | DP31: =0/142.5 -> 0 | DQ31: =0/172.5 -> 0 | DR31: =0/172.5 -> 0 | DS31: =0/172.5 -> 0
N32: 実績 | O32: =0/127.5 -> 0 | P32: =0/127.5 -> 0 | Q32: =0/127.5 -> 0 | R32: =0/127.5 -> 0 | S32: =0/127.5 -> 0 | T32: =0/127.5 -> 0 | U32: =0/127.5 -> 0 | V32: =0/127.5 -> 0 | ... X32: =0/127.5 -> 0 | Y32: =(2)/157.5 -> 0.012698413 | Z32: =(10.5+18.5+2)/157.5 -> 0.1968254 | AA32: =(0)/157.5 -> 0 | AB32: =(0)/157.5 -> 0 | AC32: =(11)/157.5 -> 0.06984127 | AD32: =(0+0.5)/157.5 -> 0.0031746032 | AE32: =(11+1.5)/157.5 -> 0.079365079 | AF32: =(4+1)/157.5 -> 0.031746032 | AG32: =(0)/157.5 -> 0 | AH32: =(0)/157.5 -> 0 | AI32: =(0)/157.5 -> 0 | AJ32: =(4.5+9)/157.5 -> 0.085714286 | AK32: =(0)/157.5 -> 0 | AL32: =(0)/157.5 -> 0 | AM32: =(0)/157.5 -> 0 | AN32: =(0)/157.5 -> 0 | AO32: =(8+10.5)/157.5 -> 0.11746032 | AP32: =(0)/157.5 -> 0 | AQ32: =(0)/157.5 -> 0 | AR32: =(0)/157.5 -> 0 | AS32: =(0)/165 -> 0 | AT32: =(0)/165 -> 0 | AU32: =(0)/165 -> 0 | AV32: =(0)/165 -> 0 | AW32: =(0)/165 -> 0 | AX32: =(0)/165 -> 0 | AY32: =(0)/165 -> 0 | AZ32: =(0)/165 -> 0 | ... BB32: =(0)/165 -> 0 | BC32: =(0)/157.5 -> 0 | BD32: =(0)/157.5 -> 0 | BE32: =(0)/157.5 -> 0 | BF32: =(0)/157.5 -> 0 | BG32: =(0)/157.5 -> 0 | BH32: =(0)/157.5 -> 0 | BI32: =(0)/157.5 -> 0 | BJ32: =(0)/157.5 -> 0 | ... BL32: =(0)/157.5 -> 0 | BM32: =(0)/165 -> 0 | BN32: =(0)/165 -> 0 | BO32: =(0)/165 -> 0 | BP32: =(0)/165 -> 0 | BQ32: =(0)/165 -> 0 | BR32: =(0)/165 -> 0 | BS32: =(0)/165 -> 0 | BT32: =(0)/165 -> 0 | ... BV32: =(0)/165 -> 0 | BW32: =(0)/150 -> 0 | BX32: =(0)/150 -> 0 | BY32: =(0)/150 -> 0 | BZ32: =(0)/150 -> 0 | CA32: =(0)/150 -> 0 | CB32: =(0)/150 -> 0 | CC32: =(0)/150 -> 0 | CD32: =(0)/150 -> 0 | ... CF32: =(0)/150 -> 0 | CG32: =(0)/135 -> 0 | CH32: =(0)/135 -> 0 | CI32: =(0)/135 -> 0 | CJ32: =(0)/135 -> 0 | CK32: =(0)/135 -> 0 | CL32: =(0)/135 -> 0 | CM32: =(0)/135 -> 0 | CN32: =(0)/135 -> 0 | ... CP32: =(0)/135 -> 0 | CQ32: =0/157.5 -> 0 | CR32: =0/157.5 -> 0 | CS32: =0/157.5 -> 0 | CT32: =0/157.5 -> 0 | CU32: =0/157.5 -> 0 | CV32: =0/172.5 -> 0 | CW32: =0/172.5 -> 0 | CX32: =0/157.5 -> 0 | CY32: =0/157.5 -> 0 | CZ32: =0/157.5 -> 0 | DA32: =0/157.5 -> 0 | DB32: =0/157.5 -> 0 | DC32: =0/172.5 -> 0 | DD32: =0/172.5 -> 0 | DE32: =0/127.5 -> 0 | DF32: =0/127.5 -> 0 | DG32: =0/127.5 -> 0 | DH32: =0/127.5 -> 0 | DI32: =0/127.5 -> 0 | DJ32: =0/172.5 -> 0 | DK32: =0/172.5 -> 0 | DL32: =0/142.5 -> 0 | DM32: =0/142.5 -> 0 | DN32: =0/142.5 -> 0 | DO32: =0/142.5 -> 0 | DP32: =0/142.5 -> 0 | DQ32: =0/172.5 -> 0 | DR32: =0/172.5 -> 0 | DS32: =0/172.5 -> 0
A33: 14 | B33: 完了 | C33: その他 | D33: 谷口 | E33: WT11 | G33: 【開発依頼】Windows11動作検証 | H33: =SUM(CG33:CP33) -> 0 | I33: =SUM(CG34:CP34) -> 0 | N33: 計画 | O33: =0/127.5 -> 0 | P33: =0/127.5 -> 0 | Q33: =0/127.5 -> 0 | R33: =0/127.5 -> 0 | S33: =0/127.5 -> 0 | T33: =0/127.5 -> 0 | U33: =0/127.5 -> 0 | V33: =0/127.5 -> 0 | ... X33: =0/127.5 -> 0 | Y33: =(0)/157.5 -> 0 | Z33: =(35)/157.5 -> 0.22222222 | AA33: =(0)/157.5 -> 0 | AB33: =(20)/157.5 -> 0.12698413 | AC33: =(0)/157.5 -> 0 | AD33: =(0)/157.5 -> 0 | AE33: =(0)/157.5 -> 0 | AF33: =(35)/157.5 -> 0.22222222 | AG33: =(5)/157.5 -> 0.031746032 | AH33: =(0)/157.5 -> 0 | AI33: =(0)/157.5 -> 0 | AJ33: =(75.25)/157.5 -> 0.47777778 | AK33: =(75.25+22.5)/157.5 -> 0.62063492 | AL33: =(10)/157.5 -> 0.063492063 | AM33: =(75.25)/157.5 -> 0.47777778 | AN33: =(0)/157.5 -> 0 | AO33: =(75.25)/157.5 -> 0.47777778 | AP33: =(75.25)/157.5 -> 0.47777778 | AQ33: =(75.25)/157.5 -> 0.47777778 | AR33: =(32.25)/157.5 -> 0.2047619 | AS33: =(0)/165 -> 0 | AT33: =(95)/165 -> 0.57575758 | AU33: =(30)/165 -> 0.18181818 | AV33: =(0)/165 -> 0 | AW33: =(18)/165 -> 0.10909091 | AX33: =(60)/165 -> 0.36363636 | AY33: =(95)/165 -> 0.57575758 | AZ33: =(0)/165 -> 0 | BA33: =(40)/165 -> 0.24242424 | BB33: =(80)/165 -> 0.48484848 | BC33: =(0)/157.5 -> 0 | BD33: =(100)/157.5 -> 0.63492063 | BE33: =(65)/157.5 -> 0.41269841 | BF33: =(0)/157.5 -> 0 | BG33: =(0)/157.5 -> 0 | BH33: =(100)/157.5 -> 0.63492063 | BI33: =(85)/157.5 -> 0.53968254 | BJ33: =(20)/157.5 -> 0.12698413 | BK33: =(50)/157.5 -> 0.31746032 | BL33: =(100)/157.5 -> 0.63492063 | BM33: =(0)/165 -> 0 | BN33: =(0)/165 -> 0 | BO33: =(0)/165 -> 0 | BP33: =(0)/165 -> 0 | BQ33: =(0)/165 -> 0 | BR33: =(0)/165 -> 0 | BS33: =(0)/165 -> 0 | BT33: =(0)/165 -> 0 | ... BV33: =(0)/165 -> 0 | BW33: =(0)/150 -> 0 | BX33: =(0)/150 -> 0 | BY33: =(0)/150 -> 0 | BZ33: =(0)/150 -> 0 | CA33: =(0)/150 -> 0 | CB33: =(0)/150 -> 0 | CC33: =(0)/150 -> 0 | CD33: =(0)/150 -> 0 | ... CF33: =(0)/150 -> 0 | CG33: =(0)/135 -> 0 | CH33: =(0)/135 -> 0 | CI33: =(0)/135 -> 0 | CJ33: =(0)/135 -> 0 | CK33: =(0)/135 -> 0 | CL33: =(0)/135 -> 0 | CM33: =(0)/135 -> 0 | CN33: =(0)/135 -> 0 | ... CP33: =(0)/135 -> 0 | CQ33: =0/157.5 -> 0 | CR33: =0/157.5 -> 0 | CS33: =0/157.5 -> 0 | CT33: =0/157.5 -> 0 | CU33: =0/157.5 -> 0 | CV33: =0/172.5 -> 0 | CW33: =0/172.5 -> 0 | CX33: =0/157.5 -> 0 | CY33: =0/157.5 -> 0 | CZ33: =0/157.5 -> 0 | DA33: =0/157.5 -> 0 | DB33: =0/157.5 -> 0 | DC33: =0/172.5 -> 0 | DD33: =0/172.5 -> 0 | DE33: =0/127.5 -> 0 | DF33: =0/127.5 -> 0 | DG33: =0/127.5 -> 0 | DH33: =0/127.5 -> 0 | DI33: =0/127.5 -> 0 | DJ33: =0/172.5 -> 0 | DK33: =0/172.5 -> 0 | DL33: =0/142.5 -> 0 | DM33: =0/142.5 -> 0 | DN33: =0/142.5 -> 0 | DO33: =0/142.5 -> 0 | DP33: =0/142.5 -> 0 | DQ33: =0/172.5 -> 0 | DR33: =0/172.5 -> 0 | DS33: =0/172.5 -> 0
N34: 実績 | O34: =0/127.5 -> 0 | P34: =0/127.5 -> 0 | Q34: =0/127.5 -> 0 | R34: =0/127.5 -> 0 | S34: =0/127.5 -> 0 | T34: =0/127.5 -> 0 | U34: =0/127.5 -> 0 | V34: =0/127.5 -> 0 | ... X34: =0/127.5 -> 0 | Y34: =(0)/157.5 -> 0 | Z34: =(2+13+12.5)/157.5 -> 0.17460317 | AA34: =(0)/157.5 -> 0 | AB34: =(4+2)/157.5 -> 0.038095238 | AC34: =(0+5+3)/157.5 -> 0.050793651 | AD34: =(0)/157.5 -> 0 | AE34: =(0)/157.5 -> 0 | AF34: =(0+34.5+10)/157.5 -> 0.28253968 | AG34: =(0+5.5)/157.5 -> 0.034920635 | AH34: =(0)/157.5 -> 0 | AI34: =(0)/157.5 -> 0 | AJ34: =(16.5+20.5+14.5+13+13)/157.5 -> 0.49206349 | AK34: =(15+27.5+29.5+23.5+17.5)/157.5 -> 0.71746032 | AL34: =(0+4)/157.5 -> 0.025396825 | AM34: =(0+6+29.5+20.5+10)/157.5 -> 0.41904762 | AN34: =(0)/157.5 -> 0 | AO34: =(0+14+17+13+8.5)/157.5 -> 0.33333333 | AP34: =(21+27.5+18.5)/157.5 -> 0.42539683 | AQ34: =(15+19+25.5+29.5+15.5)/157.5 -> 0.66349206 | AR34: =(0+16+14.5)/157.5 -> 0.19365079 | AS34: =(0)/165 -> 0 | AT34: =(7+16+26.5+27.5+16+2.5)/165 -> 0.57878788 | AU34: =(12+13)/165 -> 0.15151515 | AV34: =(0)/165 -> 0 | AW34: =(6+6)/165 -> 0.072727273 | AX34: =(0+20.5+27+6)/165 -> 0.32424242 | AY34: =(3+19.5+20+25.5+27.5+4.5)/165 -> 0.60606061 | AZ34: =(0)/165 -> 0 | BA34: =(6+13+18.5+3)/165 -> 0.24545455 | BB34: =(12+21.5+23+21.5+1)/165 -> 0.47878788 | BC34: =(0)/157.5 -> 0 | BD34: =(24.5+32+28+13.5)/157.5 -> 0.62222222 | BE34: =(0+21+10+4.5)/157.5 -> 0.22539683 | BF34: =(0)/157.5 -> 0 | BG34: =(0)/157.5 -> 0 | BH34: =(27.5+24.5+30+22)/157.5 -> 0.66031746 | BI34: =(21+34.5+23+5.5)/157.5 -> 0.53333333 | BJ34: =(0+15+10)/157.5 -> 0.15873016 | BK34: =(0+19+19+12)/157.5 -> 0.31746032 | BL34: =(28+33+32.5+20+8)/157.5 -> 0.77142857 | BM34: =(0)/165 -> 0 | BN34: =(0)/165 -> 0 | BO34: =(0)/165 -> 0 | BP34: =(0)/165 -> 0 | BQ34: =(0)/165 -> 0 | BR34: =(0)/165 -> 0 | BS34: =(0)/165 -> 0 | BT34: =(0)/165 -> 0 | ... BV34: =(0)/165 -> 0 | BW34: =(0)/150 -> 0 | BX34: =(0)/150 -> 0 | BY34: =(0)/150 -> 0 | BZ34: =(0)/150 -> 0 | CA34: =(0)/150 -> 0 | CB34: =(0)/150 -> 0 | CC34: =(0)/150 -> 0 | CD34: =(0)/150 -> 0 | ... CF34: =(0)/150 -> 0 | CG34: =(0)/135 -> 0 | CH34: =(0)/135 -> 0 | CI34: =(0)/135 -> 0 | CJ34: =(0)/135 -> 0 | CK34: =(0)/135 -> 0 | CL34: =(0)/135 -> 0 | CM34: =(0)/135 -> 0 | CN34: =(0)/135 -> 0 | ... CP34: =(0)/135 -> 0 | CQ34: =0/157.5 -> 0 | CR34: =0/157.5 -> 0 | CS34: =0/157.5 -> 0 | CT34: =0/157.5 -> 0 | CU34: =0/157.5 -> 0 | CV34: =0/172.5 -> 0 | CW34: =0/172.5 -> 0 | CX34: =0/157.5 -> 0 | CY34: =0/157.5 -> 0 | CZ34: =0/157.5 -> 0 | DA34: =0/157.5 -> 0 | DB34: =0/157.5 -> 0 | DC34: =0/172.5 -> 0 | DD34: =0/172.5 -> 0 | DE34: =0/127.5 -> 0 | DF34: =0/127.5 -> 0 | DG34: =0/127.5 -> 0 | DH34: =0/127.5 -> 0 | DI34: =0/127.5 -> 0 | DJ34: =0/172.5 -> 0 | DK34: =0/172.5 -> 0 | DL34: =0/142.5 -> 0 | DM34: =0/142.5 -> 0 | DN34: =0/142.5 -> 0 | DO34: =0/142.5 -> 0 | DP34: =0/142.5 -> 0 | DQ34: =0/172.5 -> 0 | DR34: =0/172.5 -> 0 | DS34: =0/172.5 -> 0
A35: 15 | B35: 完了 | C35: その他 | D35: 仲井 | E35: BT1 | G35: 【全社】プリファレンステーブルの設定値最新化対応 | H35: =SUM(CG35:CP35) -> 0 | I35: =SUM(CG36:CP36) -> 0 | N35: 計画 | O35: =0/127.5 -> 0 | P35: =0/127.5 -> 0 | Q35: =0/127.5 -> 0 | R35: =0/127.5 -> 0 | S35: =0/127.5 -> 0 | T35: =0/127.5 -> 0 | U35: =0/127.5 -> 0 | V35: =0/127.5 -> 0 | ... X35: =0/127.5 -> 0 | Y35: =(0)/157.5 -> 0 | Z35: =(10)/157.5 -> 0.063492063 | AA35: =(0)/157.5 -> 0 | AB35: =(35)/157.5 -> 0.22222222 | AC35: =(0)/157.5 -> 0 | AD35: =(45)/157.5 -> 0.28571429 | AE35: =(0)/157.5 -> 0 | AF35: =(0)/157.5 -> 0 | AG35: =(0)/157.5 -> 0 | AH35: =(10)/157.5 -> 0.063492063 | AI35: =(0)/157.5 -> 0 | AJ35: =(4)/157.5 -> 0.025396825 | AK35: =(0)/157.5 -> 0 | AL35: =(39.8+35.8+29.8+10)/157.5 -> 0.73269841 | AM35: =(0)/157.5 -> 0 | AN35: =(39.8+10)/157.5 -> 0.31619048 | AO35: =(10)/157.5 -> 0.063492063 | AP35: =(0)/157.5 -> 0 | AQ35: =(0)/157.5 -> 0 | AR35: =(19.8)/157.5 -> 0.12571429 | AS35: =(0)/165 -> 0 | AT35: =(28)/165 -> 0.16969697 | AU35: =(0)/165 -> 0 | AV35: =(28)/165 -> 0.16969697 | AW35: =(28)/165 -> 0.16969697 | AX35: =(28)/165 -> 0.16969697 | AY35: =(0)/165 -> 0 | AZ35: =(0)/165 -> 0 | BA35: =(0)/165 -> 0 | BB35: =(28)/165 -> 0.16969697 | BC35: =(50)/157.5 -> 0.31746032 | BD35: =(0)/157.5 -> 0 | BE35: =(0)/157.5 -> 0 | BF35: =(115)/157.5 -> 0.73015873 | BG35: =(115)/157.5 -> 0.73015873 | BH35: =(0)/157.5 -> 0 | BI35: =(0)/157.5 -> 0 | BJ35: =(0)/157.5 -> 0 | BK35: =(10)/157.5 -> 0.063492063 | BL35: =(0)/157.5 -> 0 | BM35: =(0)/165 -> 0 | BN35: =(0)/165 -> 0 | BO35: =(0)/165 -> 0 | BP35: =(0)/165 -> 0 | BQ35: =(0)/165 -> 0 | BR35: =(0)/165 -> 0 | BS35: =(0)/165 -> 0 | BT35: =(0)/165 -> 0 | ... BV35: =(0)/165 -> 0 | BW35: =(0)/150 -> 0 | BX35: =(0)/150 -> 0 | BY35: =(0)/150 -> 0 | BZ35: =(0)/150 -> 0 | CA35: =(0)/150 -> 0 | CB35: =(0)/150 -> 0 | CC35: =(0)/150 -> 0 | CD35: =(0)/150 -> 0 | ... CF35: =(0)/150 -> 0 | CG35: =(0)/135 -> 0 | CH35: =(0)/135 -> 0 | CI35: =(0)/135 -> 0 | CJ35: =(0)/135 -> 0 | CK35: =(0)/135 -> 0 | CL35: =(0)/135 -> 0 | CM35: =(0)/135 -> 0 | CN35: =(0)/135 -> 0 | ... CP35: =(0)/135 -> 0 | CQ35: =0/157.5 -> 0 | CR35: =0/157.5 -> 0 | CS35: =0/157.5 -> 0 | CT35: =0/157.5 -> 0 | CU35: =0/157.5 -> 0 | CV35: =0/172.5 -> 0 | CW35: =0/172.5 -> 0 | CX35: =0/157.5 -> 0 | CY35: =0/157.5 -> 0 | CZ35: =0/157.5 -> 0 | DA35: =0/157.5 -> 0 | DB35: =0/157.5 -> 0 | DC35: =0/172.5 -> 0 | DD35: =0/172.5 -> 0 | DE35: =0/127.5 -> 0 | DF35: =0/127.5 -> 0 | DG35: =0/127.5 -> 0 | DH35: =0/127.5 -> 0 | DI35: =0/127.5 -> 0 | DJ35: =0/172.5 -> 0 | DK35: =0/172.5 -> 0 | DL35: =0/142.5 -> 0 | DM35: =0/142.5 -> 0 | DN35: =0/142.5 -> 0 | DO35: =0/142.5 -> 0 | DP35: =0/142.5 -> 0 | DQ35: =0/172.5 -> 0 | DR35: =0/172.5 -> 0 | DS35: =0/172.5 -> 0
N36: 実績 | O36: =0/127.5 -> 0 | P36: =0/127.5 -> 0 | Q36: =0/127.5 -> 0 | R36: =0/127.5 -> 0 | S36: =0/127.5 -> 0 | T36: =0/127.5 -> 0 | U36: =0/127.5 -> 0 | V36: =0/127.5 -> 0 | ... X36: =0/127.5 -> 0 | Y36: =(0)/157.5 -> 0 | Z36: =(6+1)/157.5 -> 0.044444444 | AA36: =(0)/157.5 -> 0 | AB36: =(20+14)/157.5 -> 0.21587302 | AC36: =(0)/157.5 -> 0 | AD36: =(28+13.5)/157.5 -> 0.26349206 | AE36: =(0+5.5)/157.5 -> 0.034920635 | AF36: =(0)/157.5 -> 0 | AG36: =(0)/157.5 -> 0 | AH36: =(5+3.5)/157.5 -> 0.053968254 | AI36: =(0)/157.5 -> 0 | AJ36: =(0+1)/157.5 -> 0.0063492063 | AK36: =(0)/157.5 -> 0 | AL36: =(21+28.5+30.5+27.5+13.5)/157.5 -> 0.76825397 | AM36: =(0)/157.5 -> 0 | AN36: =(15+27.5+11.5)/157.5 -> 0.34285714 | AO36: =(7)/157.5 -> 0.044444444 | AP36: =(0)/157.5 -> 0 | AQ36: =(0)/157.5 -> 0 | AR36: =(0+9.5+4)/157.5 -> 0.085714286 | AS36: =(0)/165 -> 0 | AT36: =(1)/165 -> 0.0060606061 | AU36: =(0)/165 -> 0 | AV36: =(8+16.5+10.5+10.5+10+3.5)/165 -> 0.35757576 | AW36: =(0+17.5+17.5+6.5)/165 -> 0.25151515 | AX36: =(0+19.5)/165 -> 0.11818182 | AY36: =(0)/165 -> 0 | AZ36: =(0)/165 -> 0 | BA36: =(0)/165 -> 0 | BB36: =(0+23.5)/165 -> 0.14242424 | BC36: =(9+9+6+4.5+3)/157.5 -> 0.2 | BD36: =(0)/157.5 -> 0 | BE36: =(0)/157.5 -> 0 | BF36: =(23+18.5+30+34.5+13.5)/157.5 -> 0.75873016 | BG36: =(56.5+25+23.5+9.5)/157.5 -> 0.72698413 | BH36: =(0)/157.5 -> 0 | BI36: =(0)/157.5 -> 0 | BJ36: =(0)/157.5 -> 0 | BK36: =(0+4)/157.5 -> 0.025396825 | BL36: =(0)/157.5 -> 0 | BM36: =(0)/165 -> 0 | BN36: =(0)/165 -> 0 | BO36: =(0)/165 -> 0 | BP36: =(0)/165 -> 0 | BQ36: =(0)/165 -> 0 | BR36: =(0)/165 -> 0 | BS36: =(0)/165 -> 0 | BT36: =(0)/165 -> 0 | ... BV36: =(0)/165 -> 0 | BW36: =(0)/150 -> 0 | BX36: =(0)/150 -> 0 | BY36: =(0)/150 -> 0 | BZ36: =(0)/150 -> 0 | CA36: =(0)/150 -> 0 | CB36: =(0)/150 -> 0 | CC36: =(0)/150 -> 0 | CD36: =(0)/150 -> 0 | ... CF36: =(0)/150 -> 0 | CG36: =(0)/135 -> 0 | CH36: =(0)/135 -> 0 | CI36: =(0)/135 -> 0 | CJ36: =(0)/135 -> 0 | CK36: =(0)/135 -> 0 | CL36: =(0)/135 -> 0 | CM36: =(0)/135 -> 0 | CN36: =(0)/135 -> 0 | ... CP36: =(0)/135 -> 0 | CQ36: =0/157.5 -> 0 | CR36: =0/157.5 -> 0 | CS36: =0/157.5 -> 0 | CT36: =0/157.5 -> 0 | CU36: =0/157.5 -> 0 | CV36: =0/172.5 -> 0 | CW36: =0/172.5 -> 0 | CX36: =0/157.5 -> 0 | CY36: =0/157.5 -> 0 | CZ36: =0/157.5 -> 0 | DA36: =0/157.5 -> 0 | DB36: =0/157.5 -> 0 | DC36: =0/172.5 -> 0 | DD36: =0/172.5 -> 0 | DE36: =0/127.5 -> 0 | DF36: =0/127.5 -> 0 | DG36: =0/127.5 -> 0 | DH36: =0/127.5 -> 0 | DI36: =0/127.5 -> 0 | DJ36: =0/172.5 -> 0 | DK36: =0/172.5 -> 0 | DL36: =0/142.5 -> 0 | DM36: =0/142.5 -> 0 | DN36: =0/142.5 -> 0 | DO36: =0/142.5 -> 0 | DP36: =0/142.5 -> 0 | DQ36: =0/172.5 -> 0 | DR36: =0/172.5 -> 0 | DS36: =0/172.5 -> 0
A37: 16 | B37: 完了 | C37: その他 | D37: 山本 | E37: BT2 | G37: (44)注文失効件数チェック処理の改善_横展開 | H37: =SUM(CG37:CP37) -> 0 | I37: =SUM(CG38:CP38) -> 0 | N37: 計画 | O37: =0/127.5 -> 0 | P37: =0/127.5 -> 0 | Q37: =0/127.5 -> 0 | R37: =0/127.5 -> 0 | S37: =0/127.5 -> 0 | T37: =0/127.5 -> 0 | U37: =0/127.5 -> 0 | V37: =0/127.5 -> 0 | ... X37: =0/127.5 -> 0 | Y37: =(0)/157.5 -> 0 | Z37: =(10)/157.5 -> 0.063492063 | AA37: =(0)/157.5 -> 0 | AB37: =(0)/157.5 -> 0 | AC37: =(20)/157.5 -> 0.12698413 | AD37: =(0)/157.5 -> 0 | AE37: =(0)/157.5 -> 0 | AF37: =(0)/157.5 -> 0 | AG37: =(0)/157.5 -> 0 | AH37: =(20)/157.5 -> 0.12698413 | AI37: =(0)/157.5 -> 0 | AJ37: =(5.67)/157.5 -> 0.036 | AK37: =(0)/157.5 -> 0 | AL37: =(0)/157.5 -> 0 | AM37: =(22.67)/157.5 -> 0.14393651 | AN37: =(0)/157.5 -> 0 | AO37: =(0)/157.5 -> 0 | AP37: =(0)/157.5 -> 0 | AQ37: =(0)/157.5 -> 0 | AR37: =(22.67+17)/157.5 -> 0.25187302 | AS37: =(0)/165 -> 0 | AT37: =(0)/165 -> 0 | AU37: =(0)/165 -> 0 | AV37: =(0)/165 -> 0 | AW37: =(0)/165 -> 0 | AX37: =(0)/165 -> 0 | AY37: =(0)/165 -> 0 | AZ37: =(0)/165 -> 0 | ... BB37: =(0)/165 -> 0 | BC37: =(0)/157.5 -> 0 | BD37: =(0)/157.5 -> 0 | BE37: =(0)/157.5 -> 0 | BF37: =(0)/157.5 -> 0 | BG37: =(0)/157.5 -> 0 | BH37: =(0)/157.5 -> 0 | BI37: =(0)/157.5 -> 0 | BJ37: =(0)/157.5 -> 0 | ... BL37: =(0)/157.5 -> 0 | BM37: =(0)/165 -> 0 | BN37: =(0)/165 -> 0 | BO37: =(0)/165 -> 0 | BP37: =(0)/165 -> 0 | BQ37: =(0)/165 -> 0 | BR37: =(0)/165 -> 0 | BS37: =(0)/165 -> 0 | BT37: =(0)/165 -> 0 | ... BV37: =(0)/165 -> 0 | BW37: =(0)/150 -> 0 | BX37: =(0)/150 -> 0 | BY37: =(0)/150 -> 0 | BZ37: =(0)/150 -> 0 | CA37: =(0)/150 -> 0 | CB37: =(0)/150 -> 0 | CC37: =(0)/150 -> 0 | CD37: =(0)/150 -> 0 | ... CF37: =(0)/150 -> 0 | CG37: =(0)/135 -> 0 | CH37: =(0)/135 -> 0 | CI37: =(0)/135 -> 0 | CJ37: =(0)/135 -> 0 | CK37: =(0)/135 -> 0 | CL37: =(0)/135 -> 0 | CM37: =(0)/135 -> 0 | CN37: =(0)/135 -> 0 | ... CP37: =(0)/135 -> 0 | CQ37: =0/157.5 -> 0 | CR37: =0/157.5 -> 0 | CS37: =0/157.5 -> 0 | CT37: =0/157.5 -> 0 | CU37: =0/157.5 -> 0 | CV37: =0/172.5 -> 0 | CW37: =0/172.5 -> 0 | CX37: =0/157.5 -> 0 | CY37: =0/157.5 -> 0 | CZ37: =0/157.5 -> 0 | DA37: =0/157.5 -> 0 | DB37: =0/157.5 -> 0 | DC37: =0/172.5 -> 0 | DD37: =0/172.5 -> 0 | DE37: =0/127.5 -> 0 | DF37: =0/127.5 -> 0 | DG37: =0/127.5 -> 0 | DH37: =0/127.5 -> 0 | DI37: =0/127.5 -> 0 | DJ37: =0/172.5 -> 0 | DK37: =0/172.5 -> 0 | DL37: =0/142.5 -> 0 | DM37: =0/142.5 -> 0 | DN37: =0/142.5 -> 0 | DO37: =0/142.5 -> 0 | DP37: =0/142.5 -> 0 | DQ37: =0/172.5 -> 0 | DR37: =0/172.5 -> 0 | DS37: =0/172.5 -> 0
N38: 実績 | O38: =0/127.5 -> 0 | P38: =0/127.5 -> 0 | Q38: =0/127.5 -> 0 | R38: =0/127.5 -> 0 | S38: =0/127.5 -> 0 | T38: =0/127.5 -> 0 | U38: =0/127.5 -> 0 | V38: =0/127.5 -> 0 | ... X38: =0/127.5 -> 0 | Y38: =(0)/157.5 -> 0 | Z38: =(3)/157.5 -> 0.019047619 | AA38: =(0)/157.5 -> 0 | AB38: =(0)/157.5 -> 0 | AC38: =(13+6)/157.5 -> 0.12063492 | AD38: =(0)/157.5 -> 0 | AE38: =(0)/157.5 -> 0 | AF38: =(0)/157.5 -> 0 | AG38: =(0)/157.5 -> 0 | AH38: =(16+6)/157.5 -> 0.13968254 | AI38: =(0)/157.5 -> 0 | AJ38: =(0+4)/157.5 -> 0.025396825 | AK38: =(0)/157.5 -> 0 | AL38: =(0)/157.5 -> 0 | AM38: =(6+18+4+2.5)/157.5 -> 0.19365079 | AN38: =(0)/157.5 -> 0 | AO38: =(0)/157.5 -> 0 | AP38: =(0)/157.5 -> 0 | AQ38: =(0)/157.5 -> 0 | AR38: =(15+18)/157.5 -> 0.20952381 | AS38: =(0)/165 -> 0 | AT38: =(0)/165 -> 0 | AU38: =(0)/165 -> 0 | AV38: =(0)/165 -> 0 | AW38: =(0)/165 -> 0 | AX38: =(0)/165 -> 0 | AY38: =(0)/165 -> 0 | AZ38: =(0)/165 -> 0 | ... BB38: =(0)/165 -> 0 | BC38: =(0)/157.5 -> 0 | BD38: =(0)/157.5 -> 0 | BE38: =(0)/157.5 -> 0 | BF38: =(0)/157.5 -> 0 | BG38: =(0)/157.5 -> 0 | BH38: =(0)/157.5 -> 0 | BI38: =(0)/157.5 -> 0 | BJ38: =(0)/157.5 -> 0 | ... BL38: =(0)/157.5 -> 0 | BM38: =(0)/165 -> 0 | BN38: =(0)/165 -> 0 | BO38: =(0)/165 -> 0 | BP38: =(0)/165 -> 0 | BQ38: =(0)/165 -> 0 | BR38: =(0)/165 -> 0 | BS38: =(0)/165 -> 0 | BT38: =(0)/165 -> 0 | ... BV38: =(0)/165 -> 0 | BW38: =(0)/150 -> 0 | BX38: =(0)/150 -> 0 | BY38: =(0)/150 -> 0 | BZ38: =(0)/150 -> 0 | CA38: =(0)/150 -> 0 | CB38: =(0)/150 -> 0 | CC38: =(0)/150 -> 0 | CD38: =(0)/150 -> 0 | ... CF38: =(0)/150 -> 0 | CG38: =(0)/135 -> 0 | CH38: =(0)/135 -> 0 | CI38: =(0)/135 -> 0 | CJ38: =(0)/135 -> 0 | CK38: =(0)/135 -> 0 | CL38: =(0)/135 -> 0 | CM38: =(0)/135 -> 0 | CN38: =(0)/135 -> 0 | ... CP38: =(0)/135 -> 0 | CQ38: =0/157.5 -> 0 | CR38: =0/157.5 -> 0 | CS38: =0/157.5 -> 0 | CT38: =0/157.5 -> 0 | CU38: =0/157.5 -> 0 | CV38: =0/172.5 -> 0 | CW38: =0/172.5 -> 0 | CX38: =0/157.5 -> 0 | CY38: =0/157.5 -> 0 | CZ38: =0/157.5 -> 0 | DA38: =0/157.5 -> 0 | DB38: =0/157.5 -> 0 | DC38: =0/172.5 -> 0 | DD38: =0/172.5 -> 0 | DE38: =0/127.5 -> 0 | DF38: =0/127.5 -> 0 | DG38: =0/127.5 -> 0 | DH38: =0/127.5 -> 0 | DI38: =0/127.5 -> 0 | DJ38: =0/172.5 -> 0 | DK38: =0/172.5 -> 0 | DL38: =0/142.5 -> 0 | DM38: =0/142.5 -> 0 | DN38: =0/142.5 -> 0 | DO38: =0/142.5 -> 0 | DP38: =0/142.5 -> 0 | DQ38: =0/172.5 -> 0 | DR38: =0/172.5 -> 0 | DS38: =0/172.5 -> 0
A39: 17 | B39: 完了 | C39: その他 | D39: 寺澤 | E39: SFA6 | G39: 【SFA】画面文言変更対応のお願い | H39: =SUM(CG39:CP39) -> 0 | I39: =SUM(CG40:CP40) -> 0 | N39: 計画 | O39: =0/127.5 -> 0 | P39: =0/127.5 -> 0 | Q39: =0/127.5 -> 0 | R39: =0/127.5 -> 0 | S39: =0/127.5 -> 0 | T39: =0/127.5 -> 0 | U39: =0/127.5 -> 0 | V39: =0/127.5 -> 0 | ... X39: =0/127.5 -> 0 | Y39: =0/142.5 -> 0 | Z39: =0/142.5 -> 0 | AA39: =0/142.5 -> 0 | AB39: =0/142.5 -> 0 | AC39: =0/142.5 -> 0 | AD39: =0/142.5 -> 0 | AE39: =0/165 -> 0 | AG39: =0/165 -> 0 | AH39: =0/165 -> 0 | AI39: =(0)/157.5 -> 0 | AJ39: =(10)/157.5 -> 0.063492063 | AK39: =(0)/157.5 -> 0 | AL39: =(0)/157.5 -> 0 | AM39: =(0)/157.5 -> 0 | AN39: =(0)/157.5 -> 0 | AO39: =(8)/157.5 -> 0.050793651 | AP39: =(0)/157.5 -> 0 | AQ39: =(0)/157.5 -> 0 | AR39: =(40)/157.5 -> 0.25396825 | AS39: =(0)/165 -> 0 | AT39: =(0)/165 -> 0 | AU39: =(0)/165 -> 0 | AV39: =(0)/165 -> 0 | AW39: =(0)/165 -> 0 | AX39: =(0)/165 -> 0 | AY39: =(0)/165 -> 0 | AZ39: =(0)/165 -> 0 | ... BB39: =(0)/165 -> 0 | BC39: =(0)/157.5 -> 0 | BD39: =(0)/157.5 -> 0 | BE39: =(0)/157.5 -> 0 | BF39: =(0)/157.5 -> 0 | BG39: =(0)/157.5 -> 0 | BH39: =(0)/157.5 -> 0 | BI39: =(0)/157.5 -> 0 | BJ39: =(0)/157.5 -> 0 | ... BL39: =(0)/157.5 -> 0 | BM39: =(0)/165 -> 0 | BN39: =(0)/165 -> 0 | BO39: =(0)/165 -> 0 | BP39: =(0)/165 -> 0 | BQ39: =(0)/165 -> 0 | BR39: =(0)/165 -> 0 | BS39: =(0)/165 -> 0 | BT39: =(0)/165 -> 0 | ... BV39: =(0)/165 -> 0 | BW39: =(0)/150 -> 0 | BX39: =(0)/150 -> 0 | BY39: =(0)/150 -> 0 | BZ39: =(0)/150 -> 0 | CA39: =(0)/150 -> 0 | CB39: =(0)/150 -> 0 | CC39: =(0)/150 -> 0 | CD39: =(0)/150 -> 0 | ... CF39: =(0)/150 -> 0 | CG39: =(0)/135 -> 0 | CH39: =(0)/135 -> 0 | CI39: =(0)/135 -> 0 | CJ39: =(0)/135 -> 0 | CK39: =(0)/135 -> 0 | CL39: =(0)/135 -> 0 | CM39: =(0)/135 -> 0 | CN39: =(0)/135 -> 0 | ... CP39: =(0)/135 -> 0 | CQ39: =0/157.5 -> 0 | CR39: =0/157.5 -> 0 | CS39: =0/157.5 -> 0 | CT39: =0/157.5 -> 0 | CU39: =0/157.5 -> 0 | CV39: =0/172.5 -> 0 | CW39: =0/172.5 -> 0 | CX39: =0/157.5 -> 0 | CY39: =0/157.5 -> 0 | CZ39: =0/157.5 -> 0 | DA39: =0/157.5 -> 0 | DB39: =0/157.5 -> 0 | DC39: =0/172.5 -> 0 | DD39: =0/172.5 -> 0 | DE39: =0/127.5 -> 0 | DF39: =0/127.5 -> 0 | DG39: =0/127.5 -> 0 | DH39: =0/127.5 -> 0 | DI39: =0/127.5 -> 0 | DJ39: =0/172.5 -> 0 | DK39: =0/172.5 -> 0 | DL39: =0/142.5 -> 0 | DM39: =0/142.5 -> 0 | DN39: =0/142.5 -> 0 | DO39: =0/142.5 -> 0 | DP39: =0/142.5 -> 0 | DQ39: =0/172.5 -> 0 | DR39: =0/172.5 -> 0 | DS39: =0/172.5 -> 0
N40: 実績 | O40: =0/127.5 -> 0 | P40: =0/127.5 -> 0 | Q40: =0/127.5 -> 0 | R40: =0/127.5 -> 0 | S40: =0/127.5 -> 0 | T40: =0/127.5 -> 0 | U40: =0/127.5 -> 0 | V40: =0/127.5 -> 0 | ... X40: =0/127.5 -> 0 | Y40: =0/142.5 -> 0 | Z40: =0/142.5 -> 0 | AA40: =0/142.5 -> 0 | AB40: =0/142.5 -> 0 | AC40: =0/142.5 -> 0 | AD40: =0/142.5 -> 0 | AE40: =0/165 -> 0 | AG40: =0/165 -> 0 | AH40: =0/165 -> 0 | AI40: =(0)/157.5 -> 0 | AJ40: =(8.5+5)/157.5 -> 0.085714286 | AK40: =(0)/157.5 -> 0 | AL40: =(0)/157.5 -> 0 | AM40: =(0)/157.5 -> 0 | AN40: =(0)/157.5 -> 0 | AO40: =(5)/157.5 -> 0.031746032 | AP40: =(0)/157.5 -> 0 | AQ40: =(0)/157.5 -> 0 | AR40: =(25.5+13.5)/157.5 -> 0.24761905 | AS40: =(0)/165 -> 0 | AT40: =(0)/165 -> 0 | AU40: =(0)/165 -> 0 | AV40: =(0)/165 -> 0 | AW40: =(0)/165 -> 0 | AX40: =(0)/165 -> 0 | AY40: =(0)/165 -> 0 | AZ40: =(0)/165 -> 0 | ... BB40: =(0)/165 -> 0 | BC40: =(0)/157.5 -> 0 | BD40: =(0)/157.5 -> 0 | BE40: =(0)/157.5 -> 0 | BF40: =(0)/157.5 -> 0 | BG40: =(0)/157.5 -> 0 | BH40: =(0)/157.5 -> 0 | BI40: =(0)/157.5 -> 0 | BJ40: =(0)/157.5 -> 0 | ... BL40: =(0)/157.5 -> 0 | BM40: =(0)/165 -> 0 | BN40: =(0)/165 -> 0 | BO40: =(0)/165 -> 0 | BP40: =(0)/165 -> 0 | BQ40: =(0)/165 -> 0 | BR40: =(0)/165 -> 0 | BS40: =(0)/165 -> 0 | BT40: =(0)/165 -> 0 | ... BV40: =(0)/165 -> 0 | BW40: =(0)/150 -> 0 | BX40: =(0)/150 -> 0 | BY40: =(0)/150 -> 0 | BZ40: =(0)/150 -> 0 | CA40: =(0)/150 -> 0 | CB40: =(0)/150 -> 0 | CC40: =(0)/150 -> 0 | CD40: =(0)/150 -> 0 | ... CF40: =(0)/150 -> 0 | CG40: =(0)/135 -> 0 | CH40: =(0)/135 -> 0 | CI40: =(0)/135 -> 0 | CJ40: =(0)/135 -> 0 | CK40: =(0)/135 -> 0 | CL40: =(0)/135 -> 0 | CM40: =(0)/135 -> 0 | CN40: =(0)/135 -> 0 | ... CP40: =(0)/135 -> 0 | CQ40: =0/157.5 -> 0 | CR40: =0/157.5 -> 0 | CS40: =0/157.5 -> 0 | CT40: =0/157.5 -> 0 | CU40: =0/157.5 -> 0 | CV40: =0/172.5 -> 0 | CW40: =0/172.5 -> 0 | CX40: =0/157.5 -> 0 | CY40: =0/157.5 -> 0 | CZ40: =0/157.5 -> 0 | DA40: =0/157.5 -> 0 | DB40: =0/157.5 -> 0 | DC40: =0/172.5 -> 0 | DD40: =0/172.5 -> 0 | DE40: =0/127.5 -> 0 | DF40: =0/127.5 -> 0 | DG40: =0/127.5 -> 0 | DH40: =0/127.5 -> 0 | DI40: =0/127.5 -> 0 | DJ40: =0/172.5 -> 0 | DK40: =0/172.5 -> 0 | DL40: =0/142.5 -> 0 | DM40: =0/142.5 -> 0 | DN40: =0/142.5 -> 0 | DO40: =0/142.5 -> 0 | DP40: =0/142.5 -> 0 | DQ40: =0/172.5 -> 0 | DR40: =0/172.5 -> 0 | DS40: =0/172.5 -> 0
A41: 18 | B41: 完了 | C41: その他 | D41: 寺澤 | E41: SFA7 | G41: 【SFA】(000050)画面文言変更対応 | H41: =SUM(CG41:CP41) -> 0 | I41: =SUM(CG42:CP42) -> 0 | N41: 計画 | O41: =0/127.5 -> 0 | P41: =0/127.5 -> 0 | Q41: =0/127.5 -> 0 | R41: =0/127.5 -> 0 | S41: =0/127.5 -> 0 | T41: =0/127.5 -> 0 | U41: =0/127.5 -> 0 | V41: =0/127.5 -> 0 | ... X41: =0/127.5 -> 0 | Y41: =0/142.5 -> 0 | Z41: =0/142.5 -> 0 | AA41: =0/142.5 -> 0 | AB41: =0/142.5 -> 0 | AC41: =0/142.5 -> 0 | AD41: =0/142.5 -> 0 | AE41: =0/165 -> 0 | AG41: =0/165 -> 0 | AH41: =0/165 -> 0 | AI41: =(0)/157.5 -> 0 | AJ41: =(42.5)/157.5 -> 0.26984127 | AK41: =(0)/157.5 -> 0 | AL41: =(0)/157.5 -> 0 | AM41: =(0)/157.5 -> 0 | AN41: =(42.5)/157.5 -> 0.26984127 | AO41: =(22.5)/157.5 -> 0.14285714 | AP41: =(42.5+20)/157.5 -> 0.3968254 | AQ41: =(0)/157.5 -> 0 | AR41: =(0)/157.5 -> 0 | AS41: =(0)/165 -> 0 | AT41: =(14)/165 -> 0.084848485 | AU41: =(0)/165 -> 0 | AV41: =(0)/165 -> 0 | AW41: =(0)/165 -> 0 | AX41: =(39)/165 -> 0.23636364 | AY41: =(14)/165 -> 0.084848485 | AZ41: =(29)/165 -> 0.17575758 | BA41: =(0)/165 -> 0 | BB41: =(0)/165 -> 0 | BC41: =(0)/157.5 -> 0 | BD41: =(0)/157.5 -> 0 | BE41: =(0)/157.5 -> 0 | BF41: =(0)/157.5 -> 0 | BG41: =(0)/157.5 -> 0 | BH41: =(0)/157.5 -> 0 | BI41: =(0)/157.5 -> 0 | BJ41: =(0)/157.5 -> 0 | ... BL41: =(0)/157.5 -> 0 | BM41: =(0)/165 -> 0 | BN41: =(0)/165 -> 0 | BO41: =(0)/165 -> 0 | BP41: =(0)/165 -> 0 | BQ41: =(0)/165 -> 0 | BR41: =(0)/165 -> 0 | BS41: =(0)/165 -> 0 | BT41: =(0)/165 -> 0 | ... BV41: =(0)/165 -> 0 | BW41: =(0)/150 -> 0 | BX41: =(0)/150 -> 0 | BY41: =(0)/150 -> 0 | BZ41: =(0)/150 -> 0 | CA41: =(0)/150 -> 0 | CB41: =(0)/150 -> 0 | CC41: =(0)/150 -> 0 | CD41: =(0)/150 -> 0 | ... CF41: =(0)/150 -> 0 | CG41: =(0)/135 -> 0 | CH41: =(0)/135 -> 0 | CI41: =(0)/135 -> 0 | CJ41: =(0)/135 -> 0 | CK41: =(0)/135 -> 0 | CL41: =(0)/135 -> 0 | CM41: =(0)/135 -> 0 | CN41: =(0)/135 -> 0 | ... CP41: =(0)/135 -> 0 | CQ41: =0/157.5 -> 0 | CR41: =0/157.5 -> 0 | CS41: =0/157.5 -> 0 | CT41: =0/157.5 -> 0 | CU41: =0/157.5 -> 0 | CV41: =0/172.5 -> 0 | CW41: =0/172.5 -> 0 | CX41: =0/157.5 -> 0 | CY41: =0/157.5 -> 0 | CZ41: =0/157.5 -> 0 | DA41: =0/157.5 -> 0 | DB41: =0/157.5 -> 0 | DC41: =0/172.5 -> 0 | DD41: =0/172.5 -> 0 | DE41: =0/127.5 -> 0 | DF41: =0/127.5 -> 0 | DG41: =0/127.5 -> 0 | DH41: =0/127.5 -> 0 | DI41: =0/127.5 -> 0 | DJ41: =0/172.5 -> 0 | DK41: =0/172.5 -> 0 | DL41: =0/142.5 -> 0 | DM41: =0/142.5 -> 0 | DN41: =0/142.5 -> 0 | DO41: =0/142.5 -> 0 | DP41: =0/142.5 -> 0 | DQ41: =0/172.5 -> 0 | DR41: =0/172.5 -> 0 | DS41: =0/172.5 -> 0
N42: 実績 | O42: =0/127.5 -> 0 | P42: =0/127.5 -> 0 | Q42: =0/127.5 -> 0 | R42: =0/127.5 -> 0 | S42: =0/127.5 -> 0 | T42: =0/127.5 -> 0 | U42: =0/127.5 -> 0 | V42: =0/127.5 -> 0 | ... X42: =0/127.5 -> 0 | Y42: =0/142.5 -> 0 | Z42: =0/142.5 -> 0 | AA42: =0/142.5 -> 0 | AB42: =0/142.5 -> 0 | AC42: =0/142.5 -> 0 | AD42: =0/142.5 -> 0 | AE42: =0/165 -> 0 | AG42: =0/165 -> 0 | AH42: =0/165 -> 0 | AI42: =(0)/157.5 -> 0 | AJ42: =(6.5+11.5+7.5)/157.5 -> 0.16190476 | AK42: =(0)/157.5 -> 0 | AL42: =(0)/157.5 -> 0 | AM42: =(0)/157.5 -> 0 | AN42: =(18+29.5+16.5)/157.5 -> 0.40634921 | AO42: =(0+13+9)/157.5 -> 0.13968254 | AP42: =(14+30.5+12)/157.5 -> 0.35873016 | AQ42: =(0)/157.5 -> 0 | AR42: =(0)/157.5 -> 0 | AS42: =(0)/165 -> 0 | AT42: =(4+7+2+1+1)/165 -> 0.090909091 | AU42: =(0)/165 -> 0 | AV42: =(0)/165 -> 0 | AW42: =(0)/165 -> 0 | AX42: =(12+23.5+2+2+4)/165 -> 0.26363636 | AY42: =(8)/165 -> 0.048484848 | AZ42: =(12+16.5)/165 -> 0.17272727 | BA42: =(0)/165 -> 0 | BB42: =(0)/165 -> 0 | BC42: =(0)/157.5 -> 0 | BD42: =(0)/157.5 -> 0 | BE42: =(0)/157.5 -> 0 | BF42: =(0)/157.5 -> 0 | BG42: =(0)/157.5 -> 0 | BH42: =(0)/157.5 -> 0 | BI42: =(0)/157.5 -> 0 | BJ42: =(0)/157.5 -> 0 | ... BL42: =(0)/157.5 -> 0 | BM42: =(0)/165 -> 0 | BN42: =(0)/165 -> 0 | BO42: =(0)/165 -> 0 | BP42: =(0)/165 -> 0 | BQ42: =(0)/165 -> 0 | BR42: =(0)/165 -> 0 | BS42: =(0)/165 -> 0 | BT42: =(0)/165 -> 0 | ... BV42: =(0)/165 -> 0 | BW42: =(0)/150 -> 0 | BX42: =(0)/150 -> 0 | BY42: =(0)/150 -> 0 | BZ42: =(0)/150 -> 0 | CA42: =(0)/150 -> 0 | CB42: =(0)/150 -> 0 | CC42: =(0)/150 -> 0 | CD42: =(0)/150 -> 0 | ... CF42: =(0)/150 -> 0 | CG42: =(0)/135 -> 0 | CH42: =(0)/135 -> 0 | CI42: =(0)/135 -> 0 | CJ42: =(0)/135 -> 0 | CK42: =(0)/135 -> 0 | CL42: =(0)/135 -> 0 | CM42: =(0)/135 -> 0 | CN42: =(0)/135 -> 0 | ... CP42: =(0)/135 -> 0 | CQ42: =0/157.5 -> 0 | CR42: =0/157.5 -> 0 | CS42: =0/157.5 -> 0 | CT42: =0/157.5 -> 0 | CU42: =0/157.5 -> 0 | CV42: =0/172.5 -> 0 | CW42: =0/172.5 -> 0 | CX42: =0/157.5 -> 0 | CY42: =0/157.5 -> 0 | CZ42: =0/157.5 -> 0 | DA42: =0/157.5 -> 0 | DB42: =0/157.5 -> 0 | DC42: =0/172.5 -> 0 | DD42: =0/172.5 -> 0 | DE42: =0/127.5 -> 0 | DF42: =0/127.5 -> 0 | DG42: =0/127.5 -> 0 | DH42: =0/127.5 -> 0 | DI42: =0/127.5 -> 0 | DJ42: =0/172.5 -> 0 | DK42: =0/172.5 -> 0 | DL42: =0/142.5 -> 0 | DM42: =0/142.5 -> 0 | DN42: =0/142.5 -> 0 | DO42: =0/142.5 -> 0 | DP42: =0/142.5 -> 0 | DQ42: =0/172.5 -> 0 | DR42: =0/172.5 -> 0 | DS42: =0/172.5 -> 0
A43: 19 | B43: 完了 | C43: その他 | D43: 髙木 | E43: BT3 | G43: w3jy210foの出力メッセージの改善 | H43: =SUM(CG43:CP43) -> 0 | I43: =SUM(CG44:CP44) -> 0 | N43: 計画 | O43: =0/127.5 -> 0 | P43: =0/127.5 -> 0 | Q43: =0/127.5 -> 0 | R43: =0/127.5 -> 0 | S43: =0/127.5 -> 0 | T43: =0/127.5 -> 0 | U43: =0/127.5 -> 0 | V43: =0/127.5 -> 0 | ... X43: =0/127.5 -> 0 | Y43: =0/142.5 -> 0 | Z43: =0/142.5 -> 0 | AA43: =0/142.5 -> 0 | AB43: =0/142.5 -> 0 | AC43: =0/142.5 -> 0 | AD43: =0/142.5 -> 0 | AE43: =0/165 -> 0 | AG43: =0/165 -> 0 | AH43: =0/165 -> 0 | AI43: =0/165 -> 0 | AJ43: =0/165 -> 0 | AK43: =0/165 -> 0 | AL43: =0/165 -> 0 | AM43: =0/165 -> 0 | AN43: =0/165 -> 0 | ... AR43: =0/165 -> 0 | AS43: =(0)/165 -> 0 | AT43: =(0)/165 -> 0 | AU43: =(0)/165 -> 0 | AV43: =(37.5)/165 -> 0.22727273 | AW43: =(37.5)/165 -> 0.22727273 | AX43: =(0)/165 -> 0 | AY43: =(0)/165 -> 0 | AZ43: =(0)/165 -> 0 | BA43: =(0)/165 -> 0 | BB43: =(0)/165 -> 0 | BC43: =(8)/157.5 -> 0.050793651 | BD43: =(0)/157.5 -> 0 | BE43: =(0)/157.5 -> 0 | BF43: =(0)/157.5 -> 0 | BG43: =(10)/157.5 -> 0.063492063 | BH43: =(0)/157.5 -> 0 | BI43: =(0)/157.5 -> 0 | BJ43: =(0)/157.5 -> 0 | BK43: =(0)/157.5 -> 0 | BL43: =(0)/157.5 -> 0 | BM43: =(0)/165 -> 0 | BN43: =(0)/165 -> 0 | BO43: =(0)/165 -> 0 | BP43: =(0)/165 -> 0 | BQ43: =(0)/165 -> 0 | BR43: =(0)/165 -> 0 | BS43: =(0)/165 -> 0 | BT43: =(0)/165 -> 0 | ... BV43: =(0)/165 -> 0 | BW43: =(0)/150 -> 0 | BX43: =(0)/150 -> 0 | BY43: =(0)/150 -> 0 | BZ43: =(0)/150 -> 0 | CA43: =(0)/150 -> 0 | CB43: =(0)/150 -> 0 | CC43: =(0)/150 -> 0 | CD43: =(0)/150 -> 0 | ... CF43: =(0)/150 -> 0 | CG43: =(0)/135 -> 0 | CH43: =(0)/135 -> 0 | CI43: =(0)/135 -> 0 | CJ43: =(0)/135 -> 0 | CK43: =(0)/135 -> 0 | CL43: =(0)/135 -> 0 | CM43: =(0)/135 -> 0 | CN43: =(0)/135 -> 0 | ... CP43: =(0)/135 -> 0 | CQ43: =0/157.5 -> 0 | CR43: =0/157.5 -> 0 | CS43: =0/157.5 -> 0 | CT43: =0/157.5 -> 0 | CU43: =0/157.5 -> 0 | CV43: =0/172.5 -> 0 | CW43: =0/172.5 -> 0 | CX43: =0/157.5 -> 0 | CY43: =0/157.5 -> 0 | CZ43: =0/157.5 -> 0 | DA43: =0/157.5 -> 0 | DB43: =0/157.5 -> 0 | DC43: =0/172.5 -> 0 | DD43: =0/172.5 -> 0 | DE43: =0/127.5 -> 0 | DF43: =0/127.5 -> 0 | DG43: =0/127.5 -> 0 | DH43: =0/127.5 -> 0 | DI43: =0/127.5 -> 0 | DJ43: =0/172.5 -> 0 | DK43: =0/172.5 -> 0 | DL43: =0/142.5 -> 0 | DM43: =0/142.5 -> 0 | DN43: =0/142.5 -> 0 | DO43: =0/142.5 -> 0 | DP43: =0/142.5 -> 0 | DQ43: =0/172.5 -> 0 | DR43: =0/172.5 -> 0 | DS43: =0/172.5 -> 0
N44: 実績 | O44: =0/127.5 -> 0 | P44: =0/127.5 -> 0 | Q44: =0/127.5 -> 0 | R44: =0/127.5 -> 0 | S44: =0/127.5 -> 0 | T44: =0/127.5 -> 0 | U44: =0/127.5 -> 0 | V44: =0/127.5 -> 0 | ... X44: =0/127.5 -> 0 | Y44: =0/142.5 -> 0 | Z44: =0/142.5 -> 0 | AA44: =0/142.5 -> 0 | AB44: =0/142.5 -> 0 | AC44: =0/142.5 -> 0 | AD44: =0/142.5 -> 0 | AE44: =0/165 -> 0 | AG44: =0/165 -> 0 | AH44: =0/165 -> 0 | AI44: =0/165 -> 0 | AJ44: =0/165 -> 0 | AK44: =0/165 -> 0 | AL44: =0/165 -> 0 | AM44: =0/165 -> 0 | AN44: =0/165 -> 0 | ... AR44: =0/165 -> 0 | AS44: =(0)/165 -> 0 | AT44: =(0)/165 -> 0 | AU44: =(0)/165 -> 0 | AV44: =(7+24)/165 -> 0.18787879 | AW44: =(12+25.5+1.5)/165 -> 0.23636364 | AX44: =(0)/165 -> 0 | AY44: =(0)/165 -> 0 | AZ44: =(0)/165 -> 0 | BA44: =(0)/165 -> 0 | BB44: =(0)/165 -> 0 | BC44: =(0+2)/157.5 -> 0.012698413 | BD44: =(0)/157.5 -> 0 | BE44: =(0)/157.5 -> 0 | BF44: =(0)/157.5 -> 0 | BG44: =(10)/157.5 -> 0.063492063 | BH44: =(0)/157.5 -> 0 | BI44: =(0)/157.5 -> 0 | BJ44: =(0)/157.5 -> 0 | BK44: =(0)/157.5 -> 0 | BL44: =(0)/157.5 -> 0 | BM44: =(0)/165 -> 0 | BN44: =(0)/165 -> 0 | BO44: =(0)/165 -> 0 | BP44: =(0)/165 -> 0 | BQ44: =(0)/165 -> 0 | BR44: =(0)/165 -> 0 | BS44: =(0)/165 -> 0 | BT44: =(0)/165 -> 0 | ... BV44: =(0)/165 -> 0 | BW44: =(0)/150 -> 0 | BX44: =(0)/150 -> 0 | BY44: =(0)/150 -> 0 | BZ44: =(0)/150 -> 0 | CA44: =(0)/150 -> 0 | CB44: =(0)/150 -> 0 | CC44: =(0)/150 -> 0 | CD44: =(0)/150 -> 0 | ... CF44: =(0)/150 -> 0 | CG44: =(0)/135 -> 0 | CH44: =(0)/135 -> 0 | CI44: =(0)/135 -> 0 | CJ44: =(0)/135 -> 0 | CK44: =(0)/135 -> 0 | CL44: =(0)/135 -> 0 | CM44: =(0)/135 -> 0 | CN44: =(0)/135 -> 0 | ... CP44: =(0)/135 -> 0 | CQ44: =0/157.5 -> 0 | CR44: =0/157.5 -> 0 | CS44: =0/157.5 -> 0 | CT44: =0/157.5 -> 0 | CU44: =0/157.5 -> 0 | CV44: =0/172.5 -> 0 | CW44: =0/172.5 -> 0 | CX44: =0/157.5 -> 0 | CY44: =0/157.5 -> 0 | CZ44: =0/157.5 -> 0 | DA44: =0/157.5 -> 0 | DB44: =0/157.5 -> 0 | DC44: =0/172.5 -> 0 | DD44: =0/172.5 -> 0 | DE44: =0/127.5 -> 0 | DF44: =0/127.5 -> 0 | DG44: =0/127.5 -> 0 | DH44: =0/127.5 -> 0 | DI44: =0/127.5 -> 0 | DJ44: =0/172.5 -> 0 | DK44: =0/172.5 -> 0 | DL44: =0/142.5 -> 0 | DM44: =0/142.5 -> 0 | DN44: =0/142.5 -> 0 | DO44: =0/142.5 -> 0 | DP44: =0/142.5 -> 0 | DQ44: =0/172.5 -> 0 | DR44: =0/172.5 -> 0 | DS44: =0/172.5 -> 0
A45: 20 | B45: 完了 | C45: その他 | D45: 山田 | E45: AH29 | G45: 【開発依頼】ICC本番モジュール取得ツール改善 | H45: =SUM(CG45:CP45) -> 0 | I45: =SUM(CG46:CP46) -> 0 | N45: 計画 | O45: =0/127.5 -> 0 | P45: =0/127.5 -> 0 | Q45: =0/127.5 -> 0 | R45: =0/127.5 -> 0 | S45: =0/127.5 -> 0 | T45: =0/127.5 -> 0 | U45: =0/127.5 -> 0 | V45: =0/127.5 -> 0 | ... X45: =0/127.5 -> 0 | Y45: =0/142.5 -> 0 | Z45: =0/142.5 -> 0 | AA45: =0/142.5 -> 0 | AB45: =0/142.5 -> 0 | AC45: =0/142.5 -> 0 | AD45: =0/142.5 -> 0 | AE45: =0/165 -> 0 | AG45: =0/165 -> 0 | AH45: =0/165 -> 0 | AI45: =0/165 -> 0 | AJ45: =0/165 -> 0 | AK45: =0/165 -> 0 | AL45: =0/165 -> 0 | AM45: =0/165 -> 0 | AN45: =0/165 -> 0 | ... AR45: =0/165 -> 0 | AS45: =(0)/165 -> 0 | AT45: =(0)/165 -> 0 | AU45: =(32.5)/165 -> 0.1969697 | AV45: =(0)/165 -> 0 | AW45: =(0)/165 -> 0 | AX45: =(0)/165 -> 0 | AY45: =(0)/165 -> 0 | AZ45: =(32.5)/165 -> 0.1969697 | BA45: =(0)/165 -> 0 | BB45: =(0)/165 -> 0 | BC45: =(0)/157.5 -> 0 | BD45: =(0)/157.5 -> 0 | BE45: =(3)/157.5 -> 0.019047619 | BF45: =(0)/157.5 -> 0 | BG45: =(0)/157.5 -> 0 | BH45: =(0)/157.5 -> 0 | BI45: =(0)/157.5 -> 0 | BJ45: =(0)/157.5 -> 0 | BK45: =(0)/157.5 -> 0 | BL45: =(0)/157.5 -> 0 | BM45: =(0)/165 -> 0 | BN45: =(0)/165 -> 0 | BO45: =(0)/165 -> 0 | BP45: =(0)/165 -> 0 | BQ45: =(0)/165 -> 0 | BR45: =(0)/165 -> 0 | BS45: =(0)/165 -> 0 | BT45: =(0)/165 -> 0 | ... BV45: =(0)/165 -> 0 | BW45: =(0)/150 -> 0 | BX45: =(0)/150 -> 0 | BY45: =(0)/150 -> 0 | BZ45: =(0)/150 -> 0 | CA45: =(0)/150 -> 0 | CB45: =(0)/150 -> 0 | CC45: =(0)/150 -> 0 | CD45: =(0)/150 -> 0 | ... CF45: =(0)/150 -> 0 | CG45: =(0)/135 -> 0 | CH45: =(0)/135 -> 0 | CI45: =(0)/135 -> 0 | CJ45: =(0)/135 -> 0 | CK45: =(0)/135 -> 0 | CL45: =(0)/135 -> 0 | CM45: =(0)/135 -> 0 | CN45: =(0)/135 -> 0 | ... CP45: =(0)/135 -> 0 | CQ45: =0/157.5 -> 0 | CR45: =0/157.5 -> 0 | CS45: =0/157.5 -> 0 | CT45: =0/157.5 -> 0 | CU45: =0/157.5 -> 0 | CV45: =0/172.5 -> 0 | CW45: =0/172.5 -> 0 | CX45: =0/157.5 -> 0 | CY45: =0/157.5 -> 0 | CZ45: =0/157.5 -> 0 | DA45: =0/157.5 -> 0 | DB45: =0/157.5 -> 0 | DC45: =0/172.5 -> 0 | DD45: =0/172.5 -> 0 | DE45: =0/127.5 -> 0 | DF45: =0/127.5 -> 0 | DG45: =0/127.5 -> 0 | DH45: =0/127.5 -> 0 | DI45: =0/127.5 -> 0 | DJ45: =0/172.5 -> 0 | DK45: =0/172.5 -> 0 | DL45: =0/142.5 -> 0 | DM45: =0/142.5 -> 0 | DN45: =0/142.5 -> 0 | DO45: =0/142.5 -> 0 | DP45: =0/142.5 -> 0 | DQ45: =0/172.5 -> 0 | DR45: =0/172.5 -> 0 | DS45: =0/172.5 -> 0
N46: 実績 | O46: =0/127.5 -> 0 | P46: =0/127.5 -> 0 | Q46: =0/127.5 -> 0 | R46: =0/127.5 -> 0 | S46: =0/127.5 -> 0 | T46: =0/127.5 -> 0 | U46: =0/127.5 -> 0 | V46: =0/127.5 -> 0 | ... X46: =0/127.5 -> 0 | Y46: =0/142.5 -> 0 | Z46: =0/142.5 -> 0 | AA46: =0/142.5 -> 0 | AB46: =0/142.5 -> 0 | AC46: =0/142.5 -> 0 | AD46: =0/142.5 -> 0 | AE46: =0/165 -> 0 | AG46: =0/165 -> 0 | AH46: =0/165 -> 0 | AI46: =0/165 -> 0 | AJ46: =0/165 -> 0 | AK46: =0/165 -> 0 | AL46: =0/165 -> 0 | AM46: =0/165 -> 0 | AN46: =0/165 -> 0 | ... AR46: =0/165 -> 0 | AS46: =(0)/165 -> 0 | AT46: =(0)/165 -> 0 | AU46: =(2.5+5.5+6+3.5)/165 -> 0.10606061 | AV46: =(0)/165 -> 0 | AW46: =(0)/165 -> 0 | AX46: =(0)/165 -> 0 | AY46: =(0)/165 -> 0 | AZ46: =(7+20.5+10+4)/165 -> 0.25151515 | BA46: =(0)/165 -> 0 | BB46: =(0)/165 -> 0 | BC46: =(0)/157.5 -> 0 | BD46: =(0)/157.5 -> 0 | BE46: =(2.5)/157.5 -> 0.015873016 | BF46: =(0)/157.5 -> 0 | BG46: =(0)/157.5 -> 0 | BH46: =(0)/157.5 -> 0 | BI46: =(0)/157.5 -> 0 | BJ46: =(0)/157.5 -> 0 | BK46: =(0)/157.5 -> 0 | BL46: =(0)/157.5 -> 0 | BM46: =(0)/165 -> 0 | BN46: =(0)/165 -> 0 | BO46: =(0)/165 -> 0 | BP46: =(0)/165 -> 0 | BQ46: =(0)/165 -> 0 | BR46: =(0)/165 -> 0 | BS46: =(0)/165 -> 0 | BT46: =(0)/165 -> 0 | ... BV46: =(0)/165 -> 0 | BW46: =(0)/150 -> 0 | BX46: =(0)/150 -> 0 | BY46: =(0)/150 -> 0 | BZ46: =(0)/150 -> 0 | CA46: =(0)/150 -> 0 | CB46: =(0)/150 -> 0 | CC46: =(0)/150 -> 0 | CD46: =(0)/150 -> 0 | ... CF46: =(0)/150 -> 0 | CG46: =(0)/135 -> 0 | CH46: =(0)/135 -> 0 | CI46: =(0)/135 -> 0 | CJ46: =(0)/135 -> 0 | CK46: =(0)/135 -> 0 | CL46: =(0)/135 -> 0 | CM46: =(0)/135 -> 0 | CN46: =(0)/135 -> 0 | ... CP46: =(0)/135 -> 0 | CQ46: =0/157.5 -> 0 | CR46: =0/157.5 -> 0 | CS46: =0/157.5 -> 0 | CT46: =0/157.5 -> 0 | CU46: =0/157.5 -> 0 | CV46: =0/172.5 -> 0 | CW46: =0/172.5 -> 0 | CX46: =0/157.5 -> 0 | CY46: =0/157.5 -> 0 | CZ46: =0/157.5 -> 0 | DA46: =0/157.5 -> 0 | DB46: =0/157.5 -> 0 | DC46: =0/172.5 -> 0 | DD46: =0/172.5 -> 0 | DE46: =0/127.5 -> 0 | DF46: =0/127.5 -> 0 | DG46: =0/127.5 -> 0 | DH46: =0/127.5 -> 0 | DI46: =0/127.5 -> 0 | DJ46: =0/172.5 -> 0 | DK46: =0/172.5 -> 0 | DL46: =0/142.5 -> 0 | DM46: =0/142.5 -> 0 | DN46: =0/142.5 -> 0 | DO46: =0/142.5 -> 0 | DP46: =0/142.5 -> 0 | DQ46: =0/172.5 -> 0 | DR46: =0/172.5 -> 0 | DS46: =0/172.5 -> 0
A47: 21 | B47: 完了 | C47: その他 | D47: 山本 | E47: PR7 | G47: (44)管理者株式銘柄条件設定画面の改善 | H47: =SUM(CG47:CP47) -> 0 | I47: =SUM(CG48:CP48) -> 0 | N47: 計画 | O47: =0/127.5 -> 0 | P47: =0/127.5 -> 0 | Q47: =0/127.5 -> 0 | R47: =0/127.5 -> 0 | S47: =0/127.5 -> 0 | T47: =0/127.5 -> 0 | U47: =0/127.5 -> 0 | V47: =0/127.5 -> 0 | ... X47: =0/127.5 -> 0 | Y47: =0/142.5 -> 0 | Z47: =0/142.5 -> 0 | AA47: =0/142.5 -> 0 | AB47: =0/142.5 -> 0 | AC47: =0/142.5 -> 0 | AD47: =0/142.5 -> 0 | AE47: =0/165 -> 0 | AG47: =0/165 -> 0 | AH47: =0/165 -> 0 | AI47: =0/165 -> 0 | AJ47: =0/165 -> 0 | AK47: =0/165 -> 0 | AL47: =0/165 -> 0 | AM47: =0/165 -> 0 | AN47: =0/165 -> 0 | ... AR47: =0/165 -> 0 | AS47: =(0)/165 -> 0 | AT47: =(0)/165 -> 0 | AU47: =(16)/165 -> 0.096969697 | AV47: =(0)/165 -> 0 | AW47: =(0)/165 -> 0 | AX47: =(11)/165 -> 0.066666667 | AY47: =(11)/165 -> 0.066666667 | AZ47: =(6)/165 -> 0.036363636 | BA47: =(0)/165 -> 0 | BB47: =(0)/165 -> 0 | BC47: =(3)/157.5 -> 0.019047619 | BD47: =(0)/157.5 -> 0 | BE47: =(40)/157.5 -> 0.25396825 | BF47: =(0)/157.5 -> 0 | BG47: =(0)/157.5 -> 0 | BH47: =(0)/157.5 -> 0 | BI47: =(0)/157.5 -> 0 | BJ47: =(40)/157.5 -> 0.25396825 | BK47: =(17)/157.5 -> 0.10793651 | BL47: =(0)/157.5 -> 0 | BM47: =(0)/165 -> 0 | BN47: =(0)/165 -> 0 | BO47: =(0)/165 -> 0 | BP47: =(0)/165 -> 0 | BQ47: =(0)/165 -> 0 | BR47: =(0)/165 -> 0 | BS47: =(0)/165 -> 0 | BT47: =(0)/165 -> 0 | ... BV47: =(0)/165 -> 0 | BW47: =(0)/150 -> 0 | BX47: =(0)/150 -> 0 | BY47: =(0)/150 -> 0 | BZ47: =(0)/150 -> 0 | CA47: =(0)/150 -> 0 | CB47: =(0)/150 -> 0 | CC47: =(0)/150 -> 0 | CD47: =(0)/150 -> 0 | ... CF47: =(0)/150 -> 0 | CG47: =(0)/135 -> 0 | CH47: =(0)/135 -> 0 | CI47: =(0)/135 -> 0 | CJ47: =(0)/135 -> 0 | CK47: =(0)/135 -> 0 | CL47: =(0)/135 -> 0 | CM47: =(0)/135 -> 0 | CN47: =(0)/135 -> 0 | ... CP47: =(0)/135 -> 0 | CQ47: =0/157.5 -> 0 | CR47: =0/157.5 -> 0 | CS47: =0/157.5 -> 0 | CT47: =0/157.5 -> 0 | CU47: =0/157.5 -> 0 | CV47: =0/172.5 -> 0 | CW47: =0/172.5 -> 0 | CX47: =0/157.5 -> 0 | CY47: =0/157.5 -> 0 | CZ47: =0/157.5 -> 0 | DA47: =0/157.5 -> 0 | DB47: =0/157.5 -> 0 | DC47: =0/172.5 -> 0 | DD47: =0/172.5 -> 0 | DE47: =0/127.5 -> 0 | DF47: =0/127.5 -> 0 | DG47: =0/127.5 -> 0 | DH47: =0/127.5 -> 0 | DI47: =0/127.5 -> 0 | DJ47: =0/172.5 -> 0 | DK47: =0/172.5 -> 0 | DL47: =0/142.5 -> 0 | DM47: =0/142.5 -> 0 | DN47: =0/142.5 -> 0 | DO47: =0/142.5 -> 0 | DP47: =0/142.5 -> 0 | DQ47: =0/172.5 -> 0 | DR47: =0/172.5 -> 0 | DS47: =0/172.5 -> 0
N48: 実績 | O48: =0/127.5 -> 0 | P48: =0/127.5 -> 0 | Q48: =0/127.5 -> 0 | R48: =0/127.5 -> 0 | S48: =0/127.5 -> 0 | T48: =0/127.5 -> 0 | U48: =0/127.5 -> 0 | V48: =0/127.5 -> 0 | ... X48: =0/127.5 -> 0 | Y48: =0/142.5 -> 0 | Z48: =0/142.5 -> 0 | AA48: =0/142.5 -> 0 | AB48: =0/142.5 -> 0 | AC48: =0/142.5 -> 0 | AD48: =0/142.5 -> 0 | AE48: =0/165 -> 0 | AG48: =0/165 -> 0 | AH48: =0/165 -> 0 | AI48: =0/165 -> 0 | AJ48: =0/165 -> 0 | AK48: =0/165 -> 0 | AL48: =0/165 -> 0 | AM48: =0/165 -> 0 | AN48: =0/165 -> 0 | ... AR48: =0/165 -> 0 | AS48: =(0)/165 -> 0 | AT48: =(0)/165 -> 0 | AU48: =(9+6+4.5+1.5)/165 -> 0.12727273 | AV48: =(0)/165 -> 0 | AW48: =(0)/165 -> 0 | AX48: =(6+3)/165 -> 0.054545455 | AY48: =(6+2)/165 -> 0.048484848 | AZ48: =(0+5.5)/165 -> 0.033333333 | BA48: =(0)/165 -> 0 | BB48: =(0)/165 -> 0 | BC48: =(1)/157.5 -> 0.0063492063 | BD48: =(0)/157.5 -> 0 | BE48: =(9.5+10.5+7+3+1)/157.5 -> 0.1968254 | BF48: =(0)/157.5 -> 0 | BG48: =(0)/157.5 -> 0 | BH48: =(0)/157.5 -> 0 | BI48: =(0)/157.5 -> 0 | BJ48: =(0+24.5+15+2+1)/157.5 -> 0.26984127 | BK48: =(14+3.5+6+4.5)/157.5 -> 0.17777778 | BL48: =(0)/157.5 -> 0 | BM48: =(0)/165 -> 0 | BN48: =(0)/165 -> 0 | BO48: =(0)/165 -> 0 | BP48: =(0)/165 -> 0 | BQ48: =(0)/165 -> 0 | BR48: =(0)/165 -> 0 | BS48: =(0)/165 -> 0 | BT48: =(0)/165 -> 0 | ... BV48: =(0)/165 -> 0 | BW48: =(0)/150 -> 0 | BX48: =(0)/150 -> 0 | BY48: =(0)/150 -> 0 | BZ48: =(0)/150 -> 0 | CA48: =(0)/150 -> 0 | CB48: =(0)/150 -> 0 | CC48: =(0)/150 -> 0 | CD48: =(0)/150 -> 0 | ... CF48: =(0)/150 -> 0 | CG48: =(0)/135 -> 0 | CH48: =(0)/135 -> 0 | CI48: =(0)/135 -> 0 | CJ48: =(0)/135 -> 0 | CK48: =(0)/135 -> 0 | CL48: =(0)/135 -> 0 | CM48: =(0)/135 -> 0 | CN48: =(0)/135 -> 0 | ... CP48: =(0)/135 -> 0 | CQ48: =0/157.5 -> 0 | CR48: =0/157.5 -> 0 | CS48: =0/157.5 -> 0 | CT48: =0/157.5 -> 0 | CU48: =0/157.5 -> 0 | CV48: =0/172.5 -> 0 | CW48: =0/172.5 -> 0 | CX48: =0/157.5 -> 0 | CY48: =0/157.5 -> 0 | CZ48: =0/157.5 -> 0 | DA48: =0/157.5 -> 0 | DB48: =0/157.5 -> 0 | DC48: =0/172.5 -> 0 | DD48: =0/172.5 -> 0 | DE48: =0/127.5 -> 0 | DF48: =0/127.5 -> 0 | DG48: =0/127.5 -> 0 | DH48: =0/127.5 -> 0 | DI48: =0/127.5 -> 0 | DJ48: =0/172.5 -> 0 | DK48: =0/172.5 -> 0 | DL48: =0/142.5 -> 0 | DM48: =0/142.5 -> 0 | DN48: =0/142.5 -> 0 | DO48: =0/142.5 -> 0 | DP48: =0/142.5 -> 0 | DQ48: =0/172.5 -> 0 | DR48: =0/172.5 -> 0 | DS48: =0/172.5 -> 0
A49: 22 | B49: 完了 | C49: その他 | D49: 安藤 | E49: WA3 | G49: (0D)(0X)定例会資料作成の自動化 | H49: =SUM(DE49:DK49) -> 0.10196078 | I49: =SUM(DE50:DK50) -> 0.070588235 | N49: 計画 | O49: =0/127.5 -> 0 | P49: =0/127.5 -> 0 | Q49: =0/127.5 -> 0 | R49: =0/127.5 -> 0 | S49: =0/127.5 -> 0 | T49: =0/127.5 -> 0 | U49: =0/127.5 -> 0 | V49: =0/127.5 -> 0 | ... X49: =0/127.5 -> 0 | Y49: =0/142.5 -> 0 | Z49: =0/142.5 -> 0 | AA49: =0/142.5 -> 0 | AB49: =0/142.5 -> 0 | AC49: =0/142.5 -> 0 | AD49: =0/142.5 -> 0 | AE49: =0/165 -> 0 | AG49: =0/165 -> 0 | AH49: =0/165 -> 0 | AI49: =0/165 -> 0 | AJ49: =0/165 -> 0 | AK49: =0/165 -> 0 | AL49: =0/165 -> 0 | AM49: =0/165 -> 0 | AN49: =0/165 -> 0 | ... AR49: =0/165 -> 0 | AS49: =(0)/165 -> 0 | AT49: =(35)/165 -> 0.21212121 | AU49: =(0)/165 -> 0 | AV49: =(0)/165 -> 0 | AW49: =(0)/165 -> 0 | AX49: =(0)/165 -> 0 | AY49: =(0)/165 -> 0 | AZ49: =(0)/165 -> 0 | BA49: =(35)/165 -> 0.21212121 | BB49: =(10)/165 -> 0.060606061 | BC49: =(4)/157.5 -> 0.025396825 | BD49: =(13)/157.5 -> 0.082539683 | BE49: =(0)/157.5 -> 0 | BF49: =(0)/157.5 -> 0 | BG49: =(0)/157.5 -> 0 | BH49: =(0)/157.5 -> 0 | BI49: =(0)/157.5 -> 0 | BJ49: =(0)/157.5 -> 0 | BK49: =(13)/157.5 -> 0.082539683 | BL49: =(0)/157.5 -> 0 | BM49: =(0)/165 -> 0 | BN49: =(0)/165 -> 0 | BO49: =(0)/165 -> 0 | BP49: =(0)/165 -> 0 | BQ49: =(0)/165 -> 0 | BR49: =(0)/165 -> 0 | BS49: =(0)/165 -> 0 | BT49: =(0)/165 -> 0 | ... BV49: =(0)/165 -> 0 | BW49: =(0)/150 -> 0 | BX49: =(0)/150 -> 0 | BY49: =(0)/150 -> 0 | BZ49: =(0)/150 -> 0 | CA49: =(0)/150 -> 0 | CB49: =(0)/150 -> 0 | CC49: =(0)/150 -> 0 | CD49: =(0)/150 -> 0 | ... CF49: =(0)/150 -> 0 | CG49: =(10)/135 -> 0.074074074 | CH49: =(25)/135 -> 0.18518519 | CI49: =(0)/135 -> 0 | CJ49: =(0)/135 -> 0 | CK49: =(0)/135 -> 0 | CL49: =(0)/135 -> 0 | CM49: =(0)/135 -> 0 | CN49: =(0)/135 -> 0 | CO49: =(25)/135 -> 0.18518519 | CP49: =(0)/135 -> 0 | CQ49: =(11)/150 -> 0.073333333 | CR49: =(20)/150 -> 0.13333333 | CS49: =(0)/150 -> 0 | CT49: =(0)/150 -> 0 | CU49: =(0)/150 -> 0 | CV49: =(0)/150 -> 0 | CW49: =(20)/150 -> 0.13333333 | CX49: =(7)/157.5 -> 0.044444444 | CY49: =(7)/157.5 -> 0.044444444 | CZ49: =(0)/157.5 -> 0 | DA49: =(0)/157.5 -> 0 | DB49: =(0)/157.5 -> 0 | DC49: =(0)/157.5 -> 0 | DD49: =(5)/157.5 -> 0.031746032 | DE49: =(5)/127.5 -> 0.039215686 | DF49: =(8)/127.5 -> 0.062745098 | DG49: =(0)/127.5 -> 0 | DH49: =(0)/127.5 -> 0 | DI49: =(0)/127.5 -> 0 | DJ49: =(0)/127.5 -> 0 | DK49: =(0)/127.5 -> 0 | DL49: =0/142.5 -> 0 | DM49: =0/142.5 -> 0 | DN49: =0/142.5 -> 0 | DO49: =0/142.5 -> 0 | DP49: =0/142.5 -> 0 | DQ49: =0/172.5 -> 0 | DR49: =0/172.5 -> 0 | DS49: =0/172.5 -> 0
N50: 実績 | O50: =0/127.5 -> 0 | P50: =0/127.5 -> 0 | Q50: =0/127.5 -> 0 | R50: =0/127.5 -> 0 | S50: =0/127.5 -> 0 | T50: =0/127.5 -> 0 | U50: =0/127.5 -> 0 | V50: =0/127.5 -> 0 | ... X50: =0/127.5 -> 0 | Y50: =0/142.5 -> 0 | Z50: =0/142.5 -> 0 | AA50: =0/142.5 -> 0 | AB50: =0/142.5 -> 0 | AC50: =0/142.5 -> 0 | AD50: =0/142.5 -> 0 | AE50: =0/165 -> 0 | AG50: =0/165 -> 0 | AH50: =0/165 -> 0 | AI50: =0/165 -> 0 | AJ50: =0/165 -> 0 | AK50: =0/165 -> 0 | AL50: =0/165 -> 0 | AM50: =0/165 -> 0 | AN50: =0/165 -> 0 | ... AR50: =0/165 -> 0 | AS50: =(0)/165 -> 0 | AT50: =(6+6+11.5+3)/165 -> 0.16060606 | AU50: =(0)/165 -> 0 | AV50: =(0)/165 -> 0 | AW50: =(0)/165 -> 0 | AX50: =(0)/165 -> 0 | AY50: =(0)/165 -> 0 | AZ50: =(0)/165 -> 0 | BA50: =(3+16.5+22+3.5)/165 -> 0.27272727 | BB50: =(4.5+2)/165 -> 0.039393939 | BC50: =(1)/157.5 -> 0.0063492063 | BD50: =(13.5)/157.5 -> 0.085714286 | BE50: =(0)/157.5 -> 0 | BF50: =(0)/157.5 -> 0 | BG50: =(0)/157.5 -> 0 | BH50: =(0)/157.5 -> 0 | BI50: =(0)/157.5 -> 0 | BJ50: =(0)/157.5 -> 0 | BK50: =(13.5)/157.5 -> 0.085714286 | BL50: =(0)/157.5 -> 0 | BM50: =(0)/165 -> 0 | BN50: =(0)/165 -> 0 | BO50: =(0)/165 -> 0 | BP50: =(0)/165 -> 0 | BQ50: =(0)/165 -> 0 | BR50: =(0)/165 -> 0 | BS50: =(0)/165 -> 0 | BT50: =(0)/165 -> 0 | ... BV50: =(0)/165 -> 0 | BW50: =(0)/150 -> 0 | BX50: =(0)/150 -> 0 | BY50: =(0)/150 -> 0 | BZ50: =(0)/150 -> 0 | CA50: =(0)/150 -> 0 | CB50: =(0)/150 -> 0 | CC50: =(0)/150 -> 0 | CD50: =(0)/150 -> 0 | ... CF50: =(0)/150 -> 0 | CG50: =(7)/135 -> 0.051851852 | CH50: =(22)/135 -> 0.16296296 | CI50: =(0)/135 -> 0 | CJ50: =(0)/135 -> 0 | CK50: =(0)/135 -> 0 | CL50: =(0)/135 -> 0 | CM50: =(0)/135 -> 0 | CN50: =(0)/135 -> 0 | CO50: =(22.5)/135 -> 0.16666667 | CP50: =(0)/135 -> 0 | CQ50: =(3+3+1)/150 -> 0.046666667 | CR50: =(2+7+4.5+5.5)/150 -> 0.12666667 | CS50: =(0)/150 -> 0 | CT50: =(0)/150 -> 0 | CU50: =(0)/150 -> 0 | CV50: =(0)/150 -> 0 | CW50: =(3+15+4)/150 -> 0.14666667 | CX50: =(1+3+3)/157.5 -> 0.044444444 | CY50: =(0+4.5+1.5)/157.5 -> 0.038095238 | CZ50: =(0)/157.5 -> 0 | DA50: =(0)/157.5 -> 0 | DB50: =(0)/157.5 -> 0 | DC50: =(0)/157.5 -> 0 | DD50: =(0+5)/157.5 -> 0.031746032 | DE50: =(2)/127.5 -> 0.015686275 | DF50: =(7)/127.5 -> 0.054901961 | DG50: =(0)/127.5 -> 0 | DH50: =(0)/127.5 -> 0 | DI50: =(0)/127.5 -> 0 | DJ50: =(0)/127.5 -> 0 | DK50: =(0)/127.5 -> 0 | DL50: =0/142.5 -> 0 | DM50: =0/142.5 -> 0 | DN50: =0/142.5 -> 0 | DO50: =0/142.5 -> 0 | DP50: =0/142.5 -> 0 | DQ50: =0/172.5 -> 0 | DR50: =0/172.5 -> 0 | DS50: =0/172.5 -> 0
A51: 23 | B51: 完了 | C51: 定型 | D51: 山田 | E51: F185 | F51: PB00201943 | G51: 【定型】メールアドレス欄への注釈追加 | H51: =SUM(DE51:DK51) -> 0 | I51: =SUM(DE52:DK52) -> 0 | N51: 計画 | O51: =0/127.5 -> 0 | P51: =0/127.5 -> 0 | Q51: =0/127.5 -> 0 | R51: =0/127.5 -> 0 | S51: =0/127.5 -> 0 | T51: =0/127.5 -> 0 | U51: =0/127.5 -> 0 | V51: =0/127.5 -> 0 | ... X51: =0/127.5 -> 0 | Y51: =0/142.5 -> 0 | Z51: =0/142.5 -> 0 | AA51: =0/142.5 -> 0 | AB51: =0/142.5 -> 0 | AC51: =0/142.5 -> 0 | AD51: =0/142.5 -> 0 | AE51: =0/165 -> 0 | AG51: =0/165 -> 0 | AH51: =0/165 -> 0 | AI51: =0/165 -> 0 | AJ51: =0/165 -> 0 | AK51: =0/165 -> 0 | AL51: =0/165 -> 0 | AM51: =0/165 -> 0 | AN51: =0/165 -> 0 | ... AR51: =0/165 -> 0 | AS51: =(0)/165 -> 0 | AT51: =(0)/165 -> 0 | AU51: =(0)/165 -> 0 | AV51: =(0)/165 -> 0 | AW51: =(14)/165 -> 0.084848485 | AX51: =(0)/165 -> 0 | AY51: =(0)/165 -> 0 | AZ51: =(0)/165 -> 0 | BA51: =(0)/165 -> 0 | BB51: =(14)/165 -> 0.084848485 | BC51: =(0)/157.5 -> 0 | BD51: =(0)/157.5 -> 0 | BE51: =(0)/157.5 -> 0 | BF51: =(0)/157.5 -> 0 | BG51: =(0)/157.5 -> 0 | BH51: =(0)/157.5 -> 0 | BI51: =(0)/157.5 -> 0 | BJ51: =(0)/157.5 -> 0 | ... BL51: =(0)/157.5 -> 0 | BM51: =(0)/165 -> 0 | BN51: =(0)/165 -> 0 | BO51: =(0)/165 -> 0 | BP51: =(0)/165 -> 0 | BQ51: =(0)/165 -> 0 | BR51: =(0)/165 -> 0 | BS51: =(0)/165 -> 0 | BT51: =(0)/165 -> 0 | ... BV51: =(0)/165 -> 0 | BW51: =(0)/150 -> 0 | BX51: =(0)/150 -> 0 | BY51: =(0)/150 -> 0 | BZ51: =(0)/150 -> 0 | CA51: =(0)/150 -> 0 | CB51: =(0)/150 -> 0 | CC51: =(0)/150 -> 0 | CD51: =(0)/150 -> 0 | ... CF51: =(0)/150 -> 0 | CG51: =(0)/135 -> 0 | CH51: =(0)/135 -> 0 | CI51: =(0)/135 -> 0 | CJ51: =(0)/135 -> 0 | CK51: =(0)/135 -> 0 | CL51: =(0)/135 -> 0 | CM51: =(0)/135 -> 0 | CN51: =(0)/135 -> 0 | ... CW51: =(0)/135 -> 0 | CX51: =0/157.5 -> 0 | CY51: =0/157.5 -> 0 | CZ51: =0/157.5 -> 0 | DA51: =0/157.5 -> 0 | DB51: =0/157.5 -> 0 | DC51: =0/172.5 -> 0 | DD51: =0/172.5 -> 0 | DE51: =0/127.5 -> 0 | DF51: =0/127.5 -> 0 | DG51: =0/127.5 -> 0 | DH51: =0/127.5 -> 0 | DI51: =0/127.5 -> 0 | DJ51: =0/172.5 -> 0 | DK51: =0/172.5 -> 0 | DL51: =0/142.5 -> 0 | DM51: =0/142.5 -> 0 | DN51: =0/142.5 -> 0 | DO51: =0/142.5 -> 0 | DP51: =0/142.5 -> 0 | DQ51: =0/172.5 -> 0 | DR51: =0/172.5 -> 0 | DS51: =0/172.5 -> 0
N52: 実績 | O52: =0/127.5 -> 0 | P52: =0/127.5 -> 0 | Q52: =0/127.5 -> 0 | R52: =0/127.5 -> 0 | S52: =0/127.5 -> 0 | T52: =0/127.5 -> 0 | U52: =0/127.5 -> 0 | V52: =0/127.5 -> 0 | ... X52: =0/127.5 -> 0 | Y52: =0/142.5 -> 0 | Z52: =0/142.5 -> 0 | AA52: =0/142.5 -> 0 | AB52: =0/142.5 -> 0 | AC52: =0/142.5 -> 0 | AD52: =0/142.5 -> 0 | AE52: =0/165 -> 0 | AG52: =0/165 -> 0 | AH52: =0/165 -> 0 | AI52: =0/165 -> 0 | AJ52: =0/165 -> 0 | AK52: =0/165 -> 0 | AL52: =0/165 -> 0 | AM52: =0/165 -> 0 | AN52: =0/165 -> 0 | ... AR52: =0/165 -> 0 | AS52: =(0)/165 -> 0 | AT52: =(0)/165 -> 0 | AU52: =(0)/165 -> 0 | AV52: =(0)/165 -> 0 | AW52: =(11.5+4)/165 -> 0.093939394 | AX52: =(0)/165 -> 0 | AY52: =(0)/165 -> 0 | AZ52: =(0)/165 -> 0 | BA52: =(0)/165 -> 0 | BB52: =(8.5+2)/165 -> 0.063636364 | BC52: =(0)/157.5 -> 0 | BD52: =(0)/157.5 -> 0 | BE52: =(0)/157.5 -> 0 | BF52: =(0)/157.5 -> 0 | BG52: =(0)/157.5 -> 0 | BH52: =(0)/157.5 -> 0 | BI52: =(0)/157.5 -> 0 | BJ52: =(0)/157.5 -> 0 | ... BL52: =(0)/157.5 -> 0 | BM52: =(0)/165 -> 0 | BN52: =(0)/165 -> 0 | BO52: =(0)/165 -> 0 | BP52: =(0)/165 -> 0 | BQ52: =(0)/165 -> 0 | BR52: =(0)/165 -> 0 | BS52: =(0)/165 -> 0 | BT52: =(0)/165 -> 0 | ... BV52: =(0)/165 -> 0 | BW52: =(0)/150 -> 0 | BX52: =(0)/150 -> 0 | BY52: =(0)/150 -> 0 | BZ52: =(0)/150 -> 0 | CA52: =(0)/150 -> 0 | CB52: =(0)/150 -> 0 | CC52: =(0)/150 -> 0 | CD52: =(0)/150 -> 0 | ... CF52: =(0)/150 -> 0 | CG52: =(0)/135 -> 0 | CH52: =(0)/135 -> 0 | CI52: =(0)/135 -> 0 | CJ52: =(0)/135 -> 0 | CK52: =(0)/135 -> 0 | CL52: =(0)/135 -> 0 | CM52: =(0)/135 -> 0 | CN52: =(0)/135 -> 0 | ... CW52: =(0)/135 -> 0 | CX52: =0/157.5 -> 0 | CY52: =0/157.5 -> 0 | CZ52: =0/157.5 -> 0 | DA52: =0/157.5 -> 0 | DB52: =0/157.5 -> 0 | DC52: =0/172.5 -> 0 | DD52: =0/172.5 -> 0 | DE52: =0/127.5 -> 0 | DF52: =0/127.5 -> 0 | DG52: =0/127.5 -> 0 | DH52: =0/127.5 -> 0 | DI52: =0/127.5 -> 0 | DJ52: =0/172.5 -> 0 | DK52: =0/172.5 -> 0 | DL52: =0/142.5 -> 0 | DM52: =0/142.5 -> 0 | DN52: =0/142.5 -> 0 | DO52: =0/142.5 -> 0 | DP52: =0/142.5 -> 0 | DQ52: =0/172.5 -> 0 | DR52: =0/172.5 -> 0 | DS52: =0/172.5 -> 0
A53: 24 | B53: 完了 | C53: その他 | D53: 仲井 | E53: PR8 | G53: 【調査依頼】4453_PB00201938_(44)CFD終了対応 | H53: =SUM(DE53:DK53) -> 0 | I53: =SUM(DE54:DK54) -> 0 | N53: 計画 | O53: =0/127.5 -> 0 | P53: =0/127.5 -> 0 | Q53: =0/127.5 -> 0 | R53: =0/127.5 -> 0 | S53: =0/127.5 -> 0 | T53: =0/127.5 -> 0 | U53: =0/127.5 -> 0 | V53: =0/127.5 -> 0 | ... X53: =0/127.5 -> 0 | Y53: =0/142.5 -> 0 | Z53: =0/142.5 -> 0 | AA53: =0/142.5 -> 0 | AB53: =0/142.5 -> 0 | AC53: =0/142.5 -> 0 | AD53: =0/142.5 -> 0 | AE53: =0/165 -> 0 | AG53: =0/165 -> 0 | AH53: =0/165 -> 0 | AI53: =0/165 -> 0 | AJ53: =0/165 -> 0 | AK53: =0/165 -> 0 | AL53: =0/165 -> 0 | AM53: =0/165 -> 0 | AN53: =0/165 -> 0 | ... AR53: =0/165 -> 0 | AS53: =(0)/165 -> 0 | AT53: =(0)/165 -> 0 | AU53: =(15)/165 -> 0.090909091 | AV53: =(40)/165 -> 0.24242424 | AW53: =(0)/165 -> 0 | AX53: =(20)/165 -> 0.12121212 | AY53: =(0)/165 -> 0 | AZ53: =(40)/165 -> 0.24242424 | BA53: =(0)/165 -> 0 | BB53: =(14)/165 -> 0.084848485 | BC53: =(0)/157.5 -> 0 | BD53: =(0)/157.5 -> 0 | BE53: =(6)/157.5 -> 0.038095238 | BF53: =(0)/157.5 -> 0 | BG53: =(0)/157.5 -> 0 | BH53: =(0)/157.5 -> 0 | BI53: =(0)/157.5 -> 0 | BJ53: =(6)/157.5 -> 0.038095238 | BK53: =(0)/157.5 -> 0 | BL53: =(0)/157.5 -> 0 | BM53: =(0)/165 -> 0 | BN53: =(0)/165 -> 0 | BO53: =(0)/165 -> 0 | BP53: =(0)/165 -> 0 | BQ53: =(0)/165 -> 0 | BR53: =(0)/165 -> 0 | BS53: =(0)/165 -> 0 | BT53: =(0)/165 -> 0 | ... BV53: =(0)/165 -> 0 | BW53: =(0)/150 -> 0 | BX53: =(0)/150 -> 0 | BY53: =(0)/150 -> 0 | BZ53: =(0)/150 -> 0 | CA53: =(0)/150 -> 0 | CB53: =(0)/150 -> 0 | CC53: =(0)/150 -> 0 | CD53: =(0)/150 -> 0 | ... CF53: =(0)/150 -> 0 | CG53: =(0)/135 -> 0 | CH53: =(0)/135 -> 0 | CI53: =(0)/135 -> 0 | CJ53: =(0)/135 -> 0 | CK53: =(0)/135 -> 0 | CL53: =(0)/135 -> 0 | CM53: =(0)/135 -> 0 | CN53: =(0)/135 -> 0 | ... CW53: =(0)/135 -> 0 | CX53: =0/157.5 -> 0 | CY53: =0/157.5 -> 0 | CZ53: =0/157.5 -> 0 | DA53: =0/157.5 -> 0 | DB53: =0/157.5 -> 0 | DC53: =0/172.5 -> 0 | DD53: =0/172.5 -> 0 | DE53: =0/127.5 -> 0 | DF53: =0/127.5 -> 0 | DG53: =0/127.5 -> 0 | DH53: =0/127.5 -> 0 | DI53: =0/127.5 -> 0 | DJ53: =0/172.5 -> 0 | DK53: =0/172.5 -> 0 | DL53: =0/142.5 -> 0 | DM53: =0/142.5 -> 0 | DN53: =0/142.5 -> 0 | DO53: =0/142.5 -> 0 | DP53: =0/142.5 -> 0 | DQ53: =0/172.5 -> 0 | DR53: =0/172.5 -> 0 | DS53: =0/172.5 -> 0
N54: 実績 | O54: =0/127.5 -> 0 | P54: =0/127.5 -> 0 | Q54: =0/127.5 -> 0 | R54: =0/127.5 -> 0 | S54: =0/127.5 -> 0 | T54: =0/127.5 -> 0 | U54: =0/127.5 -> 0 | V54: =0/127.5 -> 0 | ... X54: =0/127.5 -> 0 | Y54: =0/142.5 -> 0 | Z54: =0/142.5 -> 0 | AA54: =0/142.5 -> 0 | AB54: =0/142.5 -> 0 | AC54: =0/142.5 -> 0 | AD54: =0/142.5 -> 0 | AE54: =0/165 -> 0 | AG54: =0/165 -> 0 | AH54: =0/165 -> 0 | AI54: =0/165 -> 0 | AJ54: =0/165 -> 0 | AK54: =0/165 -> 0 | AL54: =0/165 -> 0 | AM54: =0/165 -> 0 | AN54: =0/165 -> 0 | ... AR54: =0/165 -> 0 | AS54: =(0)/165 -> 0 | AT54: =(0)/165 -> 0 | AU54: =(7+6.5+1.5)/165 -> 0.090909091 | AV54: =(19+21+3.5)/165 -> 0.26363636 | AW54: =(0)/165 -> 0 | AX54: =(0+6.5+2)/165 -> 0.051515152 | AY54: =(0)/165 -> 0 | AZ54: =(15+27+6.5+1)/165 -> 0.3 | BA54: =(0)/165 -> 0 | BB54: =(0+6.5+3)/165 -> 0.057575758 | BC54: =(0)/157.5 -> 0 | BD54: =(0)/157.5 -> 0 | BE54: =(1.5)/157.5 -> 0.0095238095 | BF54: =(5)/157.5 -> 0.031746032 | BG54: =(0)/157.5 -> 0 | BH54: =(0)/157.5 -> 0 | BI54: =(0)/157.5 -> 0 | BJ54: =(5)/157.5 -> 0.031746032 | BK54: =(0)/157.5 -> 0 | BL54: =(0)/157.5 -> 0 | BM54: =(0)/165 -> 0 | BN54: =(0)/165 -> 0 | BO54: =(0)/165 -> 0 | BP54: =(0)/165 -> 0 | BQ54: =(0)/165 -> 0 | BR54: =(0)/165 -> 0 | BS54: =(0)/165 -> 0 | BT54: =(0)/165 -> 0 | ... BV54: =(0)/165 -> 0 | BW54: =(0)/150 -> 0 | BX54: =(0)/150 -> 0 | BY54: =(0)/150 -> 0 | BZ54: =(0)/150 -> 0 | CA54: =(0)/150 -> 0 | CB54: =(0)/150 -> 0 | CC54: =(0)/150 -> 0 | CD54: =(0)/150 -> 0 | ... CF54: =(0)/150 -> 0 | CG54: =(0)/135 -> 0 | CH54: =(0)/135 -> 0 | CI54: =(0)/135 -> 0 | CJ54: =(0)/135 -> 0 | CK54: =(0)/135 -> 0 | CL54: =(0)/135 -> 0 | CM54: =(0)/135 -> 0 | CN54: =(0)/135 -> 0 | ... CW54: =(0)/135 -> 0 | CX54: =0/157.5 -> 0 | CY54: =0/157.5 -> 0 | CZ54: =0/157.5 -> 0 | DA54: =0/157.5 -> 0 | DB54: =0/157.5 -> 0 | DC54: =0/172.5 -> 0 | DD54: =0/172.5 -> 0 | DE54: =0/127.5 -> 0 | DF54: =0/127.5 -> 0 | DG54: =0/127.5 -> 0 | DH54: =0/127.5 -> 0 | DI54: =0/127.5 -> 0 | DJ54: =0/172.5 -> 0 | DK54: =0/172.5 -> 0 | DL54: =0/142.5 -> 0 | DM54: =0/142.5 -> 0 | DN54: =0/142.5 -> 0 | DO54: =0/142.5 -> 0 | DP54: =0/142.5 -> 0 | DQ54: =0/172.5 -> 0 | DR54: =0/172.5 -> 0 | DS54: =0/172.5 -> 0
A55: 25 | B55: 完了 | C55: その他 | D55: 山田 | E55: F186 | F55: PB00201962 | G55: 【定型】WEB口座開設画面の外国籍文言追加（再アップロード画面） | H55: =SUM(DE55:DK55) -> 0 | I55: =SUM(DE56:DK56) -> 0 | N55: 計画 | O55: =0/127.5 -> 0 | P55: =0/127.5 -> 0 | Q55: =0/127.5 -> 0 | R55: =0/127.5 -> 0 | S55: =0/127.5 -> 0 | T55: =0/127.5 -> 0 | U55: =0/127.5 -> 0 | V55: =0/127.5 -> 0 | ... X55: =0/127.5 -> 0 | Y55: =0/142.5 -> 0 | Z55: =0/142.5 -> 0 | AA55: =0/142.5 -> 0 | AB55: =0/142.5 -> 0 | AC55: =0/142.5 -> 0 | AD55: =0/142.5 -> 0 | AE55: =0/165 -> 0 | AG55: =0/165 -> 0 | AH55: =0/165 -> 0 | AI55: =0/165 -> 0 | AJ55: =0/165 -> 0 | AK55: =0/165 -> 0 | AL55: =0/165 -> 0 | AM55: =0/165 -> 0 | AN55: =0/165 -> 0 | ... AR55: =0/165 -> 0 | AS55: =0/150 -> 0 | AT55: =0/150 -> 0 | AU55: =0/150 -> 0 | AV55: =0/150 -> 0 | AW55: =0/150 -> 0 | AX55: =0/165 -> 0 | AY55: =0/165 -> 0 | AZ55: =0/165 -> 0 | BA55: =0/165 -> 0 | BB55: =0/165 -> 0 | BC55: =(8)/157.5 -> 0.050793651 | BD55: =(0)/157.5 -> 0 | BE55: =(22)/157.5 -> 0.13968254 | BF55: =(0)/157.5 -> 0 | BG55: =(0)/157.5 -> 0 | BH55: =(0)/157.5 -> 0 | BI55: =(30)/157.5 -> 0.19047619 | BJ55: =(20)/157.5 -> 0.12698413 | BK55: =(20)/157.5 -> 0.12698413 | BL55: =(0)/157.5 -> 0 | BM55: =(5)/165 -> 0.03030303 | BN55: =(0)/165 -> 0 | BO55: =(15)/165 -> 0.090909091 | BP55: =(0)/165 -> 0 | BQ55: =(0)/165 -> 0 | BR55: =(0)/165 -> 0 | BS55: =(10)/165 -> 0.060606061 | BT55: =(10)/165 -> 0.060606061 | BU55: =(0)/165 -> 0 | BV55: =(0)/165 -> 0 | BW55: =(0)/150 -> 0 | BX55: =(0)/150 -> 0 | BY55: =(0)/150 -> 0 | BZ55: =(0)/150 -> 0 | CA55: =(0)/150 -> 0 | CB55: =(0)/150 -> 0 | CC55: =(0)/150 -> 0 | CD55: =(0)/150 -> 0 | ... CF55: =(0)/150 -> 0 | CG55: =(0)/135 -> 0 | CH55: =(0)/135 -> 0 | CI55: =(0)/135 -> 0 | CJ55: =(0)/135 -> 0 | CK55: =(0)/135 -> 0 | CL55: =(0)/135 -> 0 | CM55: =(0)/135 -> 0 | CN55: =(0)/135 -> 0 | ... CW55: =(0)/135 -> 0 | CX55: =0/157.5 -> 0 | CY55: =0/157.5 -> 0 | CZ55: =0/157.5 -> 0 | DA55: =0/157.5 -> 0 | DB55: =0/157.5 -> 0 | DC55: =0/172.5 -> 0 | DD55: =0/172.5 -> 0 | DE55: =0/127.5 -> 0 | DF55: =0/127.5 -> 0 | DG55: =0/127.5 -> 0 | DH55: =0/127.5 -> 0 | DI55: =0/127.5 -> 0 | DJ55: =0/172.5 -> 0 | DK55: =0/172.5 -> 0 | DL55: =0/142.5 -> 0 | DM55: =0/142.5 -> 0 | DN55: =0/142.5 -> 0 | DO55: =0/142.5 -> 0 | DP55: =0/142.5 -> 0 | DQ55: =0/172.5 -> 0 | DR55: =0/172.5 -> 0 | DS55: =0/172.5 -> 0
N56: 実績 | O56: =0/127.5 -> 0 | P56: =0/127.5 -> 0 | Q56: =0/127.5 -> 0 | R56: =0/127.5 -> 0 | S56: =0/127.5 -> 0 | T56: =0/127.5 -> 0 | U56: =0/127.5 -> 0 | V56: =0/127.5 -> 0 | ... X56: =0/127.5 -> 0 | Y56: =0/142.5 -> 0 | Z56: =0/142.5 -> 0 | AA56: =0/142.5 -> 0 | AB56: =0/142.5 -> 0 | AC56: =0/142.5 -> 0 | AD56: =0/142.5 -> 0 | AE56: =0/165 -> 0 | AG56: =0/165 -> 0 | AH56: =0/165 -> 0 | AI56: =0/165 -> 0 | AJ56: =0/165 -> 0 | AK56: =0/165 -> 0 | AL56: =0/165 -> 0 | AM56: =0/165 -> 0 | AN56: =0/165 -> 0 | ... AR56: =0/165 -> 0 | AS56: =0/150 -> 0 | AT56: =0/150 -> 0 | AU56: =0/150 -> 0 | AV56: =0/150 -> 0 | AW56: =0/150 -> 0 | AX56: =0/165 -> 0 | AY56: =0/165 -> 0 | AZ56: =0/165 -> 0 | BA56: =0/165 -> 0 | BB56: =0/165 -> 0 | BC56: =(3+3)/157.5 -> 0.038095238 | BD56: =(0)/157.5 -> 0 | BE56: =(0+19+5.5)/157.5 -> 0.15555556 | BF56: =(0)/157.5 -> 0 | BG56: =(0)/157.5 -> 0 | BH56: =(0)/157.5 -> 0 | BI56: =(0+20+13.5)/157.5 -> 0.21269841 | BJ56: =(0+10+5.5)/157.5 -> 0.098412698 | BK56: =(0+18)/157.5 -> 0.11428571 | BL56: =(0)/157.5 -> 0 | BM56: =(1.5+1)/165 -> 0.015151515 | BN56: =(0)/165 -> 0 | BO56: =(8+5)/165 -> 0.078787879 | BP56: =(0)/165 -> 0 | BQ56: =(0)/165 -> 0 | BR56: =(0)/165 -> 0 | BS56: =(5+1.5)/165 -> 0.039393939 | BT56: =(5+9+2.5)/165 -> 0.1 | BU56: =(0)/165 -> 0 | BV56: =(0)/165 -> 0 | BW56: =(0)/150 -> 0 | BX56: =(0)/150 -> 0 | BY56: =(0)/150 -> 0 | BZ56: =(0)/150 -> 0 | CA56: =(0)/150 -> 0 | CB56: =(0)/150 -> 0 | CC56: =(0)/150 -> 0 | CD56: =(0)/150 -> 0 | ... CF56: =(0)/150 -> 0 | CG56: =(0)/135 -> 0 | CH56: =(0)/135 -> 0 | CI56: =(0)/135 -> 0 | CJ56: =(0)/135 -> 0 | CK56: =(0)/135 -> 0 | CL56: =(0)/135 -> 0 | CM56: =(0)/135 -> 0 | CN56: =(0)/135 -> 0 | ... CW56: =(0)/135 -> 0 | CX56: =0/157.5 -> 0 | CY56: =0/157.5 -> 0 | CZ56: =0/157.5 -> 0 | DA56: =0/157.5 -> 0 | DB56: =0/157.5 -> 0 | DC56: =0/172.5 -> 0 | DD56: =0/172.5 -> 0 | DE56: =0/127.5 -> 0 | DF56: =0/127.5 -> 0 | DG56: =0/127.5 -> 0 | DH56: =0/127.5 -> 0 | DI56: =0/127.5 -> 0 | DJ56: =0/172.5 -> 0 | DK56: =0/172.5 -> 0 | DL56: =0/142.5 -> 0 | DM56: =0/142.5 -> 0 | DN56: =0/142.5 -> 0 | DO56: =0/142.5 -> 0 | DP56: =0/142.5 -> 0 | DQ56: =0/172.5 -> 0 | DR56: =0/172.5 -> 0 | DS56: =0/172.5 -> 0
A57: 26 | B57: 完了 | C57: その他 | D57: 仲井 | E57: BT4 | F57: 4429_PBxxxxxxxx | G57: 【開発依頼】シリアルナンバー初期化 | H57: =SUM(DE57:DK57) -> 0 | I57: =SUM(DE58:DK58) -> 0 | N57: 計画 | O57: =0/127.5 -> 0 | P57: =0/127.5 -> 0 | Q57: =0/127.5 -> 0 | R57: =0/127.5 -> 0 | S57: =0/127.5 -> 0 | T57: =0/127.5 -> 0 | U57: =0/127.5 -> 0 | V57: =0/127.5 -> 0 | ... X57: =0/127.5 -> 0 | Y57: =0/142.5 -> 0 | Z57: =0/142.5 -> 0 | AA57: =0/142.5 -> 0 | AB57: =0/142.5 -> 0 | AC57: =0/142.5 -> 0 | AD57: =0/142.5 -> 0 | AE57: =0/165 -> 0 | AG57: =0/165 -> 0 | AH57: =0/165 -> 0 | AI57: =0/165 -> 0 | AJ57: =0/165 -> 0 | AK57: =0/165 -> 0 | AL57: =0/165 -> 0 | AM57: =0/165 -> 0 | AN57: =0/165 -> 0 | ... AR57: =0/165 -> 0 | AS57: =0/150 -> 0 | AT57: =0/150 -> 0 | AU57: =0/150 -> 0 | AV57: =0/150 -> 0 | AW57: =0/150 -> 0 | AX57: =0/165 -> 0 | AY57: =0/165 -> 0 | AZ57: =0/165 -> 0 | BA57: =0/165 -> 0 | BB57: =0/165 -> 0 | BC57: =(0)/157.5 -> 0 | BD57: =(0)/157.5 -> 0 | BE57: =(10)/157.5 -> 0.063492063 | BF57: =(0)/157.5 -> 0 | BG57: =(0)/157.5 -> 0 | BH57: =(10)/157.5 -> 0.063492063 | BI57: =(0)/157.5 -> 0 | BJ57: =(0)/157.5 -> 0 | BK57: =(0)/157.5 -> 0 | BL57: =(0)/157.5 -> 0 | BM57: =(20)/165 -> 0.12121212 | BN57: =(0)/165 -> 0 | BO57: =(50)/165 -> 0.3030303 | BP57: =(0)/165 -> 0 | BQ57: =(0)/165 -> 0 | BR57: =(70)/165 -> 0.42424242 | BS57: =(0)/165 -> 0 | BT57: =(50)/165 -> 0.3030303 | BU57: =(0)/165 -> 0 | BV57: =(0)/165 -> 0 | BW57: =(0)/150 -> 0 | BX57: =(0)/150 -> 0 | BY57: =(3.5)/150 -> 0.023333333 | BZ57: =(0)/150 -> 0 | CA57: =(0)/150 -> 0 | CB57: =(0)/150 -> 0 | CC57: =(0)/150 -> 0 | CD57: =(3.5)/150 -> 0.023333333 | CE57: =(0)/150 -> 0 | CF57: =(0)/150 -> 0 | CG57: =(5)/135 -> 0.037037037 | CH57: =(0)/135 -> 0 | CI57: =(5)/135 -> 0.037037037 | CJ57: =(0)/135 -> 0 | CK57: =(0)/135 -> 0 | CL57: =(5)/135 -> 0.037037037 | CM57: =(0)/135 -> 0 | CN57: =(5)/135 -> 0.037037037 | CO57: =(0)/135 -> 0 | CP57: =(0)/135 -> 0 | CQ57: =(0)/150 -> 0 | CR57: =(0)/150 -> 0 | CS57: =(0)/150 -> 0 | CT57: =(0)/150 -> 0 | CU57: =(0)/150 -> 0 | CV57: =(0)/150 -> 0 | CW57: =(0)/150 -> 0 | CX57: =(0)/157.5 -> 0 | CY57: =(0)/157.5 -> 0 | CZ57: =(0)/157.5 -> 0 | DA57: =(0)/157.5 -> 0 | DB57: =(0)/157.5 -> 0 | DC57: =(0)/157.5 -> 0 | DD57: =(0)/157.5 -> 0 | DE57: =0/127.5 -> 0 | DF57: =0/127.5 -> 0 | DG57: =0/127.5 -> 0 | DH57: =0/127.5 -> 0 | DI57: =0/127.5 -> 0 | DJ57: =0/172.5 -> 0 | DK57: =0/172.5 -> 0 | DL57: =0/142.5 -> 0 | DM57: =0/142.5 -> 0 | DN57: =0/142.5 -> 0 | DO57: =0/142.5 -> 0 | DP57: =0/142.5 -> 0 | DQ57: =0/172.5 -> 0 | DR57: =0/172.5 -> 0 | DS57: =0/172.5 -> 0
N58: 実績 | O58: =0/127.5 -> 0 | P58: =0/127.5 -> 0 | Q58: =0/127.5 -> 0 | R58: =0/127.5 -> 0 | S58: =0/127.5 -> 0 | T58: =0/127.5 -> 0 | U58: =0/127.5 -> 0 | V58: =0/127.5 -> 0 | ... X58: =0/127.5 -> 0 | Y58: =0/142.5 -> 0 | Z58: =0/142.5 -> 0 | AA58: =0/142.5 -> 0 | AB58: =0/142.5 -> 0 | AC58: =0/142.5 -> 0 | AD58: =0/142.5 -> 0 | AE58: =0/165 -> 0 | AG58: =0/165 -> 0 | AH58: =0/165 -> 0 | AI58: =0/165 -> 0 | AJ58: =0/165 -> 0 | AK58: =0/165 -> 0 | AL58: =0/165 -> 0 | AM58: =0/165 -> 0 | AN58: =0/165 -> 0 | ... AR58: =0/165 -> 0 | AS58: =0/150 -> 0 | AT58: =0/150 -> 0 | AU58: =0/150 -> 0 | AV58: =0/150 -> 0 | AW58: =0/150 -> 0 | AX58: =0/165 -> 0 | AY58: =0/165 -> 0 | AZ58: =0/165 -> 0 | BA58: =0/165 -> 0 | BB58: =0/165 -> 0 | BC58: =(0+3.5)/157.5 -> 0.022222222 | BD58: =(0)/157.5 -> 0 | BE58: =(0+7)/157.5 -> 0.044444444 | BF58: =(0)/157.5 -> 0 | BG58: =(0)/157.5 -> 0 | BH58: =(0+9.5)/157.5 -> 0.06031746 | BI58: =(0)/157.5 -> 0 | BJ58: =(0)/157.5 -> 0 | BK58: =(0)/157.5 -> 0 | BL58: =(0)/157.5 -> 0 | BM58: =(3.5+4.5+2+2+4)/165 -> 0.096969697 | BN58: =(0)/165 -> 0 | BO58: =(8+10.5+17.5+14)/165 -> 0.3030303 | BP58: =(0)/165 -> 0 | BQ58: =(0)/165 -> 0 | BR58: =(9+21.5+18.5+18+13)/165 -> 0.48484848 | BS58: =(0)/165 -> 0 | BT58: =(0+12+10.5+16.5)/165 -> 0.23636364 | BU58: =(0)/165 -> 0 | BV58: =(0)/165 -> 0 | BW58: =(0)/150 -> 0 | BX58: =(0)/150 -> 0 | BY58: =(0+1.5)/150 -> 0.01 | BZ58: =(0)/150 -> 0 | CA58: =(0)/150 -> 0 | CB58: =(0+0.5)/150 -> 0.0033333333 | CC58: =(0)/150 -> 0 | CD58: =(2+0.5)/150 -> 0.016666667 | CE58: =(0)/150 -> 0 | CF58: =(0)/150 -> 0 | CG58: =(1.5+2)/135 -> 0.025925926 | CH58: =(0)/135 -> 0 | CI58: =(2.5)/135 -> 0.018518519 | CJ58: =(0)/135 -> 0 | CK58: =(0)/135 -> 0 | CL58: =(4)/135 -> 0.02962963 | CM58: =(0)/135 -> 0 | CN58: =(3)/135 -> 0.022222222 | CO58: =(0)/135 -> 0 | CP58: =(0)/135 -> 0 | CQ58: =(0)/150 -> 0 | CR58: =(0)/150 -> 0 | CS58: =(0)/150 -> 0 | CT58: =(0)/150 -> 0 | CU58: =(0)/150 -> 0 | CV58: =(0)/150 -> 0 | CW58: =(0)/150 -> 0 | CX58: =(0)/157.5 -> 0 | CY58: =(0)/157.5 -> 0 | CZ58: =(0)/157.5 -> 0 | DA58: =(0)/157.5 -> 0 | DB58: =(0)/157.5 -> 0 | DC58: =(0)/157.5 -> 0 | DD58: =(0)/157.5 -> 0 | DE58: =0/127.5 -> 0 | DF58: =0/127.5 -> 0 | DG58: =0/127.5 -> 0 | DH58: =0/127.5 -> 0 | DI58: =0/127.5 -> 0 | DJ58: =0/172.5 -> 0 | DK58: =0/172.5 -> 0 | DL58: =0/142.5 -> 0 | DM58: =0/142.5 -> 0 | DN58: =0/142.5 -> 0 | DO58: =0/142.5 -> 0 | DP58: =0/142.5 -> 0 | DQ58: =0/172.5 -> 0 | DR58: =0/172.5 -> 0 | DS58: =0/172.5 -> 0
A59: 27 | B59: 完了 | C59: その他 | D59: 德田 | E59: PR9 | F59: 4246_PBxxxxxxxx | G59: 【開発依頼】WB4クロスサイトスクリプティング対応 | H59: =SUM(DE59:DK59) -> 0 | I59: =SUM(DE60:DK60) -> 0 | N59: 計画 | O59: =0/127.5 -> 0 | P59: =0/127.5 -> 0 | Q59: =0/127.5 -> 0 | R59: =0/127.5 -> 0 | S59: =0/127.5 -> 0 | T59: =0/127.5 -> 0 | U59: =0/127.5 -> 0 | V59: =0/127.5 -> 0 | ... X59: =0/127.5 -> 0 | Y59: =0/142.5 -> 0 | Z59: =0/142.5 -> 0 | AA59: =0/142.5 -> 0 | AB59: =0/142.5 -> 0 | AC59: =0/142.5 -> 0 | AD59: =0/142.5 -> 0 | AE59: =0/165 -> 0 | AG59: =0/165 -> 0 | AH59: =0/165 -> 0 | AI59: =0/165 -> 0 | AJ59: =0/165 -> 0 | AK59: =0/165 -> 0 | AL59: =0/165 -> 0 | AM59: =0/165 -> 0 | AN59: =0/165 -> 0 | ... AR59: =0/165 -> 0 | AS59: =0/150 -> 0 | AT59: =0/150 -> 0 | AU59: =0/150 -> 0 | AV59: =0/150 -> 0 | AW59: =0/150 -> 0 | AX59: =0/165 -> 0 | AY59: =0/165 -> 0 | AZ59: =0/165 -> 0 | BA59: =0/165 -> 0 | BB59: =0/165 -> 0 | BC59: =(0)/157.5 -> 0 | BD59: =(0)/157.5 -> 0 | BE59: =(0)/157.5 -> 0 | BF59: =(0)/157.5 -> 0 | BG59: =(0)/157.5 -> 0 | BH59: =(0)/157.5 -> 0 | BI59: =(0)/157.5 -> 0 | BJ59: =(0)/157.5 -> 0 | ... BL59: =(0)/157.5 -> 0 | BM59: =(55)/165 -> 0.33333333 | BN59: =(130)/165 -> 0.78787879 | BO59: =(15)/165 -> 0.090909091 | BP59: =(100)/165 -> 0.60606061 | BQ59: =(100)/165 -> 0.60606061 | BR59: =(15)/165 -> 0.090909091 | BS59: =(100)/165 -> 0.60606061 | BT59: =(50)/165 -> 0.3030303 | BU59: =(100)/165 -> 0.60606061 | BV59: =(120)/165 -> 0.72727273 | BW59: =(17)/150 -> 0.11333333 | BX59: =(17)/150 -> 0.11333333 | BY59: =(17)/150 -> 0.11333333 | BZ59: =(34)/150 -> 0.22666667 | CA59: =(17)/150 -> 0.11333333 | CB59: =(17)/150 -> 0.11333333 | CC59: =(17)/150 -> 0.11333333 | CD59: =(0)/150 -> 0 | CE59: =(17)/150 -> 0.11333333 | CF59: =(17)/150 -> 0.11333333 | CG59: =(0)/135 -> 0 | CH59: =(0)/135 -> 0 | CI59: =(0)/135 -> 0 | CJ59: =(0)/135 -> 0 | CK59: =(0)/135 -> 0 | CL59: =(0)/135 -> 0 | CM59: =(0)/135 -> 0 | CN59: =(0)/135 -> 0 | ... CP59: =(0)/135 -> 0 | CQ59: =(7)/150 -> 0.046666667 | CR59: =(40)/150 -> 0.26666667 | CS59: =(0)/150 -> 0 | CT59: =(30)/150 -> 0.2 | CU59: =(30)/150 -> 0.2 | CV59: =(10)/150 -> 0.066666667 | CW59: =(0)/150 -> 0 | CX59: =0/157.5 -> 0 | CY59: =0/157.5 -> 0 | CZ59: =0/157.5 -> 0 | DA59: =0/157.5 -> 0 | DB59: =0/157.5 -> 0 | DC59: =0/172.5 -> 0 | DD59: =0/172.5 -> 0 | DE59: =0/127.5 -> 0 | DF59: =0/127.5 -> 0 | DG59: =0/127.5 -> 0 | DH59: =0/127.5 -> 0 | DI59: =0/127.5 -> 0 | DJ59: =0/172.5 -> 0 | DK59: =0/172.5 -> 0 | DL59: =0/142.5 -> 0 | DM59: =0/142.5 -> 0 | DN59: =0/142.5 -> 0 | DO59: =0/142.5 -> 0 | DP59: =0/142.5 -> 0 | DQ59: =0/172.5 -> 0 | DR59: =0/172.5 -> 0 | DS59: =0/172.5 -> 0
N60: 実績 | O60: =0/127.5 -> 0 | P60: =0/127.5 -> 0 | Q60: =0/127.5 -> 0 | R60: =0/127.5 -> 0 | S60: =0/127.5 -> 0 | T60: =0/127.5 -> 0 | U60: =0/127.5 -> 0 | V60: =0/127.5 -> 0 | ... X60: =0/127.5 -> 0 | Y60: =0/142.5 -> 0 | Z60: =0/142.5 -> 0 | AA60: =0/142.5 -> 0 | AB60: =0/142.5 -> 0 | AC60: =0/142.5 -> 0 | AD60: =0/142.5 -> 0 | AE60: =0/165 -> 0 | AG60: =0/165 -> 0 | AH60: =0/165 -> 0 | AI60: =0/165 -> 0 | AJ60: =0/165 -> 0 | AK60: =0/165 -> 0 | AL60: =0/165 -> 0 | AM60: =0/165 -> 0 | AN60: =0/165 -> 0 | ... AR60: =0/165 -> 0 | AS60: =0/150 -> 0 | AT60: =0/150 -> 0 | AU60: =0/150 -> 0 | AV60: =0/150 -> 0 | AW60: =0/150 -> 0 | AX60: =0/165 -> 0 | AY60: =0/165 -> 0 | AZ60: =0/165 -> 0 | BA60: =0/165 -> 0 | BB60: =0/165 -> 0 | BC60: =(0)/157.5 -> 0 | BD60: =(0)/157.5 -> 0 | BE60: =(0)/157.5 -> 0 | BF60: =(0)/157.5 -> 0 | BG60: =(0)/157.5 -> 0 | BH60: =(0)/157.5 -> 0 | BI60: =(0)/157.5 -> 0 | BJ60: =(0)/157.5 -> 0 | ... BL60: =(0)/157.5 -> 0 | BM60: =(4.25+6+15.5+18.5+6)/165 -> 0.30454545 | BN60: =(20+33.5+34.5+29.5+27.5)/165 -> 0.87878788 | BO60: =(5+8)/165 -> 0.078787879 | BP60: =(8+14+22.5+33.5+27.5)/165 -> 0.63939394 | BQ60: =(10+24.5+32+32.5+27.5)/165 -> 0.76666667 | BR60: =(11+2)/165 -> 0.078787879 | BS60: =(10+16.5+31.5+29+20.5)/165 -> 0.65151515 | BT60: =(16+10.5+5)/165 -> 0.19090909 | BU60: =(13+21.5+16+2+11.5)/165 -> 0.38787879 | BV60: =(9+18.5+34.5+34.5+27.5)/165 -> 0.75151515 | BW60: =(0.5+4+2)/150 -> 0.043333333 | BX60: =(7+13.5+4.5+5.5)/150 -> 0.20333333 | BY60: =(3.5+7)/150 -> 0.07 | BZ60: =(7+21+3)/150 -> 0.20666667 | CA60: =(7+13.5)/150 -> 0.13666667 | CB60: =(0+10.5)/150 -> 0.07 | CC60: =(0+14)/150 -> 0.093333333 | CD60: =(0)/150 -> 0 | CE60: =(4+9.5)/150 -> 0.09 | CF60: =(7+17.5+3+2.5)/150 -> 0.2 | CG60: =(0)/135 -> 0 | CH60: =(0)/135 -> 0 | CI60: =(0)/135 -> 0 | CJ60: =(0)/135 -> 0 | CK60: =(0)/135 -> 0 | CL60: =(0)/135 -> 0 | CM60: =(0)/135 -> 0 | CN60: =(0)/135 -> 0 | ... CP60: =(0)/135 -> 0 | CQ60: =(1+5+2.75)/150 -> 0.058333333 | CR60: =(5+21.5+16)/150 -> 0.28333333 | CS60: =(0)/150 -> 0 | CT60: =(10.5+16)/150 -> 0.17666667 | CU60: =(7.5+14.5+8.5)/150 -> 0.20333333 | CV60: =(0+7)/150 -> 0.046666667 | CW60: =(0)/150 -> 0 | CX60: =0/157.5 -> 0 | CY60: =0/157.5 -> 0 | CZ60: =0/157.5 -> 0 | DA60: =0/157.5 -> 0 | DB60: =0/157.5 -> 0 | DC60: =0/172.5 -> 0 | DD60: =0/172.5 -> 0 | DE60: =0/127.5 -> 0 | DF60: =0/127.5 -> 0 | DG60: =0/127.5 -> 0 | DH60: =0/127.5 -> 0 | DI60: =0/127.5 -> 0 | DJ60: =0/172.5 -> 0 | DK60: =0/172.5 -> 0 | DL60: =0/142.5 -> 0 | DM60: =0/142.5 -> 0 | DN60: =0/142.5 -> 0 | DO60: =0/142.5 -> 0 | DP60: =0/142.5 -> 0 | DQ60: =0/172.5 -> 0 | DR60: =0/172.5 -> 0 | DS60: =0/172.5 -> 0
A61: 28 | B61: 完了 | C61: 定型 | D61: 山田 | E61: F187 | F61: PB00201966 | G61: 【定型】WB4トップページサポート欄の文言変更 | H61: =SUM(DE61:DK61) -> 0 | I61: =SUM(DE62:DK62) -> 0 | N61: 計画 | O61: =0/127.5 -> 0 | P61: =0/127.5 -> 0 | Q61: =0/127.5 -> 0 | R61: =0/127.5 -> 0 | S61: =0/127.5 -> 0 | T61: =0/127.5 -> 0 | U61: =0/127.5 -> 0 | V61: =0/127.5 -> 0 | ... X61: =0/127.5 -> 0 | Y61: =0/142.5 -> 0 | Z61: =0/142.5 -> 0 | AA61: =0/142.5 -> 0 | AB61: =0/142.5 -> 0 | AC61: =0/142.5 -> 0 | AD61: =0/142.5 -> 0 | AE61: =0/165 -> 0 | AG61: =0/165 -> 0 | AH61: =0/165 -> 0 | AI61: =0/165 -> 0 | AJ61: =0/165 -> 0 | AK61: =0/165 -> 0 | AL61: =0/165 -> 0 | AM61: =0/165 -> 0 | AN61: =0/165 -> 0 | ... AR61: =0/165 -> 0 | AS61: =0/150 -> 0 | AT61: =0/150 -> 0 | AU61: =0/150 -> 0 | AV61: =0/150 -> 0 | AW61: =0/150 -> 0 | AX61: =0/165 -> 0 | AY61: =0/165 -> 0 | AZ61: =0/165 -> 0 | BA61: =0/165 -> 0 | BB61: =0/165 -> 0 | BC61: =(0)/157.5 -> 0 | BD61: =(0)/157.5 -> 0 | BE61: =(0)/157.5 -> 0 | BF61: =(0)/157.5 -> 0 | BG61: =(0)/157.5 -> 0 | BH61: =(0)/157.5 -> 0 | BI61: =(0)/157.5 -> 0 | BJ61: =(0)/157.5 -> 0 | ... BL61: =(0)/157.5 -> 0 | BM61: =(10)/165 -> 0.060606061 | BN61: =(0)/165 -> 0 | BO61: =(0)/165 -> 0 | BP61: =(0)/165 -> 0 | BQ61: =(20)/165 -> 0.12121212 | BR61: =(0)/165 -> 0 | BS61: =(0)/165 -> 0 | BT61: =(0)/165 -> 0 | BU61: =(10)/165 -> 0.060606061 | BV61: =(20)/165 -> 0.12121212 | BW61: =(0)/150 -> 0 | BX61: =(0)/150 -> 0 | BY61: =(0)/150 -> 0 | BZ61: =(0)/150 -> 0 | CA61: =(0)/150 -> 0 | CB61: =(0)/150 -> 0 | CC61: =(0)/150 -> 0 | CD61: =(0)/150 -> 0 | ... CF61: =(0)/150 -> 0 | CG61: =(0)/135 -> 0 | CH61: =(0)/135 -> 0 | CI61: =(0)/135 -> 0 | CJ61: =(0)/135 -> 0 | CK61: =(0)/135 -> 0 | CL61: =(0)/135 -> 0 | CM61: =(0)/135 -> 0 | CN61: =(0)/135 -> 0 | ... CW61: =(0)/135 -> 0 | CX61: =0/157.5 -> 0 | CY61: =0/157.5 -> 0 | CZ61: =0/157.5 -> 0 | DA61: =0/157.5 -> 0 | DB61: =0/157.5 -> 0 | DC61: =0/172.5 -> 0 | DD61: =0/172.5 -> 0 | DE61: =0/127.5 -> 0 | DF61: =0/127.5 -> 0 | DG61: =0/127.5 -> 0 | DH61: =0/127.5 -> 0 | DI61: =0/127.5 -> 0 | DJ61: =0/172.5 -> 0 | DK61: =0/172.5 -> 0 | DL61: =0/142.5 -> 0 | DM61: =0/142.5 -> 0 | DN61: =0/142.5 -> 0 | DO61: =0/142.5 -> 0 | DP61: =0/142.5 -> 0 | DQ61: =0/172.5 -> 0 | DR61: =0/172.5 -> 0 | DS61: =0/172.5 -> 0
N62: 実績 | O62: =0/127.5 -> 0 | P62: =0/127.5 -> 0 | Q62: =0/127.5 -> 0 | R62: =0/127.5 -> 0 | S62: =0/127.5 -> 0 | T62: =0/127.5 -> 0 | U62: =0/127.5 -> 0 | V62: =0/127.5 -> 0 | ... X62: =0/127.5 -> 0 | Y62: =0/142.5 -> 0 | Z62: =0/142.5 -> 0 | AA62: =0/142.5 -> 0 | AB62: =0/142.5 -> 0 | AC62: =0/142.5 -> 0 | AD62: =0/142.5 -> 0 | AE62: =0/165 -> 0 | AG62: =0/165 -> 0 | AH62: =0/165 -> 0 | AI62: =0/165 -> 0 | AJ62: =0/165 -> 0 | AK62: =0/165 -> 0 | AL62: =0/165 -> 0 | AM62: =0/165 -> 0 | AN62: =0/165 -> 0 | ... AR62: =0/165 -> 0 | AS62: =0/150 -> 0 | AT62: =0/150 -> 0 | AU62: =0/150 -> 0 | AV62: =0/150 -> 0 | AW62: =0/150 -> 0 | AX62: =0/165 -> 0 | AY62: =0/165 -> 0 | AZ62: =0/165 -> 0 | BA62: =0/165 -> 0 | BB62: =0/165 -> 0 | BC62: =(0)/157.5 -> 0 | BD62: =(0)/157.5 -> 0 | BE62: =(0)/157.5 -> 0 | BF62: =(0)/157.5 -> 0 | BG62: =(0)/157.5 -> 0 | BH62: =(0)/157.5 -> 0 | BI62: =(0)/157.5 -> 0 | BJ62: =(0)/157.5 -> 0 | ... BL62: =(0)/157.5 -> 0 | BM62: =(1+5)/165 -> 0.036363636 | BN62: =(0)/165 -> 0 | BO62: =(0)/165 -> 0 | BP62: =(0)/165 -> 0 | BQ62: =(6+10)/165 -> 0.096969697 | BR62: =(0)/165 -> 0 | BS62: =(0)/165 -> 0 | BT62: =(0)/165 -> 0 | BU62: =(0+3)/165 -> 0.018181818 | BV62: =(12+9)/165 -> 0.12727273 | BW62: =(0)/150 -> 0 | BX62: =(0)/150 -> 0 | BY62: =(0)/150 -> 0 | BZ62: =(0)/150 -> 0 | CA62: =(0)/150 -> 0 | CB62: =(0)/150 -> 0 | CC62: =(0)/150 -> 0 | CD62: =(0)/150 -> 0 | ... CF62: =(0)/150 -> 0 | CG62: =(0)/135 -> 0 | CH62: =(0)/135 -> 0 | CI62: =(0)/135 -> 0 | CJ62: =(0)/135 -> 0 | CK62: =(0)/135 -> 0 | CL62: =(0)/135 -> 0 | CM62: =(0)/135 -> 0 | CN62: =(0)/135 -> 0 | ... CW62: =(0)/135 -> 0 | CX62: =0/157.5 -> 0 | CY62: =0/157.5 -> 0 | CZ62: =0/157.5 -> 0 | DA62: =0/157.5 -> 0 | DB62: =0/157.5 -> 0 | DC62: =0/172.5 -> 0 | DD62: =0/172.5 -> 0 | DE62: =0/127.5 -> 0 | DF62: =0/127.5 -> 0 | DG62: =0/127.5 -> 0 | DH62: =0/127.5 -> 0 | DI62: =0/127.5 -> 0 | DJ62: =0/172.5 -> 0 | DK62: =0/172.5 -> 0 | DL62: =0/142.5 -> 0 | DM62: =0/142.5 -> 0 | DN62: =0/142.5 -> 0 | DO62: =0/142.5 -> 0 | DP62: =0/142.5 -> 0 | DQ62: =0/172.5 -> 0 | DR62: =0/172.5 -> 0 | DS62: =0/172.5 -> 0
